Workbook

Sheet Overview
A1: Balanced Questionnaire Control Panel
A2: Formula-driven composition and quality gates for 500 valid, scoreable, override-free questions.
A4: Selected questions | D4: Mandatory named-case | G4: Selected overrides | J4: Scoreable questions
A5: =COUNT('Selection Ledger'!$A$4:$A$503) -> 500 | D5: =COUNTIF('Selection Ledger'!$L$4:$L$503,"Yes") -> 186 | G5: =COUNTIF('Selection Ledger'!$N$4:$N$503,"*override:*") -> 0 | J5: =COUNTIF('Selection Ledger'!$AB$4:$AB$503,"Yes") -> 500
A8: The three official annulments were excluded and replaced by deterministic valid questions from Aragón 2020, Castilla-La Mancha 2022, and Castilla y León 2022. Four image-linked Andalucía questions were then replaced within the same exam/type quota cells with self-contained alternatives. All 500 selected questions are scoreable and require no separate image.
A10: Region | B10: Final target | C10: Actual | D10: Mandatory | E10: Supplemental | F10: Variance | H10: Primary type | I10: Actual | J10: Share
A11: Andalucía | B11: 34 | C11: =COUNTIF('Selection Ledger'!$D$4:$D$503,A11) -> 34 | D11: =COUNTIFS('Selection Ledger'!$D$4:$D$503,A11,'Selection Ledger'!$L$4:$L$503,"Yes") -> 0 | E11: =C11-D11 -> 34 | F11: =C11-B11 -> 0 | H11: Named clinical-case section | I11: =COUNTIF('Selection Ledger'!$I$4:$I$503,H11) -> 186 | J11: =I11/$A$5 -> 0.372
A12: Aragón | B12: 34 | C12: =COUNTIF('Selection Ledger'!$D$4:$D$503,A12) -> 34 | D12: =COUNTIFS('Selection Ledger'!$D$4:$D$503,A12,'Selection Ledger'!$L$4:$L$503,"Yes") -> 0 | E12: =C12-D12 -> 34 | F12: =C12-B12 -> 0 | H12: Standard/main | I12: =COUNTIF('Selection Ledger'!$I$4:$I$503,H12) -> 164 | J12: =I12/$A$5 -> 0.328
A13: Castilla y León | B13: 34 | C13: =COUNTIF('Selection Ledger'!$D$4:$D$503,A13) -> 34 | D13: =COUNTIFS('Selection Ledger'!$D$4:$D$503,A13,'Selection Ledger'!$L$4:$L$503,"Yes") -> 0 | E13: =C13-D13 -> 34 | F13: =C13-B13 -> 0 | H13: Other structured types | I13: =COUNTIF('Selection Ledger'!$I$4:$I$503,H13) -> 150 | J13: =I13/$A$5 -> 0.3
A14: Castilla-La Mancha | B14: 34 | C14: =COUNTIF('Selection Ledger'!$D$4:$D$503,A14) -> 34 | D14: =COUNTIFS('Selection Ledger'!$D$4:$D$503,A14,'Selection Ledger'!$L$4:$L$503,"Yes") -> 0 | E14: =C14-D14 -> 34 | F14: =C14-B14 -> 0
A15: Comunidad de Madrid | B15: 33 | C15: =COUNTIF('Selection Ledger'!$D$4:$D$503,A15) -> 33 | D15: =COUNTIFS('Selection Ledger'!$D$4:$D$503,A15,'Selection Ledger'!$L$4:$L$503,"Yes") -> 0 | E15: =C15-D15 -> 33 | F15: =C15-B15 -> 0
A16: Comunitat Valenciana | B16: 33 | C16: =COUNTIF('Selection Ledger'!$D$4:$D$503,A16) -> 33 | D16: =COUNTIFS('Selection Ledger'!$D$4:$D$503,A16,'Selection Ledger'!$L$4:$L$503,"Yes") -> 0 | E16: =C16-D16 -> 33 | F16: =C16-B16 -> 0 | H16: Formal question type | I16: Actual | J16: Share
A17: Galicia | B17: 33 | C17: =COUNTIF('Selection Ledger'!$D$4:$D$503,A17) -> 33 | D17: =COUNTIFS('Selection Ledger'!$D$4:$D$503,A17,'Selection Ledger'!$L$4:$L$503,"Yes") -> 0 | E17: =C17-D17 -> 33 | F17: =C17-B17 -> 0 | H17: Named clinical-case section | I17: =COUNTIF('Selection Ledger'!$J$4:$J$503,H17) -> 186 | J17: =I17/$A$5 -> 0.372
A18: Illes Balears | B18: 165 | C18: =COUNTIF('Selection Ledger'!$D$4:$D$503,A18) -> 165 | D18: =COUNTIFS('Selection Ledger'!$D$4:$D$503,A18,'Selection Ledger'!$L$4:$L$503,"Yes") -> 165 | E18: =C18-D18 -> 0 | F18: =C18-B18 -> 0 | H18: Standard/main | I18: =COUNTIF('Selection Ledger'!$J$4:$J$503,H18) -> 164 | J18: =I18/$A$5 -> 0.328
A19: La Rioja | B19: 33 | C19: =COUNTIF('Selection Ledger'!$D$4:$D$503,A19) -> 33 | D19: =COUNTIFS('Selection Ledger'!$D$4:$D$503,A19,'Selection Ledger'!$L$4:$L$503,"Yes") -> 0 | E19: =C19-D19 -> 33 | F19: =C19-B19 -> 0 | H19: Non-case reserve | I19: =COUNTIF('Selection Ledger'!$J$4:$J$503,H19) -> 103 | J19: =I19/$A$5 -> 0.206
A20: Navarra | B20: 34 | C20: =COUNTIF('Selection Ledger'!$D$4:$D$503,A20) -> 34 | D20: =COUNTIFS('Selection Ledger'!$D$4:$D$503,A20,'Selection Ledger'!$L$4:$L$503,"Yes") -> 21 | E20: =C20-D20 -> 13 | F20: =C20-B20 -> 0 | H20: Theoretical | I20: =COUNTIF('Selection Ledger'!$J$4:$J$503,H20) -> 17 | J20: =I20/$A$5 -> 0.034
A21: Región de Murcia | B21: 33 | C21: =COUNTIF('Selection Ledger'!$D$4:$D$503,A21) -> 33 | D21: =COUNTIFS('Selection Ledger'!$D$4:$D$503,A21,'Selection Ledger'!$L$4:$L$503,"Yes") -> 0 | E21: =C21-D21 -> 33 | F21: =C21-B21 -> 0 | H21: Practical | I21: =COUNTIF('Selection Ledger'!$J$4:$J$503,H21) -> 17 | J21: =I21/$A$5 -> 0.034
H22: Mixed theory–practical | I22: =COUNTIF('Selection Ledger'!$J$4:$J$503,H22) -> 13 | J22: =I22/$A$5 -> 0.026
A25: Quality gate | B25: Observed | C25: Expected | D25: Status
A26: Selected total | B26: =A5 -> 500 | C26: 500 | D26: =IF(B26=C26,"PASS","FAIL") -> PASS
A27: Override-tagged selected | B27: =COUNTIF('Selection Ledger'!$N$4:$N$503,"*override:*") -> 0 | C27: 0 | D27: =IF(B27=C27,"PASS","FAIL") -> PASS
A28: Declared nullified selected | B28: =COUNTIF('Selection Ledger'!$N$4:$N$503,"*nullified*") -> 0 | C28: 0 | D28: =IF(B28=C28,"PASS","FAIL") -> PASS
A29: Blank answer-key cells | B29: =COUNTBLANK('Answer Key'!$B$5:$B$504) -> 0 | C29: 0 | D29: =IF(B29=C29,"PASS","FAIL") -> PASS
A30: Duplicate source keys | B30: =SUMPRODUCT(--(COUNTIF('Selection Ledger'!$C$4:$C$503,'Selection Ledger'!$C$4:$C$503)>1)) -> 0 | C30: 0 | D30: =IF(B30=C30,"PASS","FAIL") -> PASS
A31: Answer-letter mismatches | B31: =SUMPRODUCT(--(UPPER('Answer Key'!$B$5:$B$504)<>UPPER('Selection Ledger'!$P$4:$P$503))) -> 0 | C31: 0 | D31: =IF(B31=C31,"PASS","FAIL") -> PASS
A32: Named-case rows missing context | B32: =COUNTIFS('Selection Ledger'!$I$4:$I$503,"Named clinical-case section",'Selection Ledger'!$R$4:$R$503,"") -> 0 | C32: 0 | D32: =IF(B32=C32,"PASS","FAIL") -> PASS

Sheet Questionnaire
A1: Balanced Digestive-System Questionnaire — 500 Questions
A2: Print-readable question blocks. Answers are separated; every required context is inline and no selected item needs a separate image.
A3: ITEM 1 · Illes Balears 2022 · illes-balears/2022 / Q1 · Named clinical-case section
A4: CLINICAL CONTEXT [BASE CLINICAL CONTEXT: illes-balears-2022-base-caso-1] Paciente de 57 años, sin antecedentes personales ni familiares de cáncer de colon ni de cáncer en otras localizaciones, fumador de 22 cigarrillos al día, con hábitos de vida sedentarios, enolismo de 60 gr/día, obesidad con un índice de masa corporal de 37 y una dieta rica en carnes rojas y procesadas.
A5: Señale la respuesta correcta en relación con el cáncer de colon:
A6: A. Es el tipo de cáncer con más incidencia en España. | E6: B. Su incidencia está aumentando en los últimos años.
A7: C. En la población de menos de 50 años su incidencia está bajando claramente. | E7: D. Las respuestas a) y b) son correctas.
A8: Context IDs: illes-balears-2022-base-caso-1 | Source exam PDF page: 3
A10: ITEM 2 · Illes Balears 2022 · illes-balears/2022 / Q2 · Named clinical-case section
A11: CLINICAL CONTEXT CONTINUES THE ACTIVE CONTEXT: illes-balears-2022-base-caso-1
A12: Señale la respuesta falsa en relación con los factores de riesgo del cáncer colorrectal:
A13: A. El consumo de tabaco incrementa el riesgo de cáncer de colon. | E13: B. El consumo de alcohol incrementa el riesgo de cáncer de colon.
A14: C. La obesidad no ha mostrado ser un factor de riesgo para el desarrollo del cáncer de colon. | E14: D. El ejercicio físico regular es un factor que reduce el riesgo de cáncer de colon.
A15: Context IDs: illes-balears-2022-base-caso-1 | Source exam PDF page: 3
A17: ITEM 3 · Illes Balears 2022 · illes-balears/2022 / Q3 · Named clinical-case section
A18: CLINICAL CONTEXT CONTINUES THE ACTIVE CONTEXT: illes-balears-2022-base-caso-1
A19: Señale la respuesta correcta en relación con la edad y el cáncer de colon:
A20: A. El cáncer de colon incrementa claramente su incidencia a partir de los 50. | E20: B. El cáncer de colon presenta la misma incidencia en cualquier edad.
A21: C. La edad no es un factor de riesgo determinante en el desarrollo del cáncer de colon. | E21: D. La edad es el único factor de riesgo determinante para el desarrollo de un cáncer colorrectal y no existen otros factores moduladores significativos.
A22: Context IDs: illes-balears-2022-base-caso-1 | Source exam PDF page: 3
A24: ITEM 4 · Illes Balears 2022 · illes-balears/2022 / Q4 · Named clinical-case section
A25: CLINICAL CONTEXT CONTINUES THE ACTIVE CONTEXT: illes-balears-2022-base-caso-1
A26: Señale la respuesta correcta en relación con el cáncer colorrectal (CCR):
A27: A. La dieta rica en carnes rojas y procesadas disminuye el riesgo de CCR. | E27: B. La dieta rica en frutas y vegetales disminuye el riesgo de CCR.
A28: C. La dieta rica en grasas y la obesidad disminuyen el riesgo de CCR. | E28: D. No se debe recomendar retirar el consumo de tabaco y de alcohol para prevenir el CCR.
A29: Context IDs: illes-balears-2022-base-caso-1 | Source exam PDF page: 4
A31: ITEM 5 · Illes Balears 2022 · illes-balears/2022 / Q5 · Named clinical-case section
A32: CLINICAL CONTEXT CONTINUES THE ACTIVE CONTEXT: illes-balears-2022-base-caso-1
A33: El paciente descrito inicialmente no presenta ningún tipo de sintomatología. Señale la respuesta correcta en relación con el programa de cribado del cáncer de colon:
A34: A. No tiene criterios para participar ya que solo se incluyen los pacientes de entre 60 y 75 años. | E34: B. Cumple criterios para ser incluido en el programa de cribado del CCR.
A35: C. La ausencia de antecedentes familiares es un criterio de exclusión del programa de cribado del CCR. | E35: D. La ausencia de síntomas es un criterio de exclusión del programa de cribado del CCR.
A36: Context IDs: illes-balears-2022-base-caso-1 | Source exam PDF page: 4
A38: ITEM 6 · Illes Balears 2022 · illes-balears/2022 / Q6 · Named clinical-case section
A39: CLINICAL CONTEXT CONTINUES THE ACTIVE CONTEXT: illes-balears-2022-base-caso-1
A40: Una vez incluido en el programa de cribado se hace la determinación de sangre oculta en heces (SOH) inmunológica cuantitativa, que resulta positiva. Señale la respuesta correcta:
A41: A. No se debe ofrecer ningún tipo de prueba complementaria. | E41: B. Se debe ofrecer al paciente hacer una segunda determinación de SOH.
A42: C. Se debe ofrecer al paciente hacer una colonoscopia. | E42: D. Si no hay síntomas no es necesario hacer una colonoscopia.
A43: Context IDs: illes-balears-2022-base-caso-1 | Source exam PDF page: 4
A45: ITEM 7 · Illes Balears 2022 · illes-balears/2022 / Q7 · Named clinical-case section
A46: CLINICAL CONTEXT CONTINUES THE ACTIVE CONTEXT: illes-balears-2022-base-caso-1
A47: Señale la respuesta falsa en relación con la calidad de las endoscopias del programa de cribado:
A48: A. Deben ser procedimientos hechos por endoscopistas de alta cualificación para poder detectar y tratar las lesiones. | E48: B. Se deben hacer en gabinetes con programación específica separada de las endoscopias de rutina.
A49: C. Se debe disponer de equipamientos de la máxima calidad para optimizar la detección de las lesiones. | E49: D. Las endoscopias del programa de cribado pueden hacerse en cualquier gabinete y por cualquier tipo de endoscopista independientemente de su tasa de detección de adenomas.
A50: Context IDs: illes-balears-2022-base-caso-1 | Source exam PDF page: 5
A52: ITEM 8 · Illes Balears 2022 · illes-balears/2022 / Q8 · Named clinical-case section
A53: CLINICAL CONTEXT CONTINUES THE ACTIVE CONTEXT: illes-balears-2022-base-caso-1
A54: La colonoscopia es normal hasta el ciego, pero en la estratificación del grado de limpieza, según la escala de Boston, el resultado ha sido el siguiente: Colon derecho: 1 Colon transverso: 1 Colon izquierdo: 1 Colon total: 3 puntos. Señale la respuesta correcta:
A55: A. Se debe repetir la colonoscopia para conseguir una puntuación total de 6 puntos (o superior) con un mínimo de dos puntos en cada tramo. | E55: B. Se debe repetir la colonoscopia para conseguir una puntuación total de 6 puntos (o superior), independientemente de la puntuación de cada tramo.
A56: C. No se debe repetir la colonoscopia, este grado de limpieza del colon es adecuado. | E56: D. El grado de limpieza del colon no es un factor determinante para la tasa de detección de adenomas ni para evitar la neoplasia de intervalo.
A57: Context IDs: illes-balears-2022-base-caso-1 | Source exam PDF page: 5
A59: ITEM 9 · Illes Balears 2022 · illes-balears/2022 / Q9 · Named clinical-case section
A60: CLINICAL CONTEXT CONTINUES THE ACTIVE CONTEXT: illes-balears-2022-base-caso-1
A61: Se repite la colonoscopia y se objetiva la presencia de un pólipo único pediculado de 15 mm a 30 cm del margen anal. La colonoscopia es completa hasta el ciego, con 9 puntos en la escala de Boston. Se hace una polipectomía con una resección completa del pólipo con su pedículo. En el estudio histológico se describe un adenoma tubulovelloso con displasia de alto grado focal estrictamente superficial, con márgenes de resección libres de tejido adenomatoso con margen de resección amplio en el pedículo. Señale la respuesta correcta:
A62: A. Se requiere un tratamiento quirúrgico complementario para asegurar la curación de la lesión. | E62: B. La lesión ha quedado curada tras la resección endoscópica.
A63: C. Se debe repetir la colonoscopia de inmediato para revisar la escara de la polipectomía dado el riesgo alto de lesión residual. | E63: D. Se debe hacer una TC abdominal complementaria como estudio de la extensión de la lesión.
A64: Context IDs: illes-balears-2022-base-caso-1 | Source exam PDF page: 6
A66: ITEM 10 · Illes Balears 2022 · illes-balears/2022 / Q10 · Named clinical-case section
A67: CLINICAL CONTEXT CONTINUES THE ACTIVE CONTEXT: illes-balears-2022-base-caso-1
A68: Señale la respuesta correcta según las últimas guías clínicas en cuanto al control endoscópico de la lesión descrita:
A69: A. Se requiere una revisión endoscópica en 6 meses. | E69: B. No requiere una revisión endoscópica ya que se trata de una lesión de riesgo bajo.
A70: C. Este paciente será susceptible de una colonoscopia anual a partir de ahora. | E70: D. Una revisión endoscópica dentro de tres años es suficiente.
A71: Context IDs: illes-balears-2022-base-caso-1 | Source exam PDF page: 6
A73: ITEM 11 · Illes Balears 2022 · illes-balears/2022 / Q11 · Named clinical-case section
A74: CLINICAL CONTEXT CONTINUES THE ACTIVE CONTEXT: illes-balears-2022-base-caso-1
A75: Este paciente tiene un hermano de 52 años, asintomático. En la familia no existen otros antecedentes de CCR. ¿Qué recomendación debemos dar al hermano en cuanto a prevención del CCR?
A76: A. Es susceptible de endoscopia de forma inmediata. | E76: B. No requiere ningún tipo de procedimiento dada la edad y la ausencia de clínica asociada.
A77: C. En este caso se recomienda el control por medio de una SOH bianual. | E77: D. Se le debe ofrecer una colonoscopia anual como herramienta de prevención más eficaz a nivel de coste.
A78: Context IDs: illes-balears-2022-base-caso-1 | Source exam PDF page: 6
A80: ITEM 12 · Illes Balears 2022 · illes-balears/2022 / Q12 · Named clinical-case section
A81: CLINICAL CONTEXT CONTINUES THE ACTIVE CONTEXT: illes-balears-2022-base-caso-1
A82: El paciente deja de acudir a les consultas externas. Regresa al cabo de siete años con un cuadro de rectorragias asociadas a una pérdida de ocho quilos. Señale la respuesta correcta:
A83: A. No requiere una colonoscopia porque tiene una de hace siete años. | E83: B. Requiere colonoscopia por la clínica que presenta para descartar un CCR.
A84: C. En este caso basta con un análisis de SOH. | E84: D. La exploración inicial debe ser una ecografía abdominal.
A85: Context IDs: illes-balears-2022-base-caso-1 | Source exam PDF page: 7
A87: ITEM 13 · Illes Balears 2022 · illes-balears/2022 / Q14 · Named clinical-case section
A88: CLINICAL CONTEXT CONTINUES THE ACTIVE CONTEXT: illes-balears-2022-base-caso-1
A89: El estudio de extensión muestra ausencia de lesiones a distancia en el pulmón o el hígado. También muestra ausencia de adenopatías evidentes. Se objetiva una lesión neoformativa con una imagen sugestiva de infiltración hasta la submucosa, pero sin contactar con la muscular propia. Señale la respuesta correcta respecto al estadiaje:
A90: A. Estadio T3N1M1. | E90: B. Estadio T2N0M0.
A91: C. Estadio T1N0M0. | E91: D. Estadio T2N1M0.
A92: Context IDs: illes-balears-2022-base-caso-1 | Source exam PDF page: 7
A94: ITEM 14 · Illes Balears 2022 · illes-balears/2022 / Q15 · Named clinical-case section
A95: CLINICAL CONTEXT CONTINUES THE ACTIVE CONTEXT: illes-balears-2022-base-caso-1
A96: Señale el tratamiento correcto dado el estadio y la ubicación de la lesión:
A97: A. Requiere tratamiento quirúrgico mediante resección abdominoperineal. | E97: B. La única opción válida es hacer una mucosectomía convencional en fragmentos.
A98: C. Es susceptible de una resección en bloque mediante una disección endoscópica submucosa. | E98: D. Requiere un tratamiento neoadyuvante mediante quimioterapia y radioterapia antes del tratamiento.
A99: Context IDs: illes-balears-2022-base-caso-1 | Source exam PDF page: 8
A101: ITEM 15 · Illes Balears 2022 · illes-balears/2022 / Q16 · Named clinical-case section
A102: CLINICAL CONTEXT CONTINUES THE ACTIVE CONTEXT: illes-balears-2022-base-caso-1
A103: El bloque de la anatomía patológica muestra la presencia de un pólipo resecado en bloque con un foco central de adenocarcinoma de 8 mm con infiltración hasta la submucosa sm1, pero sin contactar con la muscular propia, con márgenes de resección libres de enfermedad. Señale la respuesta correcta de acuerdo con el estudio de extensión previo a la resección:
A104: A. La resección endoscópica ha sido curativa. | E104: B. Se requiere un tratamiento quirúrgico complementario para completar el tratamlento.
A105: C. Se requiere quimioterapia y radioterapia adyuvantes. | E105: D. La resección endoscópica no muestra criterios para considerar que haya sido curativa.
A106: Context IDs: illes-balears-2022-base-caso-1 | Source exam PDF page: 8
A108: ITEM 16 · Illes Balears 2022 · illes-balears/2022 / Q17 · Named clinical-case section
A109: CLINICAL CONTEXT CONTINUES THE ACTIVE CONTEXT: illes-balears-2022-base-caso-1
A110: Señale la respuesta correcta en cuanto al seguimiento endoscópico de este paciente:
A111: A. No requiere una revisión endoscópica. | E111: B. Requiere únicamente que se le hagan rectosigmoidoscopias de control.
A112: C. Requiere un control endoscópico de forma precoz, que es aceptable a los seis meses. | E112: D. Requiere un control endoscópico a los tres años.
A113: Context IDs: illes-balears-2022-base-caso-1 | Source exam PDF page: 8
A115: ITEM 17 · Illes Balears 2022 · illes-balears/2022 / Q18 · Named clinical-case section
A116: CLINICAL CONTEXT CONTINUES THE ACTIVE CONTEXT: illes-balears-2022-base-caso-1
...

Sheet Question Data
A1: Question Data — Electronic Trace View
A2: Filterable source-aligned data for all 500 items. Use the Questionnaire sheet for the complete, print-readable question blocks.
A4: Item | B4: Region | C4: Year | D4: Source exam | E4: Exam part | F4: Source Q | G4: Primary type | H4: Formal question type | I4: Clinical context | J4: Question | K4: Option A | L4: Option B | M4: Option C | N4: Option D | O4: Context IDs | P4: Visual ID | Q4: PDF page
A5: 1 | B5: Illes Balears | C5: 2022 | D5: illes-balears/2022 | E5: caso-1 | F5: 1 | G5: Named clinical-case section | H5: Named clinical-case section | I5: [BASE CLINICAL CONTEXT: illes-balears-2022-base-caso-1] Paciente de 57 años, sin antecedentes personales ni familiares de cáncer de colon ni de cáncer en otras localizaciones, fumador de 22 cigarrillos al día, con hábitos de vida sedentarios, enolismo de 60 gr/día, obesidad con un índice de masa corporal de 37 y una dieta rica en carnes rojas y procesadas. | J5: Señale la respuesta correcta en relación con el cáncer de colon: | K5: Es el tipo de cáncer con más incidencia en España. | L5: Su incidencia está aumentando en los últimos años. | M5: En la población de menos de 50 años su incidencia está bajando claramente. | N5: Las respuestas a) y b) son correctas. | O5: illes-balears-2022-base-caso-1 | Q5: 3
A6: 2 | B6: Illes Balears | C6: 2022 | D6: illes-balears/2022 | E6: caso-1 | F6: 2 | G6: Named clinical-case section | H6: Named clinical-case section | I6: CONTINUES THE ACTIVE CONTEXT: illes-balears-2022-base-caso-1 | J6: Señale la respuesta falsa en relación con los factores de riesgo del cáncer colorrectal: | K6: El consumo de tabaco incrementa el riesgo de cáncer de colon. | L6: El consumo de alcohol incrementa el riesgo de cáncer de colon. | M6: La obesidad no ha mostrado ser un factor de riesgo para el desarrollo del cáncer de colon. | N6: El ejercicio físico regular es un factor que reduce el riesgo de cáncer de colon. | O6: illes-balears-2022-base-caso-1 | Q6: 3
A7: 3 | B7: Illes Balears | C7: 2022 | D7: illes-balears/2022 | E7: caso-1 | F7: 3 | G7: Named clinical-case section | H7: Named clinical-case section | I7: CONTINUES THE ACTIVE CONTEXT: illes-balears-2022-base-caso-1 | J7: Señale la respuesta correcta en relación con la edad y el cáncer de colon: | K7: El cáncer de colon incrementa claramente su incidencia a partir de los 50. | L7: El cáncer de colon presenta la misma incidencia en cualquier edad. | M7: La edad no es un factor de riesgo determinante en el desarrollo del cáncer de colon. | N7: La edad es el único factor de riesgo determinante para el desarrollo de un cáncer colorrectal y no existen otros factores moduladores significativos. | O7: illes-balears-2022-base-caso-1 | Q7: 3
A8: 4 | B8: Illes Balears | C8: 2022 | D8: illes-balears/2022 | E8: caso-1 | F8: 4 | G8: Named clinical-case section | H8: Named clinical-case section | I8: CONTINUES THE ACTIVE CONTEXT: illes-balears-2022-base-caso-1 | J8: Señale la respuesta correcta en relación con el cáncer colorrectal (CCR): | K8: La dieta rica en carnes rojas y procesadas disminuye el riesgo de CCR. | L8: La dieta rica en frutas y vegetales disminuye el riesgo de CCR. | M8: La dieta rica en grasas y la obesidad disminuyen el riesgo de CCR. | N8: No se debe recomendar retirar el consumo de tabaco y de alcohol para prevenir el CCR. | O8: illes-balears-2022-base-caso-1 | Q8: 4
A9: 5 | B9: Illes Balears | C9: 2022 | D9: illes-balears/2022 | E9: caso-1 | F9: 5 | G9: Named clinical-case section | H9: Named clinical-case section | I9: CONTINUES THE ACTIVE CONTEXT: illes-balears-2022-base-caso-1 | J9: El paciente descrito inicialmente no presenta ningún tipo de sintomatología. Señale la respuesta correcta en relación con el programa de cribado del cáncer de colon: | K9: No tiene criterios para participar ya que solo se incluyen los pacientes de entre 60 y 75 años. | L9: Cumple criterios para ser incluido en el programa de cribado del CCR. | M9: La ausencia de antecedentes familiares es un criterio de exclusión del programa de cribado del CCR. | N9: La ausencia de síntomas es un criterio de exclusión del programa de cribado del CCR. | O9: illes-balears-2022-base-caso-1 | Q9: 4
A10: 6 | B10: Illes Balears | C10: 2022 | D10: illes-balears/2022 | E10: caso-1 | F10: 6 | G10: Named clinical-case section | H10: Named clinical-case section | I10: CONTINUES THE ACTIVE CONTEXT: illes-balears-2022-base-caso-1 | J10: Una vez incluido en el programa de cribado se hace la determinación de sangre oculta en heces (SOH) inmunológica cuantitativa, que resulta positiva. Señale la respuesta correcta: | K10: No se debe ofrecer ningún tipo de prueba complementaria. | L10: Se debe ofrecer al paciente hacer una segunda determinación de SOH. | M10: Se debe ofrecer al paciente hacer una colonoscopia. | N10: Si no hay síntomas no es necesario hacer una colonoscopia. | O10: illes-balears-2022-base-caso-1 | Q10: 4
A11: 7 | B11: Illes Balears | C11: 2022 | D11: illes-balears/2022 | E11: caso-1 | F11: 7 | G11: Named clinical-case section | H11: Named clinical-case section | I11: CONTINUES THE ACTIVE CONTEXT: illes-balears-2022-base-caso-1 | J11: Señale la respuesta falsa en relación con la calidad de las endoscopias del programa de cribado: | K11: Deben ser procedimientos hechos por endoscopistas de alta cualificación para poder detectar y tratar las lesiones. | L11: Se deben hacer en gabinetes con programación específica separada de las endoscopias de rutina. | M11: Se debe disponer de equipamientos de la máxima calidad para optimizar la detección de las lesiones. | N11: Las endoscopias del programa de cribado pueden hacerse en cualquier gabinete y por cualquier tipo de endoscopista independientemente de su tasa de detección de adenomas. | O11: illes-balears-2022-base-caso-1 | Q11: 5
A12: 8 | B12: Illes Balears | C12: 2022 | D12: illes-balears/2022 | E12: caso-1 | F12: 8 | G12: Named clinical-case section | H12: Named clinical-case section | I12: CONTINUES THE ACTIVE CONTEXT: illes-balears-2022-base-caso-1 | J12: La colonoscopia es normal hasta el ciego, pero en la estratificación del grado de limpieza, según la escala de Boston, el resultado ha sido el siguiente: Colon derecho: 1 Colon transverso: 1 Colon izquierdo: 1 Colon total: 3 puntos. Señale la respuesta correcta: | K12: Se debe repetir la colonoscopia para conseguir una puntuación total de 6 puntos (o superior) con un mínimo de dos puntos en cada tramo. | L12: Se debe repetir la colonoscopia para conseguir una puntuación total de 6 puntos (o superior), independientemente de la puntuación de cada tramo. | M12: No se debe repetir la colonoscopia, este grado de limpieza del colon es adecuado. | N12: El grado de limpieza del colon no es un factor determinante para la tasa de detección de adenomas ni para evitar la neoplasia de intervalo. | O12: illes-balears-2022-base-caso-1 | Q12: 5
A13: 9 | B13: Illes Balears | C13: 2022 | D13: illes-balears/2022 | E13: caso-1 | F13: 9 | G13: Named clinical-case section | H13: Named clinical-case section | I13: CONTINUES THE ACTIVE CONTEXT: illes-balears-2022-base-caso-1 | J13: Se repite la colonoscopia y se objetiva la presencia de un pólipo único pediculado de 15 mm a 30 cm del margen anal. La colonoscopia es completa hasta el ciego, con 9 puntos en la escala de Boston. Se hace una polipectomía con una resección completa del pólipo con su pedículo. En el estudio histológico se describe un adenoma tubulovelloso con displasia de alto grado focal estrictamente superficial, con márgenes de resección libres de tejido adenomatoso con margen de resección amplio en el pedículo. Señale la respuesta correcta: | K13: Se requiere un tratamiento quirúrgico complementario para asegurar la curación de la lesión. | L13: La lesión ha quedado curada tras la resección endoscópica. | M13: Se debe repetir la colonoscopia de inmediato para revisar la escara de la polipectomía dado el riesgo alto de lesión residual. | N13: Se debe hacer una TC abdominal complementaria como estudio de la extensión de la lesión. | O13: illes-balears-2022-base-caso-1 | Q13: 6
A14: 10 | B14: Illes Balears | C14: 2022 | D14: illes-balears/2022 | E14: caso-1 | F14: 10 | G14: Named clinical-case section | H14: Named clinical-case section | I14: CONTINUES THE ACTIVE CONTEXT: illes-balears-2022-base-caso-1 | J14: Señale la respuesta correcta según las últimas guías clínicas en cuanto al control endoscópico de la lesión descrita: | K14: Se requiere una revisión endoscópica en 6 meses. | L14: No requiere una revisión endoscópica ya que se trata de una lesión de riesgo bajo. | M14: Este paciente será susceptible de una colonoscopia anual a partir de ahora. | N14: Una revisión endoscópica dentro de tres años es suficiente. | O14: illes-balears-2022-base-caso-1 | Q14: 6
A15: 11 | B15: Illes Balears | C15: 2022 | D15: illes-balears/2022 | E15: caso-1 | F15: 11 | G15: Named clinical-case section | H15: Named clinical-case section | I15: CONTINUES THE ACTIVE CONTEXT: illes-balears-2022-base-caso-1 | J15: Este paciente tiene un hermano de 52 años, asintomático. En la familia no existen otros antecedentes de CCR. ¿Qué recomendación debemos dar al hermano en cuanto a prevención del CCR? | K15: Es susceptible de endoscopia de forma inmediata. | L15: No requiere ningún tipo de procedimiento dada la edad y la ausencia de clínica asociada. | M15: En este caso se recomienda el control por medio de una SOH bianual. | N15: Se le debe ofrecer una colonoscopia anual como herramienta de prevención más eficaz a nivel de coste. | O15: illes-balears-2022-base-caso-1 | Q15: 6
A16: 12 | B16: Illes Balears | C16: 2022 | D16: illes-balears/2022 | E16: caso-1 | F16: 12 | G16: Named clinical-case section | H16: Named clinical-case section | I16: CONTINUES THE ACTIVE CONTEXT: illes-balears-2022-base-caso-1 | J16: El paciente deja de acudir a les consultas externas. Regresa al cabo de siete años con un cuadro de rectorragias asociadas a una pérdida de ocho quilos. Señale la respuesta correcta: | K16: No requiere una colonoscopia porque tiene una de hace siete años. | L16: Requiere colonoscopia por la clínica que presenta para descartar un CCR. | M16: En este caso basta con un análisis de SOH. | N16: La exploración inicial debe ser una ecografía abdominal. | O16: illes-balears-2022-base-caso-1 | Q16: 7
... A190: 186 | B190: Navarra | C190: 2022 | D190: navarra/2022 | E190: reserva-casos-clinicos | F190: 111 | G190: Named clinical-case section | H190: Named clinical-case section | I190: [FULL CLINICAL CONTEXT: navarra-2022-case-03] Varón de 65 años con antecedente de cirrosis hepática por VHC genotipo 3 (nunca tratado), sin otras comorbilidades, que ingresa por hematemesis. Se realiza gastroscopia visualizándose varices esofágicas grandes, una de ellas con sangrado activo y dos de ellas con extensión a curvadura menor gástrica. El paciente no presenta ascitis ni fiebre y desde el punto de vista hemodinámico tiene TA 100/60 mmHg, FC 75lpm, SatO2 94% FiO2 21%. Analítica: Hemoglobina 8,5 g/dL, plaquetas 78 x 109/L, actividad de protrombina 52%. Creatinina 0,98 mg/dL, Sodio 129 mmol/L, bilirrubina total 3,1 mg/dL, albúmina 32 g/L. AST 125 U/L, ALT 101 U/L. Serologías: IgM e IgG VHA negativo, HBsAg negativo, anti-HBs positivo, HBcAc total positivo, VIH negativo. Ecografía abdominal: Hígado con contornos nodulares y aumento de la ecogenicidad hepática con aspecto granular, sugestivo de hepatopatía crónica. No se objetivan lesiones focales. Vena porta de calibre normal con flujo hepatópeto. Esplenomegalia homogénea de 17,5 cm. Circulación colateral en espacio esplenorrenal. No líquido libre intraabdominal | J190: Pregunta de reserva Caso Clínico número 3: A las 72 horas de la gastroscopia inicial el paciente presenta nuevo episodio de hematemesis atribuible a sangrado variceal. Analíticamente destaca hemoglobina de 7,5g/dL, plaquetas 50 x 109/L, INR 2, actividad de protrombina 33%, fibrinógeno 200mg/dL, creatinina 1 mg/dL, bilirrubina total 2,8 mg/dL, ¿cuál de las siguientes actuaciones sería INCORRECTA?: | K190: Segundo intento de hemostasia endoscópica | L190: Trasfusión de 1 gramo de fibrinógeno | M190: Sería candidato a un TIPS de rescate | N190: El resangrado variceal tras un tratamiento endoscópico inicial puede ocurrir en el 10 -20% de los pacientes | O190: navarra-2022-case-03 | Q190: 26
A191: 187 | B191: Comunidad de Madrid | C191: 2021 | D191: comunidad-de-madrid/2021 | E191: main | F191: 48 | G191: Standard/main | H191: Standard/main | J191: ¿A cuál de los siguientes pacientes, con un episodio de hemorragia digestiva baja (HDB), autolimitada, atendido en Urgencias, daría usted el alta y procedería a realizar su estudio y manejo de forma mbulatoria? | K191: Varón, 73 años, sin episodios previos de HDB, tacto rectal con dedil limpio, Fc 63 lpm, TAS 133mm Hg, Hb 16 g/dl. | L191: Mujer, 52 años, HDB hace 8 meses atendida en otro centro, tacto rectal con dedil limpio, Fc 93 lpm, TAS 112mm Hg, Hb 10,3 g/dl. | M191: Varón, 57 años, sin episodios previos de HDB, tacto rectal con restos hemáticos, Fc 85 lpm, TAS 120mm Hg, Hb 11,2 g/dl. | N191: Mujer, 72 años, sin episodios previos, tacto rectal con dedil limpio, 92 lpm, TAS 109 mm Hg, Hb 12,5 g/dl. | Q191: 10
A192: 188 | B192: Castilla y León | C192: 2019 | D192: castilla-y-leon/2019 | E192: reserva-especifica | F192: 160 | G192: Other structured types | H192: Non-case reserve | J192: En una hepatitis aguda, de los síntomas abajo indicados ¿Cuál de ellos aconsejaría el ingreso del/la paciente? | K192: Ascitis | L192: Datos de encefalopatía | M192: Síntomas de hipoglucemia | N192: Todos los anteriores | Q192: 36
A193: 189 | B193: Región de Murcia | C193: 2019 | D193: region-de-murcia/2019 | E193: main | F193: 140 | G193: Standard/main | H193: Standard/main | J193: En relación al tratamiento de la ascitis en el paciente cirrótico, señale la respuesta falsa: | K193: La paracentesis de gran volumen (PGV) se debe realizar conjuntamente con la administración de albumina iv a razón de 80 g por litro extraído. | L193: En PGV de más de 5 litros el uso de expansores plasmáticos distintos a la albúmina no está recomendado. | M193: Los pacientes con un primer episodio de ascitis grado 2 (moderada) deben recibir solo antagonistas de la aldosterona, empezando a dosis de 100 mg/día. | N193: La restricción moderada de la ingesta de sal es un componente importante en el manejo de la ascitis. | Q193: 23
A194: 190 | B194: Comunidad de Madrid | C194: 2021 | D194: comunidad-de-madrid/2021 | E194: main | F194: 112 | G194: Standard/main | H194: Standard/main | J194: Señala cual NO es un efecto secundario de tacrolimus | K194: Insuficiencia renal | L194: Cefalea | M194: Convulsiones | N194: Pancreatitis aguda | Q194: 21
A195: 191 | B195: Galicia | C195: 2016 | D195: galicia/ope-2016 | E195: reserva-especifica | F195: 110 | G195: Other structured types | H195: Non-case reserve | J195: Señale la respuesta correcta en relación con la hepatitis por VHC: | K195: Todo paciente con hepatitis aguda por VHC debe recibir tratamiento antiviral. | L195: El tratamiento con ledipasvir y sofosbuvir durante 4 ó 6 semanas es muy seguro y eficaz en pacientes con hepatitis aguda por VHC con genotipo 1. | M195: El tratamiento de la hepatitis C post trasplante hepático está indicado en todos los pacientes, estando contraindicada la ribavirina. | N195: En pacientes con cirrosis por VHC no existen exámenes no invasivos que permitan descartar con un 90 por ciento de seguridad la existencia de varices esofágicas. | Q195: 26
A196: 192 | B196: Navarra | C196: 2022 | D196: navarra/2022 | E196: teorico-practica | F196: 75 | G196: Other structured types | H196: Mixed theory–practical | J196: Varón de 58 años que acude a urgencias por dolor agudo y constante en hipocondrio derecho, con náuseas, vómitos y fiebre de 38º. A la exploración presente ictericia e hipersensibilidad a la palpación en hipocondrio derecho. Se solicita una ecografía abdominal observando colelitiasis múltiple y dilatación de vía intrahepática sin poder valorar colédoco ni región pancreática por interposición de gas. Se completa con un TC observando litiasis en conducto cístico de 15 mm, dilatación de conducto hepático común y vía biliar intrahepática, estando el colédoco distal normal. ¿Cuál de los siguientes es el diagnóstico MÁS probable? | K196: Colangiocarcinoma tipo Klatskin | L196: Quiste de colédoco | M196: Síndrome de Mirizzi | N196: Colangiocarcinoma proximal | Q196: 16
A197: 193 | B197: Andalucía | C197: 2021 | D197: andalucia/2021-22-libre | E197: cuestionario-practico | F197: 126 | G197: Other structured types | H197: Practical | I197: [Full clinical context: andalucia-2021-22-libre-case-007] Una mujer de 62 años acude para realización de colonoscopia por test de sangre oculta en heces positivo en el contexto del programa de cribado poblacional de cáncer colorrectal de Andalucía. Se encontraba asintomática y no tenía comorbilidades ni antecedentes personales ni familiares de cáncer colorrectal. Se realiza colonoscopia hasta ciego, bajo sedación profunda, con un tiempo de retirada de 18 minutos. Se encontró un pólipo 0-Ip de 14mm en sigma, que se extirpa de forma completa y en bloque, informado por el patólogo como adenoma tubulovelloso con displasia de bajo grado. No se encontraron otras lesiones. La puntuación de la escala de Boston fue 5 (2 en colon izquierdo, 1 en colon transverso y 1 en ciego-colon ascendente). | J197: Realizado árbol genealógico familiar, no hay historia familiar de cáncer y el estudio inmunohistoquímico muestra tinción positiva (expresión) de las cuatro proteínas MMR (MLH1, MSH2, MSH6, PMS2). ¿Cuál sería la actitud preventiva más adecuada a seguir con su hijo de 35 años, siguiendo las recomendaciones más recientes de las guías de práctica clínica europea y española? | K197: Iniciar ya colonoscopias, con una periodicidad cada 10 años. | L197: Participar en el programa de cribado poblacional de cáncer colorrectal de Andalucía cuando se le invite. | M197: Iniciar colonoscopias a partir de los 40 años con una periodicidad cada 5 años. | N197: Iniciar colonoscopias a partir de los 50 años con una periodicidad cada 5 años. | O197: andalucia-2021-22-libre-case-007 | Q197: 33
A198: 194 | B198: Comunitat Valenciana | C198: 2022 | D198: comunitat-valenciana/2022 | E198: main-47-80 | F198: 56 | G198: Standard/main | H198: Standard/main | J198: Paciente con hepatitis crónica B con ALT 35 UI, DNA-VHB 9800 UI y Fibroscan 9,5 Kpa debe tratarse con: | K198: Interferon pegilado indefinido. | L198: Glecaprevir. | M198: Tenofovir indefinido. | N198: No tiene indicación de tratamiento. | Q198: 18
A199: 195 | B199: Aragón | C199: 2020 | D199: aragon/2020 | E199: main | F199: 93 | G199: Standard/main | H199: Standard/main | J199: En la enfermedad perianal (enfermedad de Crohn) si hay dolor intenso, usted sospechará: | K199: Absceso. | L199: Fístula compleja. | M199: Fístula transesfinteriana. | N199: Actividad rectal. | Q199: 18
A200: 196 | B200: Comunidad de Madrid | C200: 2021 | D200: comunidad-de-madrid/2021 | E200: main | F200: 135 | G200: Standard/main | H200: Standard/main | J200: En el contexto de un paciente con colangitis biliar primaria ¿qué hallazgo histológico es característico y se considera diagnóstico cuando se observa en la biopsia hepática? | K200: Cuerpos de Councilman | L200: Infiltrado linfocítico periportal con destrucción de los ductos biliares | M200: Fibrosis en puentes | N200: Granulomas no caseificantes | Q200: 24
A201: 197 | B201: Galicia | C201: 2016 | D201: galicia/ope-2016 | E201: reserva-especifica | F201: 103 | G201: Other structured types | H201: Non-case reserve | J201: ¿En cuál de las siguientes entidades no está recomendado, según las guías EASL, realizar estudios para detectar hemocromatosis? | K201: Diabetes tipo I. | L201: Diabetes tipo II. | M201: Porfiria cutánea tardía. | N201: Condrocalcinosis. | Q201: 24
A202: 198 | B202: Castilla-La Mancha | C202: 2017 | D202: castilla-la-mancha/2017-2018 | E202: reserva-especifica | F202: 102 | G202: Other structured types | H202: Non-case reserve | J202: En los gráficos de cajas (box-plot, box and whisker plot), ¿Qué representa la línea horizontal que está dentro de la caja? | K202: La moda | L202: Cuartil 2 | M202: El rango | N202: Desviación estándar | Q202: 18
A203: 199 | B203: Andalucía | C203: 2021 | D203: andalucia/2021-22-libre | E203: cuestionario-practico | F203: 134 | G203: Other structured types | H203: Practical | I203: [Full clinical context: andalucia-2021-22-libre-case-010] Paciente varón de 72 años, exfumador, con antecedentes de diabetes mellitus tipo 2, hipertensión arterial, hiperuricemia, enfermedad renal crónica y enfermedad pulmonar obstructiva crónica. En los últimos años presenta, además, arteriopatía obliterante crónica grado IV con amputación de falanges distales, enfermedad coronaria con afectación de tres vasos, insuficiencia mitral severa y disfunción del ventrículo izquierdo que precisó de plastia mitral con anillo y doble bypass. Se encontraba en tratamiento con ácido acetilsalicílico, clopidogrel, bisoprolol, furosemida, simvastatina, nitroglicerina, alopurinol, furosemida, omeprazol, bromuro de tiotropio, salmeterol y fluticasona. Acude a urgencias por dolor intestinal de intensidad moderada y rectorragia de 24 horas de evolución. No presentaba urgencia defecatoria ni refería fiebre, náuseas o vómitos. Tampoco recibió nuevos fármacos en los días previos. A su llegada a urgencias presentó tendencia a la hipotensión (tensión arterial 80/50 mmHg) que remontó con sueroterapia. No se constataron signos de hipoperfusión periférica. La exploración abdominal era dolorosa durante la palpación de la fosa ilíaca izquierda, sin datos de irritación peritoneal. Analíticamente destacaba hemoglobina de 9.2 gr/dL, con elevación de reactantes de fase aguda (proteína C reactiva 84 mg/L, leucocitos 16.500/mcL) y de creatinquinasa 994 U/l, siendo el resto normal. | J203: En relación a las pruebas complementarias necesarias en función del diagnóstico inicial, ¿Cuál de estas afirmaciones es falsa?: | K203: Se deben obtener muestras de heces para cultivo, parásitos y toxina de Clostridium difficile. | L203: La tomografía computarizada (TC) es el examen de imagen más útil. | M203: La colonoscopia es la técnica principal para el diagnóstico, siempre que no haya datos de peritonitis. | N203: La leucocitosis en un hallazgo frecuente desde las fases iniciales de la enfermedad. | O203: andalucia-2021-22-libre-case-010 | Q203: 36
A204: 200 | B204: La Rioja | C204: 2021 | D204: la-rioja/2020-2021 | E204: reserva | F204: 109 | G204: Other structured types | H204: Non-case reserve | J204: El tratamiento indicado en la Enfermedad de Caroli limitada a un solo lóbulo es: | K204: Ácido Ursodesoxicólico. | L204: Trasplante Hepático. | M204: Resección quirúrgica del lóbulo afectado. | N204: Litotricia extracorpórea. | Q204: 39
A205: 201 | B205: Región de Murcia | C205: 2019 | D205: region-de-murcia/2019 | E205: main | F205: 16 | G205: Standard/main | H205: Standard/main | J205: En el tratamiento del cáncer de esófago, señale la opción FALSA: | K205: En pacientes con adenocarcinoma esofágico en estadio T1a N0 M0 la terapéutica endoscópica es de elección. | L205: La esofagectomía radical y transtorácica (procedimiento de Ivor-Lewis) es la técnica quirúrgica de elección en el cáncer de esófago localizado, más allá de las etapas muy tempranas (T1b-T2 N0 M0). | M205: En los pacientes con adenocarcinoma de esófago con enfermedad localmente avanzada (T3-T4 N1-3 M0), después de una respuesta tumoral completa a la quimio radioterapia, nunca es preciso realizar cirugía. | N205: En pacientes con enfermedad metastásica (M1) de adenocarcinoma esofágico y buen estado general, está indicada la quimioterapia como tratamiento paliativo. | Q205: 3
A206: 202 | B206: Comunitat Valenciana | C206: 2022 | D206: comunitat-valenciana/2022 | E206: main-47-80 | F206: 54 | G206: Standard/main | H206: Standard/main | J206: Sólo una de las siguientes frases referentes al Dolor Rectal Funcional no es cierta, señálela: | K206: Los episodios de dolor en la Proctalgia Fugax duran de segundos a minutos. | L206: El Síndrome del Elevador del Ano afecta típicamente a mujeres de menos 45 años. | M206: Los criterios de Roma IV reconocen tres tipos de Dolor Rectal Funcional: Proctalgia Fugax, el Síndrome del Elevador del Ano y la Fisura Anal Crónica Idiopática. | N206: El salbutamol inhalado se utiliza para el tratamiento del Síndrome del Elevador del Ano. | Q206: 17
A207: 203 | B207: Aragón | C207: 2017 | D207: aragon/2017 | E207: reserva-especifica | F207: 109 | G207: Other structured types | H207: Non-case reserve | J207: Entre los datos siguientes uno NO es típico del síndrome hepatorenal tipo I? | K207: Sodio en sangre 115. | L207: Creatinina en sangre 5 mg/dl. | M207: Excreción de sodio en orina 50%. | N207: Proteinuria indetectable. | Q207: 39
A208: 204 | B208: Comunitat Valenciana | C208: 2022 | D208: comunitat-valenciana/2022 | E208: main | F208: 23 | G208: Standard/main | H208: Standard/main | J208: Señale cuál de las siguientes respuestas hace referencia a una prueba cuantitativa de función hepática: | K208: Eliminación del verde de Indocianina. | L208: Prueba de espiración de aminopirina. | M208: Eliminación de cafeína. | N208: Todas son correctas. | Q208: 9
A209: 205 | B209: Comunitat Valenciana | C209: 2022 | D209: comunitat-valenciana/2022 | E209: main | F209: 6 | G209: Standard/main | H209: Standard/main | J209: De conformidad con el Capítulo IV del V Convenio Colectivo del Consorcio HGUV –Planificación, Ordenación y Gestión del empleo público- ¿cuál de las siguientes plazas quedan excluidas de su regulación? | K209: Las de libre designación. | L209: Las plazas asistenciales vinculadas a otras de carácter docente. | M209: Las plazas de jefatura. | N209: Todas las respuestas anteriores son correctas. | Q209: 4
A210: 206 | B210: Castilla-La Mancha | C210: 2017 | D210: castilla-la-mancha/2017-2018 | E210: main | F210: 53 | G210: Standard/main | H210: Standard/main | J210: Señale cuál de los siguientes fármacos NO se ha relacionado con pancreatitis aguda | K210: Azatioprina | L210: Ácido valproico | M210: Tamsulosina | N210: IECA | Q210: 10
A211: 207 | B211: Región de Murcia | C211: 2019 | D211: region-de-murcia/2019 | E211: main | F211: 99 | G211: Standard/main | H211: Standard/main | J211: Con respecto al tratamiento farmacológico de la pancreatitis crónica, señale la opción cierta: | K211: No existen datos que apoyen el uso de omeprazol asociado al tratamiento sustitutivo enzimático. | L211: En la diabetes mellitus secundaria a pancreatitis crónica está indicado el tratamiento inicial con antidiabéticos orales. | M211: El tratamiento sustitutivo enzimático se debe controlar siempre mediante test de funcionalismo pancreático. | N211: La dosis de tratamiento sustitutivo enzimático correcta es de 40000-50000 unidades con las comidas principales y 20000-25000 con los snacks. | Q211: 17
A212: 208 | B212: La Rioja | C212: 2021 | D212: la-rioja/2020-2021 | E212: reserva | F212: 103 | G212: Other structured types | H212: Non-case reserve | J212: Cuál de los siguientes no es un criterio de definición de donante marginal para trasplante hepático: | K212: Edad del donante mayor de 65 años. | L212: Un IMC mayor de 30. | M212: Esteatosis hepática mayor del 60%. | N212: Bilirrubina en suero mayor de 3 mg/dL. | Q212: 37
A213: 209 | B213: Castilla-La Mancha | C213: 2022 | D213: castilla-la-mancha/2022 | E213: main | F213: 17 | G213: Standard/main | H213: Standard/main | J213: Paciente con cáncer gástrico precoz bien diferenciado sin signos endoscópicos sugestivos de invasión submucosa en el que se plantea realizar una resección endoscópica. Señale la respuesta falsa | K213: Las técnicas de cromoendoscopia pueden ser útiles para determinar los límites de la lesión. | L213: La ecoendoscopia puede ser útil para evaluar la profundidad de la lesión. | M213: Se debería suprimir el tratamiento con inhibidores de la bomba de protones pues aumentan las complicaciones tras la resección. | N213: La resección endoscópica podría realizarse en lesiones menores o iguales a 2 centímetros no ulceradas. | Q213: 4
A214: 210 | B214: Comunitat Valenciana | C214: 2022 | D214: comunitat-valenciana/2022 | E214: main-47-80 | F214: 77 | G214: Standard/main | H214: Standard/main | J214: Según la European Society of Gastrointestinal Endoscopy (ESGE) señale cuál de las siguientes afirmaciones en el tratamiento de la estenosis biliar secundaria a pancreatitis crónica no es cierta: | K214: La elevación asintomática de la fosfatasa alcalina tres veces los limites altos de la normalidad con elevación de la bilirrubina durante 1 mes se acepta como indicación para el drenaje de la vía biliar | L214: Se debe considerar la cirugía cuando hay fracaso del tratamiento endoscópico después de 1 año. | M214: Se recomienda la utilización de prótesis metálicas autoexpandibles no cubiertas. | N214: La ictericia se puede resolver espontáneamente en el plazo de 1 mes en el 20-50% de los casos. | Q214: 22
A215: 211 | B215: Galicia | C215: 2016 | D215: galicia/ope-2016 | E215: reserva-especifica | F215: 108 | G215: Other structured types | H215: Non-case reserve | J215: En relación con la enfermedad celíaca en el adulto, señale la opción incorrecta: | K215: En un porcentaje significativo de los adultos que siguen la dieta sin gluten, las biopsias solo muestran una mejoría parcial, recuperándose más rápidamente el íleon que el duodeno | L215: Se recomienda repetir la biopsia duodenal al año de iniciar la dieta sin gluten a todos los pacientes adultos celíacos. | M215: Se recomienda realizar una densitometría ósea al año del diagnóstico a todos los pacientes adultos celíacos. | N215: Además de la dieta sin gluten, algunos pacientes celíacos precisan suplementos de hierro, vitamina D, vitamina B12, ácido fólico o vitamina K. | Q215: 25
... A219: 215 | B219: Comunidad de Madrid | C219: 2021 | D219: comunidad-de-madrid/2021 | E219: reserva-especifica | F219: 159 | G219: Other structured types | H219: Non-case reserve | J219: Usted sabe que el tratamiento de la encefalopatía hepática ha de incluir recomendaciones nutricionales. Señale por favor cuál de las siguientes es INCORRECTA | K219: Se debe evaluar la presencia de sarcopenia y el estatus nutricional de todos los pacientes con encefalopatía hepática | L219: La ingesta calórica y proteica no debe ser diferente de la recomendada para cualquier paciente con cirrosis | M219: La nutrición enteral es recomendable en los pacientes con encefalopatía grado II | N219: Las proteinas vegetales y las procedentes de la leche son preferibles a las proteinas animales en pacientes con encefalopatía hepática | Q219: 28
A220: 216 | B220: Castilla y León | C220: 2022 | D220: castilla-y-leon/2022 | E220: reserva | F220: 93 | G220: Other structured types | H220: Non-case reserve | J220: Señale la opción INCORRECTA con respecto al síndrome de intestino corto: | K220: Las principales manifestaciones clínicas son la diarrea y la esteatorrea. | L220: La resección extensa de intestino delgado se relaciona con hiposecreción gástrica por disminución en los niveles de gastrina. | M220: La malabsorción de grasas secundaria a una resección ileal extensa se asocia a mayor riesgo de cálculos renales de oxalato cálcico. | Q220: 23
A221: 217 | B221: Andalucía | C221: 2022 | D221: andalucia/2022-extraordinaria-libre | E221: cuestionario-practico | F221: 115 | G221: Other structured types | H221: Practical | I221: [Full clinical context: andalucia-2022-extraordinaria-libre-caso-07] Un varón de 39 años de edad, con enfermedad de Crohn, acude a su consulta para una revisión periódica. El paciente, con enfermedad ileocólica, está bien controlado con Infliximab, actualmente sin dolor abdominal y con dos deposiciones pastosas al día. A la exploración física el paciente está consciente, orientado, con abdomen blando y depresible, no doloroso a la palpación. La exploración anal demuestra la presencia de un orificio fístuloso perianal. Una rectoscopia observó mucosa rectal normal y un orificio fistuloso interno. Una resonancia magnética observa una fístula perianal simple, sin abscesos. | J221: Indique cuál es el tratamiento adecuado en este caso. | K221: Debemos iniciar tratamiento antibiótico con ciprofloxacino o metronidazol. | L221: Además del antibiótico se debe intensificar el infliximab, o pasar adalimumab para controlar la enfermedad rectal. | M221: Debemos solicitar una ecografía endoanal previa a cualquier opción terapéutica. | N221: Al ser asintomática, basta realizar un seguimiento del paciente, no siendo preciso un tratamiento específico de la fístula. | O221: andalucia-2022-extraordinaria-libre-caso-07 | Q221: 31
A222: 218 | B222: La Rioja | C222: 2021 | D222: la-rioja/2020-2021 | E222: main | F222: 62 | G222: Standard/main | H222: Standard/main | J222: Según los criterios de Roma IV, se define el síndrome de intestino irritable como: | K222: Dolor abdominal recurrente al menos 1 día a la semana durante los últimos seis meses que se asocia a dos o más de los siguientes: se relaciona con la defecación, se asocia a un cambio en la frecuencia de las deposiciones, se asocia a un cambio en la forma (consistencia) de las deposiciones. | L222: Disconfort abdominal recurrente al menos 3 días al mes durante los tres últimos meses que se asocia a dos o más de los siguientes: Se relaciona con la defecación, se asocia a un cambio en la frecuencia de las deposiciones, se asocia a un cambio en la forma (consistencia) de las deposiciones. | M222: Disconfort abdominal recurrente al menos 1 día a la semana durante los últimos tres meses que se asocia a dos o más de los siguientes: Se relaciona con la defecación, se asocia a un cambio en la frecuencia de las deposiciones, se asocia a un cambio en la forma (consistencia) de las deposiciones. | N222: Dolor abdominal recurrente al menos 1 día a la semana durante los últimos tres meses que se asocia a dos o más de los siguientes: Se relaciona con la defecación, se asocia a un cambio en la frecuencia de las deposiciones, se asocia a un cambio en la forma (consistencia) de las deposiciones. | Q222: 24
A223: 219 | B223: Región de Murcia | C223: 2019 | D223: region-de-murcia/2019 | E223: main | F223: 57 | G223: Standard/main | H223: Standard/main | J223: Paciente intervenido de estenosis ileal por enfermedad de Crohn. Inicia tratamiento para la profilaxis de la recurrencia con azatioprina. En la colonoscopia de revisión a los 6 meses se aprecian < de 5 lesiones aftosas. Señale el estadio correspondiente y el tratamiento que se le aplicaría: | K223: Corresponde a un índice de Rutgeerts i1, continua con azatioprina. | L223: Corresponde a un índice de Rutgeerts i0, continua con azatioprina. | M223: Corresponde a un índice de Rutgeerts i2b, cambiamos el tratamiento a un anti TNF. | N223: Corresponde a un índice de Rutgeerts i2a, continua con azatioprina. | Q223: 11
A224: 220 | B224: Región de Murcia | C224: 2019 | D224: region-de-murcia/2019 | E224: main | F224: 119 | G224: Standard/main | H224: Standard/main | J224: Paciente 39 años, mujer, que acude por aumento de FA: 450 con GOT 65 y BRt de 2, Virus negativos, ANA -, LKM1: - AMA: 1/640. P-ANCA:-, BHCG -, ECO abdominal normal. ¿Cuál es el diagnóstico más probable?: | K224: Colangitis Biliar Primaria. | L224: Colangitis esclerosante primaria. | M224: Hepatitis autoinmune tipo I. | N224: Hepatitis autoinmune tipo II. | Q224: 20
A225: 221 | B225: Castilla-La Mancha | C225: 2017 | D225: castilla-la-mancha/2017-2018 | E225: main | F225: 87 | G225: Standard/main | H225: Standard/main | J225: Atendiendo a las guías de Práctica Clínica Americanas de enfermedades vasculares hepáticas de 2020 de la Asociación Americana para el Estudio de las Enfermedades Hepáticas (AASLD), ¿Cuál de los siguientes enunciados es FALSO acerca del Síndrome de Budd-Chiari (SBC)? | K225: El cribado de varices esofágicas en el paciente con SBC crónico es igual que el del paciente cirrótico. | L225: Todos los pacientes con SBC deben recibir tratamiento anticoagulante. | M225: Si no hay respuesta al tratamiento médico debe de realizarse un tratamiento quirúrgico para la hipertensión portal. | N225: El trasplante hepático es útil en pacientes con fallo hepático agudo secundario a SBC y en pacientes con fracaso de otras terapias. | Q225: 16
A226: 222 | B226: Castilla-La Mancha | C226: 2022 | D226: castilla-la-mancha/2022 | E226: main | F226: 23 | G226: Standard/main | H226: Standard/main | J226: Una paciente de 86 años acude a urgencias por dolor en epigastrio y vómitos con restos alimentarios. La paciente presenta mal estado general y deshidratación. A la exploración presenta dolor leve en epigastrio con timpanismo. Analíticamente destaca hemoglobina 16.3 g/dl, urea 133 mg/dl, creatinina 3.20 mg/dl, y PCR 189.6 mg/l. En la radiografía simple de abdomen se observa una gran dilatación de la cámara gástrica y aerobilia. También dos niveles hidroaéreos en el hipocondrio derecho. Cuál es el diagnóstico más probable | K226: Vólvulo gástrico | L226: Síndrome de Bouveret | M226: Bezoar gástrico | N226: Síndrome de la pinza aorto-mesentérica | Q226: 5
A227: 223 | B227: Aragón | C227: 2020 | D227: aragon/2020 | E227: reserva-especifica | F227: 102 | G227: Other structured types | H227: Non-case reserve | J227: En relación con la biopsia hepática, ¿cuál de estas afirmaciones es INCORRECTA?: | K227: Los estudios controlados no demuestran que la biopsia con control ecográfico ~~reduzca~~ la mortalidad, pero sí la incidencia de complicaciones graves. | L227: La indicación fundamental de la biopsia transyugular (BTY) es la presencia de una alteración grave de la coagulación. | M227: La eficacia diagnóstica de la BTY es muy elevada, lo que permite obtener un diagnóstico histológico correcto en cerca del 80% de los pacientes. | N227: La hemorragia peritoneal significativa es una complicación frecuente en la BTY. | Q227: 20
A228: 224 | B228: Comunitat Valenciana | C228: 2022 | D228: comunitat-valenciana/2022 | E228: main | F228: 24 | G228: Standard/main | H228: Standard/main | J228: Según las recomendaciones de la European Society of Gastrointestinal Endoscopy (ESGE) sobre la ecoendoscopia terapéutica ¿Cuál es el tiempo óptimo que debe transcurrir antes de realizar una CPRE transgástrica dirigida por ecoendoscopia después de la colocación de una prótesis de aposición luminal? | K228: Al menos 2 días. | L228: Al menos 5 días. | M228: Al menos 7 días. | N228: Al menos 10 días. | Q228: 9
A229: 225 | B229: Comunidad de Madrid | C229: 2021 | D229: comunidad-de-madrid/2021 | E229: main | F229: 125 | G229: Standard/main | H229: Standard/main | J229: En pacientes con síndrome de Lynch, ¿qué tipo de vigilancia endoscópica se recomienda para el cribado de cáncer colorrectal? | K229: Colonoscopia cada 1-2 años a partir de los 20-25 años | L229: Test inmunológico de sangre oculta en heces (SOHi) bienal a partir de los 50 años | M229: Colonoscopia cada 5 años a partir de los 30 años | N229: Sigmoidoscopia anual desde los 40 años | Q229: 23
A230: 226 | B230: Castilla-La Mancha | C230: 2017 | D230: castilla-la-mancha/2017-2018 | E230: main | F230: 14 | G230: Standard/main | H230: Standard/main | J230: Señale la complicación más frecuente de la úlcera péptica | K230: Perforación. | L230: Hemorragia. | M230: Obstrucción. | N230: Penetración. | Q230: 4
A231: 227 | B231: Región de Murcia | C231: 2019 | D231: region-de-murcia/2019 | E231: main | F231: 71 | G231: Standard/main | H231: Standard/main | J231: En estreñimiento funcional se recomiendan las siguientes medidas dietéticas menos una: | K231: Ingesta de 25-30 g de fibra soluble con la dieta al día. | L231: Ingesta adecuada de líquido (1,5-2 l al día). | M231: Patrón regular de comidas. | N231: Dieta sin gluten. | Q231: 13
A232: 228 | B232: Andalucía | C232: 2022 | D232: andalucia/2022-extraordinaria-libre | E232: cuestionario-practico | F232: 143 | G232: Other structured types | H232: Practical | I232: [Full clinical context: andalucia-2022-extraordinaria-libre-caso-17] Paciente de 76 años con antecedentes de cáncer de endometrio 12 años antes, tratado con éxito mediante cirugía y raditerapia, e hipertensión arterial, en tratamiento con Omeprazol, Losartan, Lormetazepam, Levosulpiride, Metamizol y Optovite, que acude a urgencias por cuadro de dolor abdominal en epigastrio irradiado a hipocondrio derecho, constante, de gran intensidad, náuseas y vómitos de contenido alimentario-bilioso, así como sensación febril no termometrada sin clara tiritona. Exploración: TA: 161/68 mmHg; frecuencia cardíaca: 69 lpm; Temperatura: 37,6 ºC; Saturación: 97% (aire ambiente). Buen estado general. Consciente, alerta y orientada. Eupneica en reposo. No cortejo vegetativo ni bacteriémico. ACR: Tonos rítmicos, sin soplos audibles. Abdomen: Blando y depresible. Dolor a la palpación en epigastrio e hipocondrio derecho. No signos de peritonismo; ruidos algo disminuidos, de timbre normal. No se palpan masas ni megalias. Miembros inferiores sin edemas. ANALÍTICA: Destaca leucocitosis de 18.420/mm³ (91% PMN), amilasa 5.518 U/L, AST: 93 U/L, ALT: 63 U/L, Fosfatasa alcalina: 350 U/L, GammaGT: 267 U/L, Bilirrubina total 3 mg/dL; PCR: 200,1 mg/L, procalcitonina 9,72 ng/mL. | J232: Teniendo en cuenta su anterior respuesta, ¿de qué tipo de pancreatitis estaríamos hablando, según la clasificación de Atlanta? | K232: Es una pancreatitis aguda leve, porque el fallo orgánico es transitorio y no hay complicaciones locales. | L232: Es una pancreatitis aguda moderadamente severa, porque el fallo orgánico puede ser transitorio. | M232: Es una pancreatitis aguda necrotizante, no pudiendo precisarse más porque estamos en fase temprana de la enfermedad. | N232: Es una pancreatitis aguda grave, porque presenta un fallo respiratorio que ya no puede considerarse transitorio, pues se prolonga más de 48 horas. | O232: andalucia-2022-extraordinaria-libre-caso-17 | Q232: 40
A233: 229 | B233: Comunitat Valenciana | C233: 2022 | D233: comunitat-valenciana/2022 | E233: main-47-80 | F233: 58 | G233: Standard/main | H233: Standard/main | J233: El dato clínico para establecer el diagnóstico de insuficiencia hepática aguda en un adulto es: | K233: Subictericia. | L233: Ascitis. | M233: Encefalopatía. | N233: Cualquiera de ellas. | Q233: 18
A234: 230 | B234: Región de Murcia | C234: 2019 | D234: region-de-murcia/2019 | E234: main | F234: 69 | G234: Standard/main | H234: Standard/main | J234: Paciente de 25 años que consulta por dolor abdominal recidivante, que presenta 3 días a la semana en los últimos 4 meses, asociado hábito alternante con predominio de estreñimiento, sin criterios clínicos de alarma. ¿Cuál sería el fármaco indicado como primera opción?: | K234: Fibra soluble. | L234: Laxante osmótico. | M234: Linaclotida. | N234: Prucaloprida. | Q234: 12
A235: 231 | B235: La Rioja | C235: 2021 | D235: la-rioja/2020-2021 | E235: main | F235: 44 | G235: Standard/main | H235: Standard/main | J235: En relación al manejo de la ascitis en la cirrosis descompensada, indique la respuesta incorrecta: | K235: Es recomendable una dieta con un contenido muy bajo de sodio (<40 mmol / día) en pacientes con ascitis moderada. | L235: La administración de baclofeno es beneficiosa en pacientes con calambres musculares secundarios al tratamiento diurético. | M235: En la actualidad, no se recomienda la adición de clonidina o midodrina al tratamiento diurético en la ascitis refractaria. | N235: Después de la paracentesis evacuadora, los pacientes deben recibir la dosis mínima de diuréticos necesaria para prevenir la reaparición de la ascitis. | Q235: 18
A236: 232 | B236: Aragón | C236: 2017 | D236: aragon/2017 | E236: main | F236: 83 | G236: Standard/main | H236: Standard/main | J236: Una de las siguientes medidas terapéuticas NO ha demostrado ser de utilidad alguna en el tratamiento de la enfermedad de Ménétrier | K236: Anticuerpos monoclonales frente al factor de crecimiento transformante alfa (TGF-alfa). | L236: Erradicar la infección por H. pylori | M236: Anticolinérgicos. | N236: Infliximab | Q236: 29
A237: 233 | B237: Comunidad de Madrid | C237: 2021 | D237: comunidad-de-madrid/2021 | E237: reserva-especifica | F237: 151 | G237: Other structured types | H237: Non-case reserve | J237: ¿Cual de las siguientes es correcta en relacion con el tratamiento con ácido ursodesoxicolico en la colangitis biliar primaria? | K237: La dosis recomendada es de 5 mg/kg/día | L237: La respuesta se valora por la normalización de la GGT | M237: La respuesta al tratamiento tiene valor pronóstico | N237: No debe iniciarse hasta que la bilirrubina supere los 2 mg/dl | Q237: 27
A238: 234 | B238: Región de Murcia | C238: 2019 | D238: region-de-murcia/2019 | E238: main | F238: 43 | G238: Standard/main | H238: Standard/main | J238: La bondad de la FIBRA en la dieta es consecuencia de los siguientes efectos beneficiosos (señale la opción FALSA): | K238: Disminución del pH fecal mediante transformación a ácidos grasos de cadena corta. | L238: Disminución fecal de los ácidos biliares secundarios y mutágenos. | M238: Disminución del volumen fecal. | N238: Aumento del volumen fecal. | Q238: 8
A239: 235 | B239: Castilla-La Mancha | C239: 2022 | D239: castilla-la-mancha/2022 | E239: reserva-especifica | F239: 102 | G239: Other structured types | H239: Non-case reserve | J239: El síndrome de Stauffer es un cuadro de colestasis intrahepática de origen paraneoplásico descrito inicialmente asociado a | K239: Cáncer pulmonar microcítico. | L239: Carcinoma hepatocelular. | M239: Carcinoma de células renales. | N239: Adenocarcinoma de páncreas. | Q239: 18
A240: 236 | B240: Galicia | C240: 2019 | D240: galicia/ope-2019 | E240: reserva-especifica | F240: 105 | G240: Other structured types | H240: Non-case reserve | J240: ¿Cuál de las siguientes entidades es una causa típica de hipertensión portal presinusoidal? | K240: Esquistosomiasis. | L240: Síndrome de Budd-Chiari. | M240: Insuficiencia cardíaca congestiva. | N240: Pericarditis constrictiva. | Q240: 20
A241: 237 | B241: Castilla y León | C241: 2019 | D241: castilla-y-leon/2019 | E241: reserva-especifica | F241: 159 | G241: Other structured types | H241: Non-case reserve | J241: La paracentesis evacuadora en paciente con Cirrosis Hepática y descompensación hidrópica puede realizarse: | K241: Sólo si hay fracaso a tratamiento con diuréticos | L241: Sólo si la ascitis es a tensión | M241: En cualquier circunstancia en que no esté contraindicada | N241: Solo si el paciente presenta datos concomitantes de encefalopatía hepática | Q241: 36
A242: 238 | B242: Castilla-La Mancha | C242: 2022 | D242: castilla-la-mancha/2022 | E242: reserva-especifica | F242: 105 | G242: Other structured types | H242: Non-case reserve | J242: Conforme al artículo 17.1 del Estatuto Marco son derechos individuales del personal estatutario de los servicios de salud | K242: El descanso necesario, mediante la limitación de la jornada, las vacaciones periódicas retribuidas y permisos en los términos que se establezcan. | L242: El derecho de reunión. | M242: La negociación colectiva. | N242: La libre sindicación | Q242: 18
A243: 239 | B243: Castilla y León | C243: 2022 | D243: castilla-y-leon/2022 | E243: main | F243: 27 | G243: Standard/main | H243: Standard/main | J243: En relación con el colangiocarcinoma, ¿cuál de las siguientes afirmaciones es falsa?: | K243: El tipo histológico más frecuentes es el adenocarcinoma. | L243: El colangiocarcinoma intrahepático tiende a la formación de masas. | M243: Los adenocarcinomas intraductales-papilares se extienden en profundidad a lo largo de la mucosa biliar invadiendo las capas de las paredes fibromusculares. | Q243: 8
A244: 240 | B244: Andalucía | C244: 2022 | D244: andalucia/2022-extraordinaria-libre | E244: cuestionario-practico | F244: 133 | G244: Other structured types | H244: Practical | I244: [Full clinical context: andalucia-2022-extraordinaria-libre-caso-14] Una niña de 15 años de edad es remitida a su consulta por ictericia recurrente y episodios de colangitis. La paciente ha necesitado drenajes percutáneos en cuatro ocasiones durante los pasados 5 años. En la exploración física se observa ictericia escleral y hepatomegalia. Analíticamente tiene 4 mg/dl de bilirrubina. Se realiza una colangiografía por RNM, que demuestra dilataciones saculares de la vía biliar en ambos lóbulos. | J244: ¿Cuál es la actitud más adecuada? | K244: Acido Ursodesoxicólico a dosis elevadas. | L244: Hepatectomía de los segmentos afectos. | M244: Iniciar protocolo pretrasplante hepático. | N244: CPRE con colangioscopia y drenaje biliar selectivo de las zonas afectas. | O244: andalucia-2022-extraordinaria-libre-caso-14 | Q244: 36
A245: 241 | B245: Castilla y León | C245: 2022 | D245: castilla-y-leon/2022 | E245: main | F245: 87 | G245: Standard/main | H245: Standard/main | J245: Entre los factores asociados a un aumento de frecuencia en la población de enfermedad de Crohn NO se encuentra uno de los siguientes: | K245: Antibióticos en la infancia. | L245: Dieta pobre en fibra. | M245: Lactancia materna. | Q245: 22
A246: 242 | B246: Castilla y León | C246: 2022 | D246: castilla-y-leon/2022 | E246: main | F246: 42 | G246: Standard/main | H246: Standard/main | J246: Ante un paciente que inicia tratamiento con Rituximab, deberíamos plantear tratamiento preventivo de reactivación del VBH: | K246: Solo en los pacientes con HBsAg POSITIVO. | L246: Solo en los pacientes con HBcAc POSITIVO. | M246: Tanto en los pacientes HBsAg POSITIVO como en los HBcAc POSITIVO. | Q246: 11
A247: 243 | B247: Comunidad de Madrid | C247: 2021 | D247: comunidad-de-madrid/2021 | E247: main | F247: 147 | G247: Standard/main | H247: Standard/main | J247: La primera línea de tratamiento farmacológico para la colangitis biliar primaria es: | K247: Metotrexato | L247: Ácido ursodesoxicólico (UDCA) | M247: Azatioprina | N247: Ciclosporina | Q247: 26
A248: 244 | B248: Aragón | C248: 2020 | D248: aragon/2020 | E248: reserva-especifica | F248: 108 | G248: Other structured types | H248: Non-case reserve | J248: En el tratamiento del fallo hepático agudo sobre crónico con fallo renal agudo (AKI: acute kidney injury) son ciertas las siguientes afirmaciones EXCEPTO: | K248: Se deben retirar los diuréticos. | L248: En la reanimación hemodinámica están contraindicados los preparados a base de coloides de almidón. | M248: En caso de shock persistente el vasopresor indicado es norepinefrina. | N248: La diálisis de albúmina mediante el Sistema Recirculante de Absorción Molecular (MARS) mejora la supervivencia a corto plazo (28 días). | Q248: 21
A249: 245 | B249: Comunitat Valenciana | C249: 2022 | D249: comunitat-valenciana/2022 | E249: main | F249: 31 | G249: Standard/main | H249: Standard/main | J249: ¿Cuál de los siguientes es el tumor metastásico más frecuente en el estómago? | K249: Mama. | L249: Melanoma. | M249: Pulmón. | N249: Ovario. | Q249: 11
A250: 246 | B250: Galicia | C250: 2019 | D250: galicia/ope-2019 | E250: reserva-especifica | F250: 109 | G250: Other structured types | H250: Non-case reserve | J250: ¿Cuál de las siguientes entidades se asocia con más frecuencia a la colangitis esclerosante primaria? | K250: Lupus eritematoso sistémico. | L250: Esclerodermia. | M250: Enfermedad celíaca. | N250: Colitis ulcerosa. | Q250: 21
A251: 247 | B251: Comunidad de Madrid | C251: 2021 | D251: comunidad-de-madrid/2021 | E251: reserva-especifica | F251: 156 | G251: Other structured types | H251: Non-case reserve | J251: Farmacoterapia y sedación en endoscopia. ¿Cuál de las siguientes asociaciones entre fármaco y objetivo terapéutico es FALSA? | K251: Propofol- Sedación profunda. | L251: Fentanilo- Analgesia. | M251: Naloxona- Antagonista benzodiacepinico. | N251: Midazolam- Sedación superficial. | Q251: 28
A252: 248 | B252: Comunidad de Madrid | C252: 2021 | D252: comunidad-de-madrid/2021 | E252: reserva-especifica | F252: 157 | G252: Other structured types | H252: Non-case reserve | J252: ¿Cuál de las afirmaciones siguientes es FALSA en relación con la infección por H pylori? | K252: Se debe excluir gastritis por H. pylori antes de hacer un diagnóstico de dispepsia funcional | L252: Antes de testar por la presencia de infección por H. pylori, los IBP deben suspenderse 2 semanas antes y los compuestos con bismuto y los antibióticos 4 semanas antes | M252: Como tratamiento de primera línea de la infección por H. pylori se recomienda una pauta cuádruple concomitante sin bismuto (IBP, claritromicina, amoxicilina y metronidazol) o una combinación cuádruple con bismuto (IBP, bismuto, tetraciclina y metronidazol) | N252: Se recomienda que la duración del tratamiento con terapia cuádruple sin bismuto o cuádruple con bismuto sea de 14 días | Q252: 28
A253: 249 | B253: Aragón | C253: 2020 | D253: aragon/2020 | E253: reserva-especifica | F253: 101 | G253: Other structured types | H253: Non-case reserve | J253: Respecto al octreótido, un análogo sintético de la somatostatina, ¿qué afirmación NO es cierta? | K253: Su vida media es de unas 8 horas. | L253: Está indicado en el síndrome de Zollinger-Ellison. | M253: Está indicado en el síndrome del intestino corto. | N253: Puede utilizarse en el síndrome carcinoide. | Q253: 20
A254: 250 | B254: Aragón | C254: 2020 | D254: aragon/2020 | E254: reserva-especifica | F254: 106 | G254: Other structured types | H254: Non-case reserve | J254: La clasificación de Chicago se refiere a: | K254: Una clasificación de la candidiasis esofágica. | L254: Una clasificación de los trastornos motores esofágicos basada en manometría de alta resolución. | M254: Una clasificación de la esofagitis por cáusticos. | N254: Una clasificación del tipo de estenosis esofágica. | Q254: 20
A255: 251 | B255: Región de Murcia | C255: 2019 | D255: region-de-murcia/2019 | E255: main | F255: 142 | G255: Standard/main | H255: Standard/main | J255: En relación a la peritonitis Bacteriana espontanea (PBE), señale la respuesta verdadera: | K255: Se resuelve con tratamiento antibiótico en la mayoría de los pacientes. | L255: Los organismos más comúnmente aislados son bacterias Gram positivas. | M255: La aparición de PBE en un paciente cirrótico no condiciona un empeoramiento del pronóstico de la enfermedad. | N255: Nunca hay que plantear diagnóstico diferencial con una peritonitis bacteriana secundaria. | Q255: 23
A256: 252 | B256: Aragón | C256: 2017 | D256: aragon/2017 | E256: main | F256: 53 | G256: Standard/main | H256: Standard/main | J256: Señale cuál de estas afirmaciones NO es cierta respecto al uso de propofol en exploraciones endoscópicas: | K256: El uso de propofol por personal de enfermería entrenado es equiparable en seguridad a los sedantes tradicionales si se hace en las condiciones de monitorización y vigilancia adecuadas | L256: La utilización de propofol por personal de endoscopias en pacientes ASA III es posible y segura cuando se realiza en unidades de endoscopia con experiencia en el uso del mismo | M256: La dosificación del propofol debe individualizarse de acuerdo a la respuesta y condiciones basales del paciente | N256: La administración de midazolam previa al propofol permite reducir sus dosis y disminuir los efectos adversos, especialmente la hipotensión en cardiópatas o en situaciones de hipovolemia, porque disminuye el tiempo de recuperación | Q256: 21
A257: 253 | B257: Galicia | C257: 2019 | D257: galicia/ope-2019 | E257: reserva-especifica | F257: 102 | G257: Other structured types | H257: Non-case reserve | J257: Los siguientes factores incrementan el riesgo de pancreatitis postCPRE EXCEPTO: | K257: Pancreatitis crónica. | L257: Sexo femenino. | M257: Vía biliar no dilatada. | N257: Disfunción del esfínter de Oddi. | Q257: 20
A258: 254 | B258: Galicia | C258: 2019 | D258: galicia/ope-2019 | E258: reserva-especifica | F258: 104 | G258: Other structured types | H258: Non-case reserve | J258: En cuanto a la diarrea secretora, es VERDADERO: | K258: Una causa es el déficit adquirido de la lactasa. | L258: Se puede producir por consumo excesivo de sorbitol. | M258: Continúa a pesar del ayuno. | N258: Es el mecanismo de acción de la lactulosa. | Q258: 20
... A261: 257 | B261: Comunidad de Madrid | C261: 2021 | D261: comunidad-de-madrid/2021 | E261: reserva-especifica | F261: 155 | G261: Other structured types | H261: Non-case reserve | J261: ¿Cuál de los siguientes criterios es imprescindible para realizar el diagnóstico de pancreatitis aguda? | K261: Elevación de amilasa y lipasa sérica más de tres veces el límite superior de la normalidad | L261: Dolor abdominal en piso abdominal superior | M261: Datos compatibles en prueba de imagen (ecografía, TC o resonancia magnética) compatibles | N261: Ninguno de las anteriores | Q261: 28
A262: 258 | B262: Andalucía | C262: 2022 | D262: andalucia/2022-extraordinaria-libre | E262: cuestionario-practico | F262: 101 | G262: Other structured types | H262: Practical | I262: [Full clinical context: andalucia-2022-extraordinaria-libre-caso-01] Paciente varón de 69 años, diagnosticado de cirrosis hepática de causa etílica. Dos años antes había ingresado por un primer episodio de ascitis que fue bien controlado, favorecido por un periodo subsiguiente de abstinencia alcohólica. En sus antecedentes se incluye diabetes de tipo 2 que trataba con hipoglucemiantes orales y broncopatía crónica en relación con su condición de fumador activo de 2 paquetes diarios hasta hacía 6 meses. Acude a Urgencias por distensión abdominal intensa por acumulación de ascitis, reconociendo una clara recaída del consumo abusivo de alcohol. Tiene aceptable estado general, se observa pérdida notable de masa muscular, la TA era de 110/60 mmHg y no tenía fiebre. En el examen físico se apreció ictericia leve de piel, estigmas cutáneos de cirrosis y una discreta bradipsiquia. En análisis destacan los siguientes datos: Hb 8.7 gr/dl, VCM 112, leucocitos 2.700/mm³, plaquetas 70.000/mm³. Glucemia 131 mg/dl, sodio sérico de 129 mEq/L, creatinina 1.8 mg/dl, bilirrubina total 3.5 mg/dl, albúmina 2.6 gr/dl, actividad de protrombina de 45%, AST 80 UI/L, ALT 30 UI/L, GGT 567 UI/L, FA 152 IU/L. HBsAg negativo, Ac-HBc positivos, Ac-VHC negativos. | J262: Una de las afirmaciones siguientes, en el contexto de una primera evaluación del paciente, es INCORRECTA: | K262: La encefalopatía del paciente en fases iniciales justificaría una dieta baja en proteínas. | L262: Entre las actuaciones iniciales debe incluirse una paracentesis diagnóstica y una ecografía. | M262: A pesar de los antecedentes clínicos de este paciente y sus hábitos tóxicos, no se puede establecer de entrada una contraindicación absoluta para trasplante hepático. | N262: La utilización de diuréticos en este paciente tiene un alto riesgo de efectos secundarios. | O262: andalucia-2022-extraordinaria-libre-caso-01 | Q262: 27
A263: 259 | B263: Castilla y León | C263: 2022 | D263: castilla-y-leon/2022 | E263: reserva | F263: 94 | G263: Other structured types | H263: Non-case reserve | J263: Con respecto a la hepatitis autoinmune ¿Qué es falso? | K263: La presencia de niveles elevados de IgG, especialmente en ausencia de cirrosis, es una característica distintiva de la Hepatitis autoinmune. Una IgG selectivamente elevada en ausencia de IgA e IgM es particularmente sugestiva de HAI. | L263: La demostración histológica de hepatitis era un requisito previo para el diagnóstico de Hepatitis autoinmune, pero en la actualidad puede sustituirse por la elastografía hepática mucho menos invasiva. | M263: La coexistencia de características de Hepatitis autoinmune e hígado colestásico pueden observarse, tanto en el momento del diagnóstico como durante el seguimiento por los que deben realizarse pruebas de diagnóstico de CBP y CEP en pacientes que muestran características de colestasis. | Q263: 23
A264: 260 | B264: Galicia | C264: 2022 | D264: galicia/ope-2022 | E264: reserva-especifica | F264: 106 | G264: Other structured types | H264: Non-case reserve | J264: Señale la respuesta FALSA en relación con el trasplante hepático en pacientes con fallo hepático agudo: | K264: El contacto con el centro de trasplante y la planificación apropiada del traslado debe hacerse de forma temprana en la evaluación del paciente. | L264: Están indicados los sistemas de soporte hepático como puente al trasplante. | M264: En pacientes con hepatomegalia gigante debe descartarse infiltración maligna mediante pruebas de imagen o biopsia. | N264: Debe indicarse el trasplante en aquellos pacientes que cumplen criterios del Kings College o de Clichy. | Q264: 21
A265: 261 | B265: Andalucía | C265: 2021 | D265: andalucia/2021-22-libre | E265: cuestionario-teorico | F265: 50 | G265: Other structured types | H265: Theoretical | J265: El virus de la hepatitis B tiene varias mutaciones, la más importante es la mutación pre-C o pre-core, que es la más frecuente en nuestro medio. Indique lo que considere falso: | K265: Es una variante mas agresiva, con peor pronóstico | L265: Se caracteriza por no detectarse el Ag HBe | M265: Nunca coexiste con la variante no mutada | N265: La mutación mas frecuente es la sustitución de una única base | Q265: 13
A266: 262 | B266: Galicia | C266: 2022 | D266: galicia/ope-2022 | E266: reserva-especifica | F266: 108 | G266: Other structured types | H266: Non-case reserve | J266: En cuanto al cáncer colo-rectal, señale la respuesta INCORRECTA: | K266: Es el más frecuente en España globalmente. | L266: La forma hereditaria más frecuente es el Síndrome de Lynch. | M266: La obesidad es un factor de riesgo. | N266: Se recomienda administrar suplementos de vitamina D en poblaciones de riesgo de cáncer de colon. | Q266: 22
A267: 263 | B267: La Rioja | C267: 2024 | D267: la-rioja/2023-2024 | E267: main | F267: 62 | G267: Standard/main | H267: Standard/main | J267: Respecto al tratamiento con Mirikizumab en colitis ulcerosa, señale la respuesta VERDADERA: | K267: Es un anticuerpo monoclonal IgG4 humanizado que se une a la subunidad p19 de la IL-23. | L267: La inducción extendida (3 dosis más de 300 mg iv cada 4 semanas), consigue que más del 80% de pacientes alcancen respuesta clínica en semana 24 en los estudios de registro. | M267: Está indicado en pacientes que han perdido respuesta al tratamiento con Ustekinumab (anti IL-12/23). | N267: Todas las anteriores son ciertas. | Q267: 16
A268: 264 | B268: Galicia | C268: 2022 | D268: galicia/ope-2022 | E268: reserva-especifica | F268: 101 | G268: Other structured types | H268: Non-case reserve | J268: En los cánceres ductales de cabeza de páncreas, ¿cuál de los siguientes criterios NO se corresponde con un tumor resecable "borderline"? | K268: Contacto con la arteria mesentérica superior menos de 180 grados. | L268: Invasión de la pared duodenal. | M268: Contacto con la vena cava inferior. | N268: Contacto con la vena mesentérica superior más de 180 grados. | Q268: 20
A269: 265 | B269: Galicia | C269: 2022 | D269: galicia/ope-2022 | E269: reserva-especifica | F269: 105 | G269: Other structured types | H269: Non-case reserve | J269: Varón, 63 años, sin antecedentes personales de interés. Es diagnosticado en 2018 de cirrosis hepática por alcohol tras una primera descompensación en forma de hemorragia digestiva por varices esofágicas. Abstinente desde entonces, con función hepática normal, A5 de Child–Pugh, PS 0. En TC abdominal se observa un nódulo de 31 mm con comportamiento dinámico diagnóstico de hepatocarcinoma. Según criterio BCLC la primera opción terapéutica a considerar sería: | K269: Resección. | L269: Ablación. | M269: Trasplante hepático. | N269: Quimioembolización transarterial. | Q269: 21
A270: 266 | B270: Aragón | C270: 2017 | D270: aragon/2017 | E270: reserva-especifica | F270: 106 | G270: Other structured types | H270: Non-case reserve | J270: Respecto al tratamiento del estreñimiento crónico idiopático, ¿Cuál de las siguientes afirmaciones NO es cierta? | K270: Se recomienda un consumo de fibra dietética de 20 a 35 gr al día | L270: El psyllium es un laxante formador de volumen | M270: La prucaloprida actúa activando los canales de cloro | N270: La linaclotida es un agonista de la guanilato-ciclasa | Q270: 37
A271: 267 | B271: La Rioja | C271: 2021 | D271: la-rioja/2020-2021 | E271: main | F271: 77 | G271: Standard/main | H271: Standard/main | J271: Indique la respuesta falsa respecto a la litotricia mecánica biliar. | K271: Fue descrita por primera vez en la década de 1980. | L271: Es imprescindible la visión directa de la litiasis mediante colangioscopia para poder practicarla. | M271: La mayoría de los dispositivos son rígidos y de cierta dificultad de manejo. | N271: Es la modalidad de litotricia más económica. | Q271: 28
A272: 268 | B272: Castilla-La Mancha | C272: 2017 | D272: castilla-la-mancha/2017-2018 | E272: main | F272: 51 | G272: Standard/main | H272: Standard/main | J272: Uno de los siguientes Criterios del Síndrome de Lynch no se incluye en los Criterios de Ámsterdam II | K272: Tres o más individuos afectados de CCR o neoplasia relacionada (endometrio, intestino delgado, uréter o pelvis renal), uno de ellos familiar de primer grado de los otros dos. | L272: Afectación de 2 generaciones consecutivas. | M272: Como mínimo un caso diagnosticado antes de los 40 años. | N272: Exclusión del diagnóstico de poliposis adenomatosa familiar. | Q272: 10
A273: 269 | B273: Aragón | C273: 2020 | D273: aragon/2020 | E273: main | F273: 83 | G273: Standard/main | H273: Standard/main | J273: En la pancreatitis crónica es cierto que: | K273: Se puede producir déficit de B12 secundaria a menor proteolisis del compuesto vitamina B12- proteínas R fijadoras. | L273: La anemia ferropénica es la norma en estos pacientes. | M273: La anemia habitual es mixta, ferropénica y de proceso crónico. | N273: Lo habitual es una anemia asociada al tratamiento con enzimas pancreáticas. | Q273: 17
A274: 270 | B274: Comunitat Valenciana | C274: 2022 | D274: comunitat-valenciana/2022 | E274: main-47-80 | F274: 78 | G274: Standard/main | H274: Standard/main | J274: Según la Guía Europea de Gastroenterología basada en la evidencia para el diagnóstico y tratamiento de la pancreatitis crónica (HaPanEU), ante un paciente diagnosticado de pancreatitis crónica con insuficiencia pancreática exocrina, una de las siguientes aseveraciones no es cierta: | K274: No se precisan de forma sistemática pruebas de función pancreática exocrina para controlar eficacia del tratamiento enzimático. | L274: La presencia de insuficiencia pancreática exocrina debe evaluarse anualmente en pacientes con pancreatitis crónica. | M274: Todo paciente con nuevo diagnóstico de pancreatitis crónica debe realizarse pruebas de detección de insuficiencia exocrina pancreática. | N274: Mayores niveles de elastasa fecal reflejan mayor grado de insuficiencia pancreática. | Q274: 23
A275: 271 | B275: Andalucía | C275: 2022 | D275: andalucia/2022-extraordinaria-libre | E275: cuestionario-practico | F275: 132 | G275: Other structured types | H275: Practical | I275: [Full clinical context: andalucia-2022-extraordinaria-libre-caso-13] Un varón de 61 años de edad, acude a su consulta con ictericia y heces acólicas de 3 meses de evolución. Niega la presencia de dolor abdominal, náuseas o vómitos. Su historia previa destaca por la presencia de hipertensión arterial, diabetes y osteoatritis. Por lo demás, el paciente está sano y laboralmente activo. A la exploración física el paciente está afebril, sin dolor abdominal ni hepatomegalia. Analíticamente destaca: leucocitos 6.300/mm³, hemoglobina 13,1 g/dl, fosfatasa alcalina 805 U/L, AST 30 U/L, ALT 60 U/L, bilirrubina total 6,9 mg/dl, bilirrubina directa 4,2 mg/dl, creatinina 1,1 mg/dl, INR 1,0. Una RMN demuestra una dilatación de vía intra y extrahepática con obstáculo en la papila, y conducto pancreático también dilatado. No se observan masas ni adenopatías regionales. La CPRE demuestra una mucosa irregular en papila, con estenosis en la misma, que se observa tras ser canulada. Se realiza esfinterotomía y se inserta una prótesis biliar plástica. Las biopsias de la mucosa ampular revelan la presencia de un adenocarcinoma. | J275: ¿Cuál es el paso más adecuado en el tratamiento subsiguiente de este paciente? | K275: Ampulectomía endoscópica dependiendo de su tamaño y extensión intraductal. | L275: Ampulectomía quirúrgica dependiendo de su tamaño y extensión intraductal. | M275: Duodenopancreatectomía cefálica. | N275: Tratamiento neoadyuvante. | O275: andalucia-2022-extraordinaria-libre-caso-13 | Q275: 36
A276: 272 | B276: Galicia | C276: 2022 | D276: galicia/ope-2022 | E276: reserva-especifica | F276: 103 | G276: Other structured types | H276: Non-case reserve | J276: NO se asocia a uso crónico de IBP (Inhibidores de la Bomba de protones): | K276: Aumento de riesgo de infección por Clostridium Difficile. | L276: Déficit de vitamina B12. | M276: Hipomagnesemia. | N276: Hipogastrinemia. | Q276: 21
A277: 273 | B277: Andalucía | C277: 2022 | D277: andalucia/2022-extraordinaria-libre | E277: cuestionario-teorico | F277: 10 | G277: Other structured types | H277: Theoretical | J277: Usted está leyendo un artículo que publica los resultados de un gran ensayo clínico aleatorizado y doble ciego, de gran interés en su ámbito profesional. En concreto le llama la atención el resultado que muestra este estudio sobre la mortalidad global al comparar un nuevo tratamiento experimental con la terapia estándar hasta este momento, en una población de pacientes que tienen un perfil muy similar a los que se tratan en su Unidad. Este resultado publicado es: RR = 0.71 (IC95% 0.98-0.59, p=0.046). ¿Cuál de las siguientes afirmaciones es correcta? | K277: El valor p asociado al contraste no es significativo estadísticamente. | L277: La reducción relativa del riesgo (RRR) para la variable "mortalidad global" es aproximadamente del 29%. | M277: El NNT (número de pacientes que necesitaría tratarse con el nuevo tratamiento en vez del estándar para reducir un resultado de muerte por cualquier causa) sería 71. | N277: La probabilidad de que estos resultados se deban al error del muestreo es del 95%. | Q277: 4
A278: 274 | B278: Galicia | C278: 2022 | D278: galicia/ope-2022 | E278: reserva-especifica | F278: 110 | G278: Other structured types | H278: Non-case reserve | J278: Señale la afirmación INCORRECTA: | K278: Los AINEs se asocian a un aumento del riesgo de complicaciones en todo el tracto digestivo. | L278: El daño gastrointestinal mediado por AINEs se debe en su mayoría, a la inhibición sistémica de la COX-1. | M278: Los IBP reducen la incidencia de úlcera péptica en pacientes con factores de riesgo para el desarrollo de complicaciones gastrointestinales asociadas al uso de AINEs. | N278: El uso de COXIB, frente a AINEs clásicos, se asocia a una mayor tasa de úlcera péptica, complicaciones y síntomas gastrointestinales. | Q278: 22
A279: 275 | B279: Andalucía | C279: 2021 | D279: andalucia/2021-22-libre | E279: cuestionario-teorico | F279: 73 | G279: Other structured types | H279: Theoretical | J279: ¿Cuál de los siguientes pólipos se considera lesión colorrectal avanzada? | K279: Pólipo serrado con displasia | L279: Adenoma tubular de 8 mm | M279: Adenoma con displasia de bajo grado | N279: Pólipo hiperplásico | Q279: 17
...

Sheet Answer Key
A1: Answer Key
A2: Print area: item, controlling letter, and full answer text. Additional source fields remain available electronically to the right.
A4: Item | B4: Correct letter | C4: Correct option text | D4: Region | E4: Year | F4: Source exam | G4: Source Q | H4: Primary type | I4: Flags | J4: Source answer-key PDF | K4: Source key
A5: 1 | B5: D | C5: Las respuestas a) y b) son correctas. | D5: Illes Balears | E5: 2022 | F5: illes-balears/2022 | G5: 1 | H5: Named clinical-case section | J5: AD_ILLES_BALEARS_2022__ANSWER_KEY__answer-key__plantilla-correctora-del-examen.pdf | K5: illes-balears|2022|caso-1|1
A6: 2 | B6: C | C6: La obesidad no ha mostrado ser un factor de riesgo para el desarrollo del cáncer de colon. | D6: Illes Balears | E6: 2022 | F6: illes-balears/2022 | G6: 2 | H6: Named clinical-case section | I6: negated | J6: AD_ILLES_BALEARS_2022__ANSWER_KEY__answer-key__plantilla-correctora-del-examen.pdf | K6: illes-balears|2022|caso-1|2
A7: 3 | B7: A | C7: El cáncer de colon incrementa claramente su incidencia a partir de los 50. | D7: Illes Balears | E7: 2022 | F7: illes-balears/2022 | G7: 3 | H7: Named clinical-case section | J7: AD_ILLES_BALEARS_2022__ANSWER_KEY__answer-key__plantilla-correctora-del-examen.pdf | K7: illes-balears|2022|caso-1|3
A8: 4 | B8: B | C8: La dieta rica en frutas y vegetales disminuye el riesgo de CCR. | D8: Illes Balears | E8: 2022 | F8: illes-balears/2022 | G8: 4 | H8: Named clinical-case section | J8: AD_ILLES_BALEARS_2022__ANSWER_KEY__answer-key__plantilla-correctora-del-examen.pdf | K8: illes-balears|2022|caso-1|4
A9: 5 | B9: B | C9: Cumple criterios para ser incluido en el programa de cribado del CCR. | D9: Illes Balears | E9: 2022 | F9: illes-balears/2022 | G9: 5 | H9: Named clinical-case section | J9: AD_ILLES_BALEARS_2022__ANSWER_KEY__answer-key__plantilla-correctora-del-examen.pdf | K9: illes-balears|2022|caso-1|5
A10: 6 | B10: C | C10: Se debe ofrecer al paciente hacer una colonoscopia. | D10: Illes Balears | E10: 2022 | F10: illes-balears/2022 | G10: 6 | H10: Named clinical-case section | J10: AD_ILLES_BALEARS_2022__ANSWER_KEY__answer-key__plantilla-correctora-del-examen.pdf | K10: illes-balears|2022|caso-1|6
A11: 7 | B11: D | C11: Las endoscopias del programa de cribado pueden hacerse en cualquier gabinete y por cualquier tipo de endoscopista independientemente de su tasa de detección de adenomas. | D11: Illes Balears | E11: 2022 | F11: illes-balears/2022 | G11: 7 | H11: Named clinical-case section | I11: negated | J11: AD_ILLES_BALEARS_2022__ANSWER_KEY__answer-key__plantilla-correctora-del-examen.pdf | K11: illes-balears|2022|caso-1|7
A12: 8 | B12: A | C12: Se debe repetir la colonoscopia para conseguir una puntuación total de 6 puntos (o superior) con un mínimo de dos puntos en cada tramo. | D12: Illes Balears | E12: 2022 | F12: illes-balears/2022 | G12: 8 | H12: Named clinical-case section | J12: AD_ILLES_BALEARS_2022__ANSWER_KEY__answer-key__plantilla-correctora-del-examen.pdf | K12: illes-balears|2022|caso-1|8
A13: 9 | B13: B | C13: La lesión ha quedado curada tras la resección endoscópica. | D13: Illes Balears | E13: 2022 | F13: illes-balears/2022 | G13: 9 | H13: Named clinical-case section | J13: AD_ILLES_BALEARS_2022__ANSWER_KEY__answer-key__plantilla-correctora-del-examen.pdf | K13: illes-balears|2022|caso-1|9
A14: 10 | B14: D | C14: Una revisión endoscópica dentro de tres años es suficiente. | D14: Illes Balears | E14: 2022 | F14: illes-balears/2022 | G14: 10 | H14: Named clinical-case section | J14: AD_ILLES_BALEARS_2022__ANSWER_KEY__answer-key__plantilla-correctora-del-examen.pdf | K14: illes-balears|2022|caso-1|10
A15: 11 | B15: C | C15: En este caso se recomienda el control por medio de una SOH bianual. | D15: Illes Balears | E15: 2022 | F15: illes-balears/2022 | G15: 11 | H15: Named clinical-case section | J15: AD_ILLES_BALEARS_2022__ANSWER_KEY__answer-key__plantilla-correctora-del-examen.pdf | K15: illes-balears|2022|caso-1|11
A16: 12 | B16: B | C16: Requiere colonoscopia por la clínica que presenta para descartar un CCR. | D16: Illes Balears | E16: 2022 | F16: illes-balears/2022 | G16: 12 | H16: Named clinical-case section | J16: AD_ILLES_BALEARS_2022__ANSWER_KEY__answer-key__plantilla-correctora-del-examen.pdf | K16: illes-balears|2022|caso-1|12
A17: 13 | B17: C | C17: Estadio T1N0M0. | D17: Illes Balears | E17: 2022 | F17: illes-balears/2022 | G17: 14 | H17: Named clinical-case section | J17: AD_ILLES_BALEARS_2022__ANSWER_KEY__answer-key__plantilla-correctora-del-examen.pdf | K17: illes-balears|2022|caso-1|14
A18: 14 | B18: C | C18: Es susceptible de una resección en bloque mediante una disección endoscópica submucosa. | D18: Illes Balears | E18: 2022 | F18: illes-balears/2022 | G18: 15 | H18: Named clinical-case section | J18: AD_ILLES_BALEARS_2022__ANSWER_KEY__answer-key__plantilla-correctora-del-examen.pdf | K18: illes-balears|2022|caso-1|15
A19: 15 | B19: A | C19: La resección endoscópica ha sido curativa. | D19: Illes Balears | E19: 2022 | F19: illes-balears/2022 | G19: 16 | H19: Named clinical-case section | J19: AD_ILLES_BALEARS_2022__ANSWER_KEY__answer-key__plantilla-correctora-del-examen.pdf | K19: illes-balears|2022|caso-1|16
A20: 16 | B20: C | C20: Requiere un control endoscópico de forma precoz, que es aceptable a los seis meses. | D20: Illes Balears | E20: 2022 | F20: illes-balears/2022 | G20: 17 | H20: Named clinical-case section | J20: AD_ILLES_BALEARS_2022__ANSWER_KEY__answer-key__plantilla-correctora-del-examen.pdf | K20: illes-balears|2022|caso-1|17
A21: 17 | B21: A | C21: Si es factible, la resección endoscópica de las lesiones ha de ser el tratamiento de elección. | D21: Illes Balears | E21: 2022 | F21: illes-balears/2022 | G21: 18 | H21: Named clinical-case section | J21: AD_ILLES_BALEARS_2022__ANSWER_KEY__answer-key__plantilla-correctora-del-examen.pdf | K21: illes-balears|2022|caso-1|18
A22: 18 | B22: B | C22: Puede ser susceptible de un estudio genético complementario. | D22: Illes Balears | E22: 2022 | F22: illes-balears/2022 | G22: 19 | H22: Named clinical-case section | J22: AD_ILLES_BALEARS_2022__ANSWER_KEY__answer-key__plantilla-correctora-del-examen.pdf | K22: illes-balears|2022|caso-1|19
A23: 19 | B23: A | C23: Poliposis adenomatosa familiar clásica. | D23: Illes Balears | E23: 2022 | F23: illes-balears/2022 | G23: 20 | H23: Named clinical-case section | J23: AD_ILLES_BALEARS_2022__ANSWER_KEY__answer-key__plantilla-correctora-del-examen.pdf | K23: illes-balears|2022|caso-1|20
... A27: 23 | B27: D | C27: Todas las respuestas anteriores son falsas. | D27: Illes Balears | E27: 2022 | F27: illes-balears/2022 | G27: 24 | H27: Named clinical-case section | J27: AD_ILLES_BALEARS_2022__ANSWER_KEY__answer-key__plantilla-correctora-del-examen.pdf | K27: illes-balears|2022|caso-1|24
A28: 24 | B28: B | C28: La endoscopia digestiva está indicada como método diagnóstico inicial en todos los pacientes que muestran síntomas típicos de ERGE. | D28: Illes Balears | E28: 2022 | F28: illes-balears/2022 | G28: 25 | H28: Named clinical-case section | I28: negated | J28: AD_ILLES_BALEARS_2022__ANSWER_KEY__answer-key__plantilla-correctora-supuesto-2.pdf | K28: illes-balears|2022|caso-2|25
A29: 25 | B29: D | C29: En los pacientes con gastroscopia normal y con pirosis que no responden al tratamiento médico con inhibidores de la bomba de protones, se debe descartar una enfermedad por reflujo gastroesofágico y no se deben hacer otros estudios. | D29: Illes Balears | E29: 2022 | F29: illes-balears/2022 | G29: 26 | H29: Named clinical-case section | I29: negated | J29: AD_ILLES_BALEARS_2022__ANSWER_KEY__answer-key__plantilla-correctora-supuesto-2.pdf | K29: illes-balears|2022|caso-2|26
A30: 26 | B30: C | C30: Las alteraciones de la motilidad del cuerpo esofágico no influyen en el reflujo gastroesofágico. | D30: Illes Balears | E30: 2022 | F30: illes-balears/2022 | G30: 27 | H30: Named clinical-case section | I30: negated | J30: AD_ILLES_BALEARS_2022__ANSWER_KEY__answer-key__plantilla-correctora-supuesto-2.pdf | K30: illes-balears|2022|caso-2|27
A31: 27 | B31: B | C31: No hay diferencias en la gravedad de la pirosis entre los diferentes fenotipos de reflujo gastroesofágico. | D31: Illes Balears | E31: 2022 | F31: illes-balears/2022 | G31: 28 | H31: Named clinical-case section | J31: AD_ILLES_BALEARS_2022__ANSWER_KEY__answer-key__plantilla-correctora-supuesto-2.pdf | K31: illes-balears|2022|caso-2|28
A32: 28 | B32: B | C32: Existe una buena correlación entre la intensidad o la frecuencia de los síntomas de ERGE y la gravedad de las lesiones endoscópicas. | D32: Illes Balears | E32: 2022 | F32: illes-balears/2022 | G32: 29 | H32: Named clinical-case section | I32: negated | J32: AD_ILLES_BALEARS_2022__ANSWER_KEY__answer-key__plantilla-correctora-supuesto-2.pdf | K32: illes-balears|2022|caso-2|29
A33: 29 | B33: C | C33: Supone una o más lesiones de la mucosa, con confluencia y afectación menor del 75 % de la circunferencia del esófago. | D33: Illes Balears | E33: 2022 | F33: illes-balears/2022 | G33: 30 | H33: Named clinical-case section | J33: AD_ILLES_BALEARS_2022__ANSWER_KEY__answer-key__plantilla-correctora-supuesto-2.pdf | K33: illes-balears|2022|caso-2|30
A34: 30 | B34: C | C34: Impedancia intraluminal multicanal asociada a pH-metría. | D34: Illes Balears | E34: 2022 | F34: illes-balears/2022 | G34: 31 | H34: Named clinical-case section | J34: AD_ILLES_BALEARS_2022__ANSWER_KEY__answer-key__plantilla-correctora-supuesto-2.pdf | K34: illes-balears|2022|caso-2|31
A35: 31 | B35: C | C35: No interfiere su interpretación si hay alteraciones de la motilidad o histológicas del esófago. | D35: Illes Balears | E35: 2022 | F35: illes-balears/2022 | G35: 32 | H35: Named clinical-case section | I35: negated | J35: AD_ILLES_BALEARS_2022__ANSWER_KEY__answer-key__plantilla-correctora-supuesto-2.pdf | K35: illes-balears|2022|caso-2|32
A36: 32 | B36: D | C36: Edad superior a 50 años sin diferencia de sexo y raza. | D36: Illes Balears | E36: 2022 | F36: illes-balears/2022 | G36: 33 | H36: Named clinical-case section | I36: negated | J36: AD_ILLES_BALEARS_2022__ANSWER_KEY__answer-key__plantilla-correctora-supuesto-2.pdf | K36: illes-balears|2022|caso-2|33
A37: 33 | B37: C | C37: Siempre se aconseja biopsiar un esófago de Barrett en presencia de esofagitis por reflujo. | D37: Illes Balears | E37: 2022 | F37: illes-balears/2022 | G37: 34 | H37: Named clinical-case section | I37: negated | J37: AD_ILLES_BALEARS_2022__ANSWER_KEY__answer-key__plantilla-correctora-supuesto-2.pdf | K37: illes-balears|2022|caso-2|34
A38: 34 | B38: D | C38: Todas las respuestas anteriores son correctas. | D38: Illes Balears | E38: 2022 | F38: illes-balears/2022 | G38: 35 | H38: Named clinical-case section | J38: AD_ILLES_BALEARS_2022__ANSWER_KEY__answer-key__plantilla-correctora-supuesto-2.pdf | K38: illes-balears|2022|caso-2|35
A39: 35 | B39: B | C39: La longitud del esófago. | D39: Illes Balears | E39: 2022 | F39: illes-balears/2022 | G39: 36 | H39: Named clinical-case section | I39: negated | J39: AD_ILLES_BALEARS_2022__ANSWER_KEY__answer-key__plantilla-correctora-supuesto-2.pdf | K39: illes-balears|2022|caso-2|36
A40: 36 | B40: B | C40: Se deben hacer biopsias en botes separados de los cuatro cuadrantes cada 2 cm de esófago de Barrett o cada 1 cm si hay displasia severa previa. | D40: Illes Balears | E40: 2022 | F40: illes-balears/2022 | G40: 37 | H40: Named clinical-case section | J40: AD_ILLES_BALEARS_2022__ANSWER_KEY__answer-key__plantilla-correctora-supuesto-2.pdf | K40: illes-balears|2022|caso-2|37
A41: 37 | B41: C | C41: Ante el hallazgo de displasia indefinida se recomienda una revisión endoscópica en dos años. | D41: Illes Balears | E41: 2022 | F41: illes-balears/2022 | G41: 38 | H41: Named clinical-case section | I41: negated | J41: AD_ILLES_BALEARS_2022__ANSWER_KEY__answer-key__plantilla-correctora-supuesto-2.pdf | K41: illes-balears|2022|caso-2|38
A42: 38 | B42: B | C42: La cirugía antirreflujo se considera una opción más eficaz que el tratamiento médico con IBP para los pacientes con esófago de Barrett. | D42: Illes Balears | E42: 2022 | F42: illes-balears/2022 | G42: 39 | H42: Named clinical-case section | I42: negated | J42: AD_ILLES_BALEARS_2022__ANSWER_KEY__answer-key__plantilla-correctora-supuesto-2.pdf | K42: illes-balears|2022|caso-2|39
A43: 39 | B43: B | C43: La ablación por radiofrecuencia es coste-efectiva en todos los casos de esófago de Barrett de longitud larga (superior a 5 cm). | D43: Illes Balears | E43: 2022 | F43: illes-balears/2022 | G43: 40 | H43: Named clinical-case section | I43: negated | J43: AD_ILLES_BALEARS_2022__ANSWER_KEY__answer-key__plantilla-correctora-supuesto-2.pdf | K43: illes-balears|2022|caso-2|40
A44: 40 | B44: A | C44: Planificar una resección endoscópica de la lesión con displasia de grado alto y posteriormente una ablación con radiofrecuencia de todo el esófago de Barrett. | D44: Illes Balears | E44: 2022 | F44: illes-balears/2022 | G44: 41 | H44: Named clinical-case section | J44: AD_ILLES_BALEARS_2022__ANSWER_KEY__answer-key__plantilla-correctora-supuesto-2.pdf | K44: illes-balears|2022|caso-2|41
A45: 41 | B45: D | C45: Todas las respuestas anteriores son correctas. | D45: Illes Balears | E45: 2022 | F45: illes-balears/2022 | G45: 42 | H45: Named clinical-case section | J45: AD_ILLES_BALEARS_2022__ANSWER_KEY__answer-key__plantilla-correctora-supuesto-2.pdf | K45: illes-balears|2022|caso-2|42
A46: 42 | B46: B | C46: Los factores pronósticos del tumor son favorables por lo que se debe discutir en un equipo multidisciplinar para decidir la actitud terapéutica. | D46: Illes Balears | E46: 2022 | F46: illes-balears/2022 | G46: 43 | H46: Named clinical-case section | J46: AD_ILLES_BALEARS_2022__ANSWER_KEY__answer-key__plantilla-correctora-supuesto-2.pdf | K46: illes-balears|2022|caso-2|43
A47: 43 | B47: D | C47: Una vez hecha la ablación por RFA no necesita ningún seguimiento endoscópico por la recurrencia baja de displasia. | D47: Illes Balears | E47: 2022 | F47: illes-balears/2022 | G47: 44 | H47: Named clinical-case section | I47: negated | J47: AD_ILLES_BALEARS_2022__ANSWER_KEY__answer-key__plantilla-correctora-supuesto-2.pdf | K47: illes-balears|2022|caso-2|44
A48: 44 | B48: D | C48: Raza caucásica. | D48: Illes Balears | E48: 2022 | F48: illes-balears/2022 | G48: 45 | H48: Named clinical-case section | I48: negated | J48: AD_ILLES_BALEARS_2022__ANSWER_KEY__answer-key__plantilla-correctora-supuesto-2.pdf | K48: illes-balears|2022|caso-2|45
A49: 45 | B49: D | C49: La incidencia de adenocarcinoma de esófago está disminuyendo gracias a los avances diagnósticos. | D49: Illes Balears | E49: 2022 | F49: illes-balears/2022 | G49: 47 | H49: Named clinical-case section | I49: negated | J49: AD_ILLES_BALEARS_2022__ANSWER_KEY__answer-key__plantilla-correctora-supuesto-2.pdf | K49: illes-balears|2022|caso-2|47
A50: 46 | B50: B | C50: Crioterapia. | D50: Illes Balears | E50: 2022 | F50: illes-balears/2022 | G50: 48 | H50: Named clinical-case section | J50: AD_ILLES_BALEARS_2022__ANSWER_KEY__answer-key__plantilla-correctora-supuesto-2.pdf | K50: illes-balears|2022|caso-2|48
A51: 47 | B51: C | C51: Pancreatitis crónica calcificante. | D51: Illes Balears | E51: 2022 | F51: illes-balears/2022 | G51: 49 | H51: Named clinical-case section | J51: AD_ILLES_BALEARS_2022__ANSWER_KEY__answer-key__plantilla-correctora-del-examen.pdf | K51: illes-balears|2022|caso-3|49
A52: 48 | B52: B | C52: La historia clínica, los datos analíticos y las pruebas de imagen son suficientes para establecer el diagnóstico. | D52: Illes Balears | E52: 2022 | F52: illes-balears/2022 | G52: 50 | H52: Named clinical-case section | J52: AD_ILLES_BALEARS_2022__ANSWER_KEY__answer-key__plantilla-correctora-del-examen.pdf | K52: illes-balears|2022|caso-3|50
A53: 49 | B53: B | C53: Colangiopancreatografía por resonancia magnética. | D53: Illes Balears | E53: 2022 | F53: illes-balears/2022 | G53: 51 | H53: Named clinical-case section | J53: AD_ILLES_BALEARS_2022__ANSWER_KEY__answer-key__plantilla-correctora-del-examen.pdf | K53: illes-balears|2022|caso-3|51
A54: 50 | B54: D | C54: TIGAR-O. | D54: Illes Balears | E54: 2022 | F54: illes-balears/2022 | G54: 52 | H54: Named clinical-case section | J54: AD_ILLES_BALEARS_2022__ANSWER_KEY__answer-key__plantilla-correctora-del-examen.pdf | K54: illes-balears|2022|caso-3|52
A55: 51 | B55: B | C55: Elastasa fecal pancreática. | D55: Illes Balears | E55: 2022 | F55: illes-balears/2022 | G55: 53 | H55: Named clinical-case section | J55: AD_ILLES_BALEARS_2022__ANSWER_KEY__answer-key__plantilla-correctora-del-examen.pdf | K55: illes-balears|2022|caso-3|53
A56: 52 | B56: B | C56: Peso, índice de masa corporal y determinación de vitaminas liposolubles y otros micronutrientes (magnesio, zinc y vitamina B12). | D56: Illes Balears | E56: 2022 | F56: illes-balears/2022 | G56: 54 | H56: Named clinical-case section | J56: AD_ILLES_BALEARS_2022__ANSWER_KEY__answer-key__plantilla-correctora-del-examen.pdf | K56: illes-balears|2022|caso-3|54
A57: 53 | B57: D | C57: Todas las respuestas anteriores son correctas. | D57: Illes Balears | E57: 2022 | F57: illes-balears/2022 | G57: 55 | H57: Named clinical-case section | J57: AD_ILLES_BALEARS_2022__ANSWER_KEY__answer-key__plantilla-correctora-del-examen.pdf | K57: illes-balears|2022|caso-3|55
A58: 54 | B58: C | C58: Debe iniciarse inmediatamente un tratamiento enzimático sustitutivo. | D58: Illes Balears | E58: 2022 | F58: illes-balears/2022 | G58: 56 | H58: Named clinical-case section | J58: AD_ILLES_BALEARS_2022__ANSWER_KEY__answer-key__plantilla-correctora-del-examen.pdf | K58: illes-balears|2022|caso-3|56
A59: 55 | B59: D | C59: 50.000 U en desayuno, comida y cena y 25.000 U en los snacks. | D59: Illes Balears | E59: 2022 | F59: illes-balears/2022 | G59: 57 | H59: Named clinical-case section | J59: AD_ILLES_BALEARS_2022__ANSWER_KEY__answer-key__plantilla-correctora-del-examen.pdf | K59: illes-balears|2022|caso-3|57
A60: 56 | B60: B | C60: Aumentar la dosis de enzimas pancreáticas y añadir inhibidores de la bomba de protones al TES. | D60: Illes Balears | E60: 2022 | F60: illes-balears/2022 | G60: 58 | H60: Named clinical-case section | J60: AD_ILLES_BALEARS_2022__ANSWER_KEY__answer-key__plantilla-correctora-del-examen.pdf | K60: illes-balears|2022|caso-3|58
A61: 57 | B61: C | C61: ...presenta más riesgo de sobrecrecimiento bacteriano en el intestino delgado (SIBO). | D61: Illes Balears | E61: 2022 | F61: illes-balears/2022 | G61: 59 | H61: Named clinical-case section | J61: AD_ILLES_BALEARS_2022__ANSWER_KEY__answer-key__plantilla-correctora-del-examen.pdf | K61: illes-balears|2022|caso-3|59
... A69: 65 | B69: C | C69: Localmente avanzado. | D69: Illes Balears | E69: 2022 | F69: illes-balears/2022 | G69: 67 | H69: Named clinical-case section | J69: AD_ILLES_BALEARS_2022__ANSWER_KEY__answer-key__plantilla-correctora-del-examen.pdf | K69: illes-balears|2022|caso-3|67
A70: 66 | B70: C | C70: Un 75 % de la población no expresa el antígeno Lewis por lo que los niveles de CA 19-9 no son informativos en estos pacientes. | D70: Illes Balears | E70: 2022 | F70: illes-balears/2022 | G70: 68 | H70: Named clinical-case section | I70: negated | J70: AD_ILLES_BALEARS_2022__ANSWER_KEY__answer-key__plantilla-correctora-del-examen.pdf | K70: illes-balears|2022|caso-3|68
A71: 67 | B71: D | C71: Todas las respuestas anteriores son correctas. | D71: Illes Balears | E71: 2022 | F71: illes-balears/2022 | G71: 69 | H71: Named clinical-case section | J71: AD_ILLES_BALEARS_2022__ANSWER_KEY__answer-key__plantilla-correctora-del-examen.pdf | K71: illes-balears|2022|caso-3|69
A72: 68 | B72: D | C72: La gabapentina puede ser útil en el tratamiento del dolor neuropático. | D72: Illes Balears | E72: 2022 | F72: illes-balears/2022 | G72: 70 | H72: Named clinical-case section | J72: AD_ILLES_BALEARS_2022__ANSWER_KEY__answer-key__plantilla-correctora-del-examen.pdf | K72: illes-balears|2022|caso-3|70
A73: 69 | B73: C | C73: Normalmente aparece como una lesión hiperdensa comparada con el parénquima pancreático adyacente. | D73: Illes Balears | E73: 2022 | F73: illes-balears/2022 | G73: 71 | H73: Named clinical-case section | I73: negated | J73: AD_ILLES_BALEARS_2022__ANSWER_KEY__answer-key__plantilla-correctora-del-examen.pdf | K73: illes-balears|2022|caso-3|71
A74: 70 | B74: D | C74: Todas las respuestas anteriores son ciertas. | D74: Illes Balears | E74: 2022 | F74: illes-balears/2022 | G74: 72 | H74: Named clinical-case section | J74: AD_ILLES_BALEARS_2022__ANSWER_KEY__answer-key__plantilla-correctora-del-examen.pdf | K74: illes-balears|2022|caso-3|72
A75: 71 | B75: C | C75: Enfermedad de Crohn. | D75: Illes Balears | E75: 2022 | F75: illes-balears/2022 | G75: 73 | H75: Named clinical-case section | J75: AD_ILLES_BALEARS_2022__ANSWER_KEY__answer-key__plantilla-correctora-del-examen.pdf | K75: illes-balears|2022|caso-4|73
A76: 72 | B76: D | C76: Todas las respuestas anteriores son correctas. | D76: Illes Balears | E76: 2022 | F76: illes-balears/2022 | G76: 74 | H76: Named clinical-case section | J76: AD_ILLES_BALEARS_2022__ANSWER_KEY__answer-key__plantilla-correctora-del-examen.pdf | K76: illes-balears|2022|caso-4|74
A77: 73 | B77: D | C77: En la colitis ulcerosa la inflamación intestinal es transmural. | D77: Illes Balears | E77: 2022 | F77: illes-balears/2022 | G77: 75 | H77: Named clinical-case section | I77: negated | J77: AD_ILLES_BALEARS_2022__ANSWER_KEY__answer-key__plantilla-correctora-del-examen.pdf | K77: illes-balears|2022|caso-4|75
A78: 74 | B78: A | C78: Edad. | D78: Illes Balears | E78: 2022 | F78: illes-balears/2022 | G78: 76 | H78: Named clinical-case section | J78: AD_ILLES_BALEARS_2022__ANSWER_KEY__answer-key__plantilla-correctora-del-examen.pdf | K78: illes-balears|2022|caso-4|76
A79: 75 | B79: D | C79: Todas las respuestas anteriores son correctas. | D79: Illes Balears | E79: 2022 | F79: illes-balears/2022 | G79: 77 | H79: Named clinical-case section | J79: AD_ILLES_BALEARS_2022__ANSWER_KEY__answer-key__plantilla-correctora-del-examen.pdf | K79: illes-balears|2022|caso-4|77
A80: 76 | B80: C | C80: Resonancia magnética. | D80: Illes Balears | E80: 2022 | F80: illes-balears/2022 | G80: 78 | H80: Named clinical-case section | J80: AD_ILLES_BALEARS_2022__ANSWER_KEY__answer-key__plantilla-correctora-del-examen.pdf | K80: illes-balears|2022|caso-4|78
A81: 77 | B81: C | C81: Sexo masculino. | D81: Illes Balears | E81: 2022 | F81: illes-balears/2022 | G81: 79 | H81: Named clinical-case section | J81: AD_ILLES_BALEARS_2022__ANSWER_KEY__answer-key__plantilla-correctora-del-examen.pdf | K81: illes-balears|2022|caso-4|79
A82: 78 | B82: B | C82: A2 L3 B1. | D82: Illes Balears | E82: 2022 | F82: illes-balears/2022 | G82: 80 | H82: Named clinical-case section | J82: AD_ILLES_BALEARS_2022__ANSWER_KEY__answer-key__plantilla-correctora-del-examen.pdf | K82: illes-balears|2022|caso-4|80
A83: 79 | B83: C | C83: Corticoides. | D83: Illes Balears | E83: 2022 | F83: illes-balears/2022 | G83: 81 | H83: Named clinical-case section | J83: AD_ILLES_BALEARS_2022__ANSWER_KEY__answer-key__plantilla-correctora-del-examen.pdf | K83: illes-balears|2022|caso-4|81
A84: 80 | B84: D | C84: Todas las respuestas anteriores son correctas. | D84: Illes Balears | E84: 2022 | F84: illes-balears/2022 | G84: 82 | H84: Named clinical-case section | J84: AD_ILLES_BALEARS_2022__ANSWER_KEY__answer-key__plantilla-correctora-del-examen.pdf | K84: illes-balears|2022|caso-4|82
A85: 81 | B85: B | C85: Los corticoides se utilizan como tratamiento de mantenimiento en la enfermedad de Crohn. | D85: Illes Balears | E85: 2022 | F85: illes-balears/2022 | G85: 83 | H85: Named clinical-case section | I85: negated | J85: AD_ILLES_BALEARS_2022__ANSWER_KEY__answer-key__plantilla-correctora-del-examen.pdf | K85: illes-balears|2022|caso-4|83
A86: 82 | B86: D | C86: La azatioprina está recomendada para el mantenimiento de la remisión en pacientes con enfermedad de Crohn corticodependiente. | D86: Illes Balears | E86: 2022 | F86: illes-balears/2022 | G86: 84 | H86: Named clinical-case section | J86: AD_ILLES_BALEARS_2022__ANSWER_KEY__answer-key__plantilla-correctora-del-examen.pdf | K86: illes-balears|2022|caso-4|84
A87: 83 | B87: C | C87: Calprotectina fecal. | D87: Illes Balears | E87: 2022 | F87: illes-balears/2022 | G87: 85 | H87: Named clinical-case section | J87: AD_ILLES_BALEARS_2022__ANSWER_KEY__answer-key__plantilla-correctora-del-examen.pdf | K87: illes-balears|2022|caso-4|85
A88: 84 | B88: A | C88: Tofacitinib. | D88: Illes Balears | E88: 2022 | F88: illes-balears/2022 | G88: 86 | H88: Named clinical-case section | J88: AD_ILLES_BALEARS_2022__ANSWER_KEY__answer-key__plantilla-correctora-del-examen.pdf | K88: illes-balears|2022|caso-4|86
A89: 85 | B89: C | C89: Siempre deben monitorizarse los niveles de biológicos. | D89: Illes Balears | E89: 2022 | F89: illes-balears/2022 | G89: 87 | H89: Named clinical-case section | I89: negated | J89: AD_ILLES_BALEARS_2022__ANSWER_KEY__answer-key__plantilla-correctora-del-examen.pdf | K89: illes-balears|2022|caso-4|87
A90: 86 | B90: B | C90: El tratamiento quirúrgico es el tratamiento de elección de las fístulas. | D90: Illes Balears | E90: 2022 | F90: illes-balears/2022 | G90: 88 | H90: Named clinical-case section | I90: negated | J90: AD_ILLES_BALEARS_2022__ANSWER_KEY__answer-key__plantilla-correctora-del-examen.pdf | K90: illes-balears|2022|caso-4|88
A91: 87 | B91: B | C91: Tipo de cirugía. | D91: Illes Balears | E91: 2022 | F91: illes-balears/2022 | G91: 90 | H91: Named clinical-case section | J91: AD_ILLES_BALEARS_2022__ANSWER_KEY__answer-key__plantilla-correctora-del-examen.pdf | K91: illes-balears|2022|caso-4|90
A92: 88 | B92: B | C92: A los 6 meses. | D92: Illes Balears | E92: 2022 | F92: illes-balears/2022 | G92: 91 | H92: Named clinical-case section | J92: AD_ILLES_BALEARS_2022__ANSWER_KEY__answer-key__plantilla-correctora-del-examen.pdf | K92: illes-balears|2022|caso-4|91
A93: 89 | B93: C | C93: Más de cinco aftas o lesiones ulceradas con mucosa normal entre las lesiones a menos de 1 cm de la anastomosis. | D93: Illes Balears | E93: 2022 | F93: illes-balears/2022 | G93: 92 | H93: Named clinical-case section | J93: AD_ILLES_BALEARS_2022__ANSWER_KEY__answer-key__plantilla-correctora-del-examen.pdf | K93: illes-balears|2022|caso-4|92
A94: 90 | B94: D | C94: Todas las mujeres con enfermedad inflamatoria intestinal tienen menos fertilidad que la población general. | D94: Illes Balears | E94: 2022 | F94: illes-balears/2022 | G94: 93 | H94: Named clinical-case section | I94: negated | J94: AD_ILLES_BALEARS_2022__ANSWER_KEY__answer-key__plantilla-correctora-del-examen.pdf | K94: illes-balears|2022|caso-4|93
A95: 91 | B95: A | C95: Budesonida. | D95: Illes Balears | E95: 2022 | F95: illes-balears/2022 | G95: 94 | H95: Named clinical-case section | J95: AD_ILLES_BALEARS_2022__ANSWER_KEY__answer-key__plantilla-correctora-del-examen.pdf | K95: illes-balears|2022|caso-4|94
A96: 92 | B96: B | C96: Durante el tratamiento con vedolizumab se pueden administrar vacunas de virus vivos. | D96: Illes Balears | E96: 2022 | F96: illes-balears/2022 | G96: 95 | H96: Named clinical-case section | I96: negated | J96: AD_ILLES_BALEARS_2022__ANSWER_KEY__answer-key__plantilla-correctora-del-examen.pdf | K96: illes-balears|2022|caso-4|95
A97: 93 | B97: D | C97: Se une a la subunidad p40 de la interleuquina12/23. | D97: Illes Balears | E97: 2022 | F97: illes-balears/2022 | G97: 96 | H97: Named clinical-case section | J97: AD_ILLES_BALEARS_2022__ANSWER_KEY__answer-key__plantilla-correctora-del-examen.pdf | K97: illes-balears|2022|caso-4|96
A98: 94 | B98: A | C98: La CU es un proceso inflamatorio crónico que característicamente afecta todo el espesor de la pared colónica. | D98: Illes Balears | E98: 2022 | F98: illes-balears/2022 | G98: 97 | H98: Named clinical-case section | I98: negated | J98: AD_ILLES_BALEARS_2022__ANSWER_KEY__answer-key__plantilla-correctora-del-examen.pdf | K98: illes-balears|2022|caso-5|97
A99: 95 | B99: D | C99: La prevalencia es más importante en países subdesarrollados. | D99: Illes Balears | E99: 2022 | F99: illes-balears/2022 | G99: 98 | H99: Named clinical-case section | I99: negated | J99: AD_ILLES_BALEARS_2022__ANSWER_KEY__answer-key__plantilla-correctora-del-examen.pdf | K99: illes-balears|2022|caso-5|98
A100: 96 | B100: A | C100: La afectación de familiares de primer grado aumenta el riesgo de desarrollar la patología. | D100: Illes Balears | E100: 2022 | F100: illes-balears/2022 | G100: 99 | H100: Named clinical-case section | J100: AD_ILLES_BALEARS_2022__ANSWER_KEY__answer-key__plantilla-correctora-del-examen.pdf | K100: illes-balears|2022|caso-5|99
A101: 97 | B101: A | C101: El diagnóstico de la CU se establece por la suma de criterios clínicos, analíticos, endoscópicos e histológicos. | D101: Illes Balears | E101: 2022 | F101: illes-balears/2022 | G101: 100 | H101: Named clinical-case section | J101: AD_ILLES_BALEARS_2022__ANSWER_KEY__answer-key__plantilla-correctora-del-examen.pdf | K101: illes-balears|2022|caso-5|100
A102: 98 | B102: B | C102: Mesalazina en enemas para inducir la remisión y la pautar como tratamiento de mantenimiento. | D102: Illes Balears | E102: 2022 | F102: illes-balears/2022 | G102: 101 | H102: Named clinical-case section | J102: AD_ILLES_BALEARS_2022__ANSWER_KEY__answer-key__plantilla-correctora-del-examen.pdf | K102: illes-balears|2022|caso-5|101
A103: 99 | B103: B | C103: Los medicamentos antiinflamatorios no esteroides (AINES) están completamente contraindicados en la CU. | D103: Illes Balears | E103: 2022 | F103: illes-balears/2022 | G103: 102 | H103: Named clinical-case section | I103: negated | J103: AD_ILLES_BALEARS_2022__ANSWER_KEY__answer-key__plantilla-correctora-del-examen.pdf | K103: illes-balears|2022|caso-5|102
A104: 100 | B104: D | C104: Todas las respuestas anteriores son correctas. | D104: Illes Balears | E104: 2022 | F104: illes-balears/2022 | G104: 103 | H104: Named clinical-case section | J104: AD_ILLES_BALEARS_2022__ANSWER_KEY__answer-key__plantilla-correctora-del-examen.pdf | K104: illes-balears|2022|caso-5|103
A105: 101 | B105: C | C105: En este caso se debe completar el estudio con una nueva colonoscopia o una rectosigmoidoscopia con toma de biopsias y se deben descartar infecciones por citomegalovirus (CMV) o Clostridium. | D105: Illes Balears | E105: 2022 | F105: illes-balears/2022 | G105: 104 | H105: Named clinical-case section | J105: AD_ILLES_BALEARS_2022__ANSWER_KEY__answer-key__plantilla-correctora-del-examen.pdf | K105: illes-balears|2022|caso-5|104
A106: 102 | B106: A | C106: Los corticoides sistémicos vía oral deben ser la primera opción de tratamiento con un fuerte grado de recomendación en las guías de la European Crohn and Colitis Organization (ECCO) fundamentado en un nivel alto de evidencia en la literatura. | D106: Illes Balears | E106: 2022 | F106: illes-balears/2022 | G106: 105 | H106: Named clinical-case section | I106: negated | J106: AD_ILLES_BALEARS_2022__ANSWER_KEY__answer-key__plantilla-correctora-del-examen.pdf | K106: illes-balears|2022|caso-5|105
A107: 103 | B107: D | C107: Las respuestas b) y c) son correctas. | D107: Illes Balears | E107: 2022 | F107: illes-balears/2022 | G107: 106 | H107: Named clinical-case section | J107: AD_ILLES_BALEARS_2022__ANSWER_KEY__answer-key__plantilla-correctora-del-examen.pdf | K107: illes-balears|2022|caso-5|106
A108: 104 | B108: B | C108: Para inducir la remisión, vedolizumab es superior a cualquier anti-TNF. | D108: Illes Balears | E108: 2022 | F108: illes-balears/2022 | G108: 107 | H108: Named clinical-case section | I108: negated | J108: AD_ILLES_BALEARS_2022__ANSWER_KEY__answer-key__plantilla-correctora-del-examen.pdf | K108: illes-balears|2022|caso-5|107
A109: 105 | B109: C | C109: Vedolizumab y ustekinumab tienen menos riesgo de infecciones graves que los anti-TNF. | D109: Illes Balears | E109: 2022 | F109: illes-balears/2022 | G109: 108 | H109: Named clinical-case section | J109: AD_ILLES_BALEARS_2022__ANSWER_KEY__answer-key__plantilla-correctora-del-examen.pdf | K109: illes-balears|2022|caso-5|108
A110: 106 | B110: D | C110: Si la ecografía y la colangioresonancia son normales debe hacerse una biopsia hepática. | D110: Illes Balears | E110: 2022 | F110: illes-balears/2022 | G110: 109 | H110: Named clinical-case section | J110: AD_ILLES_BALEARS_2022__ANSWER_KEY__answer-key__plantilla-correctora-del-examen.pdf | K110: illes-balears|2022|caso-5|109
A111: 107 | B111: C | C111: Los fármacos anti-TNF utilizados en los pacientes con CU y CEP han demostrado una mejoría en la colestasis crónica y en la evolución de la CEP. | D111: Illes Balears | E111: 2022 | F111: illes-balears/2022 | G111: 110 | H111: Named clinical-case section | I111: negated | J111: AD_ILLES_BALEARS_2022__ANSWER_KEY__answer-key__plantilla-correctora-del-examen.pdf | K111: illes-balears|2022|caso-5|110
...

Sheet Case Contexts
A1: Selected Shared Clinical Contexts
A2: Electronic trace table; complete print-readable contexts are inline in Questionnaire. Long source text is split here into visible continuation rows.
A4: Context ID | B4: Kind / part | C4: Clinical context | D4: Questionnaire items | E4: Source pair | F4: Source question numbers | G4: PDF pages | H4: Source exam PDF | I4: Source PDF SHA256
A5: illes-balears-2022-base-caso-1 | B5: Base case narrative · 1/1 | C5: Paciente de 57 años, sin antecedentes personales ni familiares de cáncer de colon ni de cáncer en otras localizaciones, fumador de 22 cigarrillos al día, con hábitos de vida sedentarios, enolismo de 60 gr/día, obesidad con un índice de masa corporal de 37 y una dieta rica en carnes rojas y procesadas. | D5: 1, 2, 3, 4, 5, 6, 7, 8, 9, 10, 11, 12, 13, 14, 15, 16, 17, 18, 19, 20, 21, 22, 23 | E5: illes-balears/2022 | F5: 1-24 | G5: 3 | H5: exams-other-regions-spain-pdfs/illes-balears/2022/exam/exam__cuadernillo-de-examen-aparato-digestivo-fea.pdf | I5: c90fbb40ff4e10d7c01d175f5d2da8cb90bc002c4c856e378ad6a75908faf626
A6: illes-balears-2022-base-caso-2 | B6: Base case narrative · 1/3 | C6: Varón de 63 años remitido a la unidad de endoscopia para hacerle una gastroscopia por un reflujo de larga evolución (superior a 10 años). El paciente es obeso, hipertenso y fumador. Refiere disfagia a sólidos desde hace un mes. Se hace una gastroscopia que detecta a 32 cm de las arcadas dentarias la presencia de una mucosa ectópica que se extiende hasta la unión esofagogástrica situada a 38 cm de las arcadas dentarias en donde se aprecian signos de esofagitis por reflujo grado C. | D6: 24, 25, 26, 27, 28, 29, 30, 31, 32, 33, 34, 35, 36, 37, 38, 39, 40, 41, 42, 43, 44, 45, 46 | E6: illes-balears/2022 | F6: 25-48 | G6: 11 | H6: exams-other-regions-spain-pdfs/illes-balears/2022/exam/exam__cuadernillo-de-examen-aparato-digestivo-fea.pdf | I6: c90fbb40ff4e10d7c01d175f5d2da8cb90bc002c4c856e378ad6a75908faf626
A7: illes-balears-2022-base-caso-2 | B7: Base case narrative · 2/3 | C7: Se pauta un tratamiento médico y se hace una nueva gastroscopia a las ocho semanas. En ella se aprecia la mucosa ectópica descrita previamente sugestiva de esófago de Barrett (C5M6) con una cicatrización completa de la esofagitis por reflujo y a 35 cm de las arcadas dentarias se aprecia un área irregular sobreelevada de unos 8 mm (0-Is) diferente al resto de la mucosa circundante. Se hacen biopsias de forma aleatoria de la lesión descrita, suponiendo que puede tratarse de un esófago de Barrett según el protocolo de Seattle. Los resultados de la lesión visible en el esófago confirman un esófago | D7: 24, 25, 26, 27, 28, 29, 30, 31, 32, 33, 34, 35, 36, 37, 38, 39, 40, 41, 42, 43, 44, 45, 46 | E7: illes-balears/2022 | F7: 25-48 | G7: 11 | H7: exams-other-regions-spain-pdfs/illes-balears/2022/exam/exam__cuadernillo-de-examen-aparato-digestivo-fea.pdf | I7: c90fbb40ff4e10d7c01d175f5d2da8cb90bc002c4c856e378ad6a75908faf626
A8: illes-balears-2022-base-caso-2 | B8: Base case narrative · 3/3 | C8: de Barrett con metaplasia intestinal y presencia de focos de displasia de grado alto y las biopsias aleatorias confirmaban el esófago de Barrett sin displasia. Se planifica una estrategia de tratamiento y seguimiento. | D8: 24, 25, 26, 27, 28, 29, 30, 31, 32, 33, 34, 35, 36, 37, 38, 39, 40, 41, 42, 43, 44, 45, 46 | E8: illes-balears/2022 | F8: 25-48 | G8: 11 | H8: exams-other-regions-spain-pdfs/illes-balears/2022/exam/exam__cuadernillo-de-examen-aparato-digestivo-fea.pdf | I8: c90fbb40ff4e10d7c01d175f5d2da8cb90bc002c4c856e378ad6a75908faf626
A9: illes-balears-2022-base-caso-3 | B9: Base case narrative · 1/3 | C9: Paciente varón de 62 años con antecedentes de enolismo superior a 60 g/día de veinte años de evolución y fumador de 25 paquetes/año desde los 17 años. Antecedente de dos ingresos por pancreatitis agudas leves en los últimos tres años. En los últimos tres meses presenta un cuadro de diarrea en forma de cuatro deposiciones al día, dolor abdominal continuo y diario, localizado en el epigastrio que no mejora con paracetamol. Además, refiere que ha perdido cuatro quilos. Se le hace una gastroscopia que es normal. Una TC abdominal revela la presencia de múltiples calcificaciones parenquimatosas en | D9: 47, 48, 49, 50, 51, 52, 53, 54, 55, 56, 57, 58, 59, 60, 61, 62, 63, 64, 65, 66, 67, 68, 69, 70 | E9: illes-balears/2022 | F9: 49-72 | G9: 19 | H9: exams-other-regions-spain-pdfs/illes-balears/2022/exam/exam__cuadernillo-de-examen-aparato-digestivo-fea.pdf | I9: c90fbb40ff4e10d7c01d175f5d2da8cb90bc002c4c856e378ad6a75908faf626
A10: illes-balears-2022-base-caso-3 | B10: Base case narrative · 2/3 | C10: la cabeza del páncreas, dilatación del conducto pancreático principal, una lesión quística de 10 mm en el cuerpo pancreático y atrofia de la cola de páncreas. Los coprocultivos, los parásitos en heces y la toxina de Clostridium difficile en heces son negativos, la serología de celiaquía negativa y las hormonas tiroideas son normales. Elementos relevantes de la analítica. Glucosa: 124 mg/dl, GGT: 101 U/L, AST: 55 U/L, ALT: 65 U/L, VCM: 102 fl, BI total: 1,4 mg/dl, triglicéridos: 180 mg/dl, amilasa: 125 U/L, lipasa: 25 U/L. | D10: 47, 48, 49, 50, 51, 52, 53, 54, 55, 56, 57, 58, 59, 60, 61, 62, 63, 64, 65, 66, 67, 68, 69, 70 | E10: illes-balears/2022 | F10: 49-72 | G10: 19 | H10: exams-other-regions-spain-pdfs/illes-balears/2022/exam/exam__cuadernillo-de-examen-aparato-digestivo-fea.pdf | I10: c90fbb40ff4e10d7c01d175f5d2da8cb90bc002c4c856e378ad6a75908faf626
A11: illes-balears-2022-base-caso-3 | B11: Base case narrative · 3/3 | C11: El resto del hemograma y de la bioquímica está dentro de valores normales. | D11: 47, 48, 49, 50, 51, 52, 53, 54, 55, 56, 57, 58, 59, 60, 61, 62, 63, 64, 65, 66, 67, 68, 69, 70 | E11: illes-balears/2022 | F11: 49-72 | G11: 19 | H11: exams-other-regions-spain-pdfs/illes-balears/2022/exam/exam__cuadernillo-de-examen-aparato-digestivo-fea.pdf | I11: c90fbb40ff4e10d7c01d175f5d2da8cb90bc002c4c856e378ad6a75908faf626
A12: illes-balears-2022-caso-3-transition-01 | B12: Shared clinical context · 1/1 | C12: Las pruebas para determinar la insuficiencia pancreática exocrina demuestran una insuficiencia pancreática exocrina (IPE) grave. | D12: 53, 54, 55, 56, 57, 58, 59, 60, 61, 62, 63, 64, 65, 66, 67, 68, 69, 70 | E12: illes-balears/2022 | F12: 55,56,57,58,59,60,61 | G12: 21 | H12: exams-other-regions-spain-pdfs/illes-balears/2022/exam/exam__cuadernillo-de-examen-aparato-digestivo-fea.pdf | I12: c90fbb40ff4e10d7c01d175f5d2da8cb90bc002c4c856e378ad6a75908faf626
A13: illes-balears-2022-caso-3-transition-02 | B13: Shared clinical context · 1/1 | C13: 22 meses después del diagnóstico el paciente ingresa por ictericia conjuntival y cutánea con cifras de bilirrubina de 9 mg/dl (de predominio directo) y colestasis marcada en la analítica. Una ecografía abdominal en urgencias muestra una dilatación de la vía biliar extrahepática. | D13: 60, 61, 62, 63, 64, 65, 66, 67, 68, 69, 70 | E13: illes-balears/2022 | F13: 62 | G13: 22 | H13: exams-other-regions-spain-pdfs/illes-balears/2022/exam/exam__cuadernillo-de-examen-aparato-digestivo-fea.pdf | I13: c90fbb40ff4e10d7c01d175f5d2da8cb90bc002c4c856e378ad6a75908faf626
A14: illes-balears-2022-caso-3-transition-03 | B14: Shared clinical context · 1/1 | C14: Una TC abdominal con protocolo pancreático objetiva una lesión sólida en la cabeza del páncreas de 2,7 x 2,5 cm con dilatación de la vía biliar extrahepática de 13 mm. No se observan lesiones hepáticas ocupantes de espacio. La lesión está en contacto con la arteria mesentérica superior en más de 180° con presencia de una trombosis portal. | D14: 61, 62, 63, 64, 65, 66, 67, 68, 69, 70 | E14: illes-balears/2022 | F14: 63,64,65,66,67,68,69,70,71,72 | G14: 23 | H14: exams-other-regions-spain-pdfs/illes-balears/2022/exam/exam__cuadernillo-de-examen-aparato-digestivo-fea.pdf | I14: c90fbb40ff4e10d7c01d175f5d2da8cb90bc002c4c856e378ad6a75908faf626
A15: illes-balears-2022-base-caso-4 | B15: Base case narrative · 1/3 | C15: Mujer de 18 años sin antecedentes personales ni familiares de interés y sin hábitos tóxicos. Ingresa por fiebre, pérdida de peso asociada a hiporexia, diarrea de comienzo reciente sin productos patológicos y dolor abdominal de dos semanas de evolución. Exploración. Temperatura: 37,6 °C; TA: 100/60 mmHg; consciente, orientada, eupneica; peso: 40 quilos, talla: 155 cm, delgadez, retraso del desarrollo puberal, palidez discreta, bien hidratada y perfundida. No se palparon adenopatías. La auscultación cardiorrespiratoria fue normal y la exploración abdominal no mostró hallazgos de interés. En la | D15: 71, 72, 73, 74, 75, 76, 77, 78, 79, 80, 81, 82, 83, 84, 85, 86, 87, 88, 89, 90, 91, 92, 93 | E15: illes-balears/2022 | F15: 73-96 | G15: 26 | H15: exams-other-regions-spain-pdfs/illes-balears/2022/exam/exam__cuadernillo-de-examen-aparato-digestivo-fea.pdf | I15: c90fbb40ff4e10d7c01d175f5d2da8cb90bc002c4c856e378ad6a75908faf626
... A79: andalucia-2021-22-libre-case-013 | B79: Shared clinical context · 1/1 | C79: Paciente varón de 64 años de edad con antecedentes de cirrosis hepática compensada con hipertensión portal, que acude a la consulta externa de Aparato Digestivo por dispepsia de 3 meses de evolución. Ante esta situación, se realiza una gastroscopia que revela una lesión sobre-elevada de 25 mm en cara anterior del cuerpo gástrico proximal con depresión central, no ulcerada. El estudio histopatológico de las biopsias revela un adenocarcinoma gástrico bien diferenciado. | D79: 494 | E79: andalucia/2021-22-libre | F79: 143,144,145,146 | G79: 39 | H79: exams-other-regions-spain-pdfs/andalucia/2021-22-libre/exam/07__9122-aparato-digestivo-pdf.pdf | I79: 0c2550a488a3ff52c35c9585e819e37790ac375690067e1f2cd064b123f0cc2d

Sheet Visuals
A1: Selected Source Visuals
A2: This image-free release contains no selected image-linked questions. The sheet is retained as an explicit audit surface.
A4: Visual ID | B4: Questionnaire items | C4: Source pair | D4: Source question numbers | E4: PDF page | F4: Description | G4: Source exam PDF | H4: Asset SHA256 | I4: Source PDF SHA256
A5: No visual assets are required: all READY rows carrying a Visual ID were excluded before deterministic quota selection.

Sheet Selection Ledger
A1: Selection and Traceability Ledger
A2: Electronic-only audit table. Every item maps to one immutable source row with source, answer, flag, comment, and deterministic-selection evidence.
A3: Item | B3: Source row | C3: Source key | D3: Region | E3: Year | F3: Source pair | G3: Exam part | H3: Source Q | I3: Primary type | J3: Formal question type | K3: Selection reason | L3: Mandatory | M3: Wording | N3: Flags | O3: Needs attention | P3: Correct letter | Q3: Correct option text | R3: Effective context IDs | S3: Visual ID | T3: PDF page | U3: Source exam PDF | V3: Source answer-key PDF | W3: Content SHA256 | X3: Selection score | Y3: Source repair comments | Z3: Source case ID | AA3: Clinical format | AB3: Scored
A4: 1 | B4: 2272 | C4: illes-balears|2022|caso-1|1 | D4: Illes Balears | E4: 2022 | F4: illes-balears/2022 | G4: caso-1 | H4: 1 | I4: Named clinical-case section | J4: Named clinical-case section | K4: mandatory_named_case | L4: Yes | M4: Positive / standard | P4: D | Q4: Las respuestas a) y b) son correctas. | R4: illes-balears-2022-base-caso-1 | T4: 3 | U4: AD_ILLES_BALEARS_2022__EXAM__exam__cuadernillo-de-examen-aparato-digestivo-fea.pdf | V4: AD_ILLES_BALEARS_2022__ANSWER_KEY__answer-key__plantilla-correctora-del-examen.pdf | W4: a0ff5563869acb431480bfd8bc75e5bbeb5f63d999e3fd532457ca40791b8d82 | X4: dd96f8043881100bbfef3eff82d6c9c148202d5dbec14a4d5c8d739ec7385367 | AA4: Named case block | AB4: Yes
A5: 2 | B5: 2273 | C5: illes-balears|2022|caso-1|2 | D5: Illes Balears | E5: 2022 | F5: illes-balears/2022 | G5: caso-1 | H5: 2 | I5: Named clinical-case section | J5: Named clinical-case section | K5: mandatory_named_case | L5: Yes | M5: Negated / exception | N5: negated | P5: C | Q5: La obesidad no ha mostrado ser un factor de riesgo para el desarrollo del cáncer de colon. | R5: illes-balears-2022-base-caso-1 | T5: 3 | U5: AD_ILLES_BALEARS_2022__EXAM__exam__cuadernillo-de-examen-aparato-digestivo-fea.pdf | V5: AD_ILLES_BALEARS_2022__ANSWER_KEY__answer-key__plantilla-correctora-del-examen.pdf | W5: 07a23a2bdd3c6899611ce482adeca8eb151e4b7a102b9b03d85cf3a69ee7bec3 | X5: 3a7fc54854636e0b77c6c50dfc421a2ebf6fc1b98716d3c2ee5c0cf160de4461 | AA5: Named case block | AB5: Yes
A6: 3 | B6: 2274 | C6: illes-balears|2022|caso-1|3 | D6: Illes Balears | E6: 2022 | F6: illes-balears/2022 | G6: caso-1 | H6: 3 | I6: Named clinical-case section | J6: Named clinical-case section | K6: mandatory_named_case | L6: Yes | M6: Positive / standard | P6: A | Q6: El cáncer de colon incrementa claramente su incidencia a partir de los 50. | R6: illes-balears-2022-base-caso-1 | T6: 3 | U6: AD_ILLES_BALEARS_2022__EXAM__exam__cuadernillo-de-examen-aparato-digestivo-fea.pdf | V6: AD_ILLES_BALEARS_2022__ANSWER_KEY__answer-key__plantilla-correctora-del-examen.pdf | W6: 566493c08e1fb0364c6a2c0276405c754f92580e8298d2b090f92c39d4b34336 | X6: 9a1181d9b587ab1ea912edf4cbb61e4307baad774f60dff160d6062d89054eaf | AA6: Named case block | AB6: Yes
A7: 4 | B7: 2275 | C7: illes-balears|2022|caso-1|4 | D7: Illes Balears | E7: 2022 | F7: illes-balears/2022 | G7: caso-1 | H7: 4 | I7: Named clinical-case section | J7: Named clinical-case section | K7: mandatory_named_case | L7: Yes | M7: Positive / standard | P7: B | Q7: La dieta rica en frutas y vegetales disminuye el riesgo de CCR. | R7: illes-balears-2022-base-caso-1 | T7: 4 | U7: AD_ILLES_BALEARS_2022__EXAM__exam__cuadernillo-de-examen-aparato-digestivo-fea.pdf | V7: AD_ILLES_BALEARS_2022__ANSWER_KEY__answer-key__plantilla-correctora-del-examen.pdf | W7: 6181e50b2b33a05ba0ab3c2757fa7af006495f76779afc10883bca9a0c945ca2 | X7: 7723e887c47345e43ca6e8a10f816e51861eaa6af459a5db251089510c5b24cb | AA7: Named case block | AB7: Yes
A8: 5 | B8: 2276 | C8: illes-balears|2022|caso-1|5 | D8: Illes Balears | E8: 2022 | F8: illes-balears/2022 | G8: caso-1 | H8: 5 | I8: Named clinical-case section | J8: Named clinical-case section | K8: mandatory_named_case | L8: Yes | M8: Positive / standard | P8: B | Q8: Cumple criterios para ser incluido en el programa de cribado del CCR. | R8: illes-balears-2022-base-caso-1 | T8: 4 | U8: AD_ILLES_BALEARS_2022__EXAM__exam__cuadernillo-de-examen-aparato-digestivo-fea.pdf | V8: AD_ILLES_BALEARS_2022__ANSWER_KEY__answer-key__plantilla-correctora-del-examen.pdf | W8: 5542fadb1335631c34a095acfefddb43d0a31ff90540b0f15ead867f23325519 | X8: 3ebc505224f4118b14635d1e00ef3bdd244afe15cb9f17eef1425d815591243d | AA8: Named case block | AB8: Yes
A9: 6 | B9: 2277 | C9: illes-balears|2022|caso-1|6 | D9: Illes Balears | E9: 2022 | F9: illes-balears/2022 | G9: caso-1 | H9: 6 | I9: Named clinical-case section | J9: Named clinical-case section | K9: mandatory_named_case | L9: Yes | M9: Positive / standard | P9: C | Q9: Se debe ofrecer al paciente hacer una colonoscopia. | R9: illes-balears-2022-base-caso-1 | T9: 4 | U9: AD_ILLES_BALEARS_2022__EXAM__exam__cuadernillo-de-examen-aparato-digestivo-fea.pdf | V9: AD_ILLES_BALEARS_2022__ANSWER_KEY__answer-key__plantilla-correctora-del-examen.pdf | W9: 959ccdbeb722e1ed27257935fa1b7c342a6d305250318aa3a0e7a817c562a718 | X9: 54b28899ada20b86d4120845ad02224ba5e02d49d6b0c2ce2616175bcab659d7 | AA9: Named case block | AB9: Yes
A10: 7 | B10: 2278 | C10: illes-balears|2022|caso-1|7 | D10: Illes Balears | E10: 2022 | F10: illes-balears/2022 | G10: caso-1 | H10: 7 | I10: Named clinical-case section | J10: Named clinical-case section | K10: mandatory_named_case | L10: Yes | M10: Negated / exception | N10: negated | P10: D | Q10: Las endoscopias del programa de cribado pueden hacerse en cualquier gabinete y por cualquier tipo de endoscopista independientemente de su tasa de detección de adenomas. | R10: illes-balears-2022-base-caso-1 | T10: 5 | U10: AD_ILLES_BALEARS_2022__EXAM__exam__cuadernillo-de-examen-aparato-digestivo-fea.pdf | V10: AD_ILLES_BALEARS_2022__ANSWER_KEY__answer-key__plantilla-correctora-del-examen.pdf | W10: 11625cd44dba8c7ea369809a9dfe4ce219882d7fc76401778d7565c2e06ca0b9 | X10: 42b91bfa7ffca12622e8e55f28711fee26f50c46bca65e28cb2d7b99071ed13a | AA10: Named case block | AB10: Yes
A11: 8 | B11: 2279 | C11: illes-balears|2022|caso-1|8 | D11: Illes Balears | E11: 2022 | F11: illes-balears/2022 | G11: caso-1 | H11: 8 | I11: Named clinical-case section | J11: Named clinical-case section | K11: mandatory_named_case | L11: Yes | M11: Positive / standard | P11: A | Q11: Se debe repetir la colonoscopia para conseguir una puntuación total de 6 puntos (o superior) con un mínimo de dos puntos en cada tramo. | R11: illes-balears-2022-base-caso-1 | T11: 5 | U11: AD_ILLES_BALEARS_2022__EXAM__exam__cuadernillo-de-examen-aparato-digestivo-fea.pdf | V11: AD_ILLES_BALEARS_2022__ANSWER_KEY__answer-key__plantilla-correctora-del-examen.pdf | W11: 92413aec254f6945368eea44ca720f415b16402ac50be3db7f25ac8a06951075 | X11: aa72f2ab98e1441c41296d648701fc8be27a182c9ff24a80b30ac73da492e4d0 | AA11: Named case block | AB11: Yes
A12: 9 | B12: 2280 | C12: illes-balears|2022|caso-1|9 | D12: Illes Balears | E12: 2022 | F12: illes-balears/2022 | G12: caso-1 | H12: 9 | I12: Named clinical-case section | J12: Named clinical-case section | K12: mandatory_named_case | L12: Yes | M12: Positive / standard | P12: B | Q12: La lesión ha quedado curada tras la resección endoscópica. | R12: illes-balears-2022-base-caso-1 | T12: 6 | U12: AD_ILLES_BALEARS_2022__EXAM__exam__cuadernillo-de-examen-aparato-digestivo-fea.pdf | V12: AD_ILLES_BALEARS_2022__ANSWER_KEY__answer-key__plantilla-correctora-del-examen.pdf | W12: 4d35a80c2ab6502131f84057b3759c49efdcabf8f25ffec9782d180f40b51443 | X12: 7139238159efdcc65e0ab496f8fda23fdfdb082d9c7836fcbebd2c0dca380bc4 | AA12: Named case block | AB12: Yes
A13: 10 | B13: 2281 | C13: illes-balears|2022|caso-1|10 | D13: Illes Balears | E13: 2022 | F13: illes-balears/2022 | G13: caso-1 | H13: 10 | I13: Named clinical-case section | J13: Named clinical-case section | K13: mandatory_named_case | L13: Yes | M13: Positive / standard | P13: D | Q13: Una revisión endoscópica dentro de tres años es suficiente. | R13: illes-balears-2022-base-caso-1 | T13: 6 | U13: AD_ILLES_BALEARS_2022__EXAM__exam__cuadernillo-de-examen-aparato-digestivo-fea.pdf | V13: AD_ILLES_BALEARS_2022__ANSWER_KEY__answer-key__plantilla-correctora-del-examen.pdf | W13: bb64ccebab205c81be13079054b34322a12718c98108907afd84f2c756bbf87c | X13: 5ef45e83475557d105756ee6636f8f42861d01fa68017080caaf5e1af60777ac | AA13: Named case block | AB13: Yes
A14: 11 | B14: 2282 | C14: illes-balears|2022|caso-1|11 | D14: Illes Balears | E14: 2022 | F14: illes-balears/2022 | G14: caso-1 | H14: 11 | I14: Named clinical-case section | J14: Named clinical-case section | K14: mandatory_named_case | L14: Yes | M14: Positive / standard | P14: C | Q14: En este caso se recomienda el control por medio de una SOH bianual. | R14: illes-balears-2022-base-caso-1 | T14: 6 | U14: AD_ILLES_BALEARS_2022__EXAM__exam__cuadernillo-de-examen-aparato-digestivo-fea.pdf | V14: AD_ILLES_BALEARS_2022__ANSWER_KEY__answer-key__plantilla-correctora-del-examen.pdf | W14: 4c383eef4717778210749fa7bfae2c1ff3dcc952068d550dc2c721252ba7a0af | X14: d0d7aef16070926dc723abe647e67080f8b23c483d8b893c70e05d65e66b6e16 | AA14: Named case block | AB14: Yes
A15: 12 | B15: 2283 | C15: illes-balears|2022|caso-1|12 | D15: Illes Balears | E15: 2022 | F15: illes-balears/2022 | G15: caso-1 | H15: 12 | I15: Named clinical-case section | J15: Named clinical-case section | K15: mandatory_named_case | L15: Yes | M15: Positive / standard | P15: B | Q15: Requiere colonoscopia por la clínica que presenta para descartar un CCR. | R15: illes-balears-2022-base-caso-1 | T15: 7 | U15: AD_ILLES_BALEARS_2022__EXAM__exam__cuadernillo-de-examen-aparato-digestivo-fea.pdf | V15: AD_ILLES_BALEARS_2022__ANSWER_KEY__answer-key__plantilla-correctora-del-examen.pdf | W15: b02c5b6670c3190bdaa4c2e5d9e6cc482f67d73dd28c11e8b8293e7bb3a0f859 | X15: 6bfc650aa9a755437c630e63b0e0c75f83d43e1f13ffbb4797bd80b8cc48eaf1 | AA15: Named case block | AB15: Yes
A16: 13 | B16: 2285 | C16: illes-balears|2022|caso-1|14 | D16: Illes Balears | E16: 2022 | F16: illes-balears/2022 | G16: caso-1 | H16: 14 | I16: Named clinical-case section | J16: Named clinical-case section | K16: mandatory_named_case | L16: Yes | M16: Positive / standard | P16: C | Q16: Estadio T1N0M0. | R16: illes-balears-2022-base-caso-1 | T16: 7 | U16: AD_ILLES_BALEARS_2022__EXAM__exam__cuadernillo-de-examen-aparato-digestivo-fea.pdf | V16: AD_ILLES_BALEARS_2022__ANSWER_KEY__answer-key__plantilla-correctora-del-examen.pdf | W16: aff3151dc1a61323e21c11bd0589e0005b300a751ff913dbcdd31b8c953d0df1 | X16: 7d443f0d0212cb3064184d0af9461783fcc8aabaf1479911d11e9380252a978d | AA16: Named case block | AB16: Yes
A17: 14 | B17: 2286 | C17: illes-balears|2022|caso-1|15 | D17: Illes Balears | E17: 2022 | F17: illes-balears/2022 | G17: caso-1 | H17: 15 | I17: Named clinical-case section | J17: Named clinical-case section | K17: mandatory_named_case | L17: Yes | M17: Positive / standard | P17: C | Q17: Es susceptible de una resección en bloque mediante una disección endoscópica submucosa. | R17: illes-balears-2022-base-caso-1 | T17: 8 | U17: AD_ILLES_BALEARS_2022__EXAM__exam__cuadernillo-de-examen-aparato-digestivo-fea.pdf | V17: AD_ILLES_BALEARS_2022__ANSWER_KEY__answer-key__plantilla-correctora-del-examen.pdf | W17: 88df8aa0674cc446054de3e5891ddf22beda16502574a3773ea71925b041dd14 | X17: 265df5d0b3f084338cda2289e9af5ba9a04b733d588dda73b6bd6467ef3fad85 | AA17: Named case block | AB17: Yes
A18: 15 | B18: 2287 | C18: illes-balears|2022|caso-1|16 | D18: Illes Balears | E18: 2022 | F18: illes-balears/2022 | G18: caso-1 | H18: 16 | I18: Named clinical-case section | J18: Named clinical-case section | K18: mandatory_named_case | L18: Yes | M18: Positive / standard | P18: A | Q18: La resección endoscópica ha sido curativa. | R18: illes-balears-2022-base-caso-1 | T18: 8 | U18: AD_ILLES_BALEARS_2022__EXAM__exam__cuadernillo-de-examen-aparato-digestivo-fea.pdf | V18: AD_ILLES_BALEARS_2022__ANSWER_KEY__answer-key__plantilla-correctora-del-examen.pdf | W18: 67aa9ad13c13ae0699fa6d1a98c5a82f666526e043280163afe52f08136a3a99 | X18: ce9dbeac77d39f481f2891d5cfc442d77b1fcfa9397e13395a534a7309f3905a | AA18: Named case block | AB18: Yes
A19: 16 | B19: 2288 | C19: illes-balears|2022|caso-1|17 | D19: Illes Balears | E19: 2022 | F19: illes-balears/2022 | G19: caso-1 | H19: 17 | I19: Named clinical-case section | J19: Named clinical-case section | K19: mandatory_named_case | L19: Yes | M19: Positive / standard | P19: C | Q19: Requiere un control endoscópico de forma precoz, que es aceptable a los seis meses. | R19: illes-balears-2022-base-caso-1 | T19: 8 | U19: AD_ILLES_BALEARS_2022__EXAM__exam__cuadernillo-de-examen-aparato-digestivo-fea.pdf | V19: AD_ILLES_BALEARS_2022__ANSWER_KEY__answer-key__plantilla-correctora-del-examen.pdf | W19: 7a825164928fc8af7706455f2129fd0cbb968eaef6cc16915e04344f5a58ad53 | X19: 42f6114c7ca2bbec6eb1c946e5cad9296dabcc7843fa73a8463f792e5d5dc298 | AA19: Named case block | AB19: Yes
A20: 17 | B20: 2289 | C20: illes-balears|2022|caso-1|18 | D20: Illes Balears | E20: 2022 | F20: illes-balears/2022 | G20: caso-1 | H20: 18 | I20: Named clinical-case section | J20: Named clinical-case section | K20: mandatory_named_case | L20: Yes | M20: Positive / standard | P20: A | Q20: Si es factible, la resección endoscópica de las lesiones ha de ser el tratamiento de elección. | R20: illes-balears-2022-base-caso-1 | T20: 9 | U20: AD_ILLES_BALEARS_2022__EXAM__exam__cuadernillo-de-examen-aparato-digestivo-fea.pdf | V20: AD_ILLES_BALEARS_2022__ANSWER_KEY__answer-key__plantilla-correctora-del-examen.pdf | W20: a567190f5396499aa0f62c074c0245823878267d655998356bd64aea600abed0 | X20: d632d4c0a68b17e9aa487a9391c8f87a3a21db16d5101c66f04b87d72287bbd1 | AA20: Named case block | AB20: Yes
A21: 18 | B21: 2290 | C21: illes-balears|2022|caso-1|19 | D21: Illes Balears | E21: 2022 | F21: illes-balears/2022 | G21: caso-1 | H21: 19 | I21: Named clinical-case section | J21: Named clinical-case section | K21: mandatory_named_case | L21: Yes | M21: Positive / standard | P21: B | Q21: Puede ser susceptible de un estudio genético complementario. | R21: illes-balears-2022-base-caso-1 | T21: 9 | U21: AD_ILLES_BALEARS_2022__EXAM__exam__cuadernillo-de-examen-aparato-digestivo-fea.pdf | V21: AD_ILLES_BALEARS_2022__ANSWER_KEY__answer-key__plantilla-correctora-del-examen.pdf | W21: f644a22f49e7e5b90f398c4ed1a9eb36902ac515e763a0f51e9aad012cf02ae3 | X21: 5ec1109cb8c5c8c315198cac1c1f3c00d08f6f4313c9999369a835da06c150ee | AA21: Named case block | AB21: Yes
A22: 19 | B22: 2291 | C22: illes-balears|2022|caso-1|20 | D22: Illes Balears | E22: 2022 | F22: illes-balears/2022 | G22: caso-1 | H22: 20 | I22: Named clinical-case section | J22: Named clinical-case section | K22: mandatory_named_case | L22: Yes | M22: Positive / standard | P22: A | Q22: Poliposis adenomatosa familiar clásica. | R22: illes-balears-2022-base-caso-1 | T22: 9 | U22: AD_ILLES_BALEARS_2022__EXAM__exam__cuadernillo-de-examen-aparato-digestivo-fea.pdf | V22: AD_ILLES_BALEARS_2022__ANSWER_KEY__answer-key__plantilla-correctora-del-examen.pdf | W22: 1b01a702a113543689c56428705ad01e7dcdce2c79ad5bad7b8ebe008194441f | X22: 7b6d88e3ada591c7a5e49858ee6c72ec02830fb56c3ac9ecf8402f96f8c03737 | AA22: Named case block | AB22: Yes
... A26: 23 | B26: 2295 | C26: illes-balears|2022|caso-1|24 | D26: Illes Balears | E26: 2022 | F26: illes-balears/2022 | G26: caso-1 | H26: 24 | I26: Named clinical-case section | J26: Named clinical-case section | K26: mandatory_named_case | L26: Yes | M26: Positive / standard | P26: D | Q26: Todas las respuestas anteriores son falsas. | R26: illes-balears-2022-base-caso-1 | T26: 10 | U26: AD_ILLES_BALEARS_2022__EXAM__exam__cuadernillo-de-examen-aparato-digestivo-fea.pdf | V26: AD_ILLES_BALEARS_2022__ANSWER_KEY__answer-key__plantilla-correctora-del-examen.pdf | W26: 1749a64be74a8f517f93cd63d20500658464230f3aaa8d9d25745de589aff6b7 | X26: a5c0c1542ef50e179f771244b40de6c124b750ac0bc72001f1febaacce332332 | AA26: Named case block | AB26: Yes
A27: 24 | B27: 2296 | C27: illes-balears|2022|caso-2|25 | D27: Illes Balears | E27: 2022 | F27: illes-balears/2022 | G27: caso-2 | H27: 25 | I27: Named clinical-case section | J27: Named clinical-case section | K27: mandatory_named_case | L27: Yes | M27: Negated / exception | N27: negated | P27: B | Q27: La endoscopia digestiva está indicada como método diagnóstico inicial en todos los pacientes que muestran síntomas típicos de ERGE. | R27: illes-balears-2022-base-caso-2 | T27: 11 | U27: AD_ILLES_BALEARS_2022__EXAM__exam__cuadernillo-de-examen-aparato-digestivo-fea.pdf | V27: AD_ILLES_BALEARS_2022__ANSWER_KEY__answer-key__plantilla-correctora-supuesto-2.pdf | W27: 46b617af1800cd3ba2810ae6308d98cf5f1a55cd037f319fc8ea9f0d4f414030 | X27: ca5f3cd15c78dba696178a8961c6a02632e767f341d4a95fe680d1a60cb796dc | Y27: source_answer_key_pdf: Codex PDF-source repair: PDF-source repair SRC-008. Source: exams-other-regions-spain-pdfs/illes-balears/2022/answer-key/answer-key__plantilla-correctora-supuesto-2.pdf, PDF page 1. | AA27: Named case block | AB27: Yes
A28: 25 | B28: 2297 | C28: illes-balears|2022|caso-2|26 | D28: Illes Balears | E28: 2022 | F28: illes-balears/2022 | G28: caso-2 | H28: 26 | I28: Named clinical-case section | J28: Named clinical-case section | K28: mandatory_named_case | L28: Yes | M28: Negated / exception | N28: negated | P28: D | Q28: En los pacientes con gastroscopia normal y con pirosis que no responden al tratamiento médico con inhibidores de la bomba de protones, se debe descartar una enfermedad por reflujo gastroesofágico y no se deben hacer otros estudios. | R28: illes-balears-2022-base-caso-2 | T28: 12 | U28: AD_ILLES_BALEARS_2022__EXAM__exam__cuadernillo-de-examen-aparato-digestivo-fea.pdf | V28: AD_ILLES_BALEARS_2022__ANSWER_KEY__answer-key__plantilla-correctora-supuesto-2.pdf | W28: 939bd030fb3627eb0a1eed937267212fb9ce4a60cd4df3e70b33cd2ee9bd159c | X28: adc41abf18b9a546396a5b63cc614d00787a3b1aa49e37faef509dae00869ea4 | Y28: source_answer_key_pdf: Codex PDF-source repair: PDF-source repair SRC-008. Source: exams-other-regions-spain-pdfs/illes-balears/2022/answer-key/answer-key__plantilla-correctora-supuesto-2.pdf, PDF page 1. | AA28: Named case block | AB28: Yes
A29: 26 | B29: 2298 | C29: illes-balears|2022|caso-2|27 | D29: Illes Balears | E29: 2022 | F29: illes-balears/2022 | G29: caso-2 | H29: 27 | I29: Named clinical-case section | J29: Named clinical-case section | K29: mandatory_named_case | L29: Yes | M29: Negated / exception | N29: negated | P29: C | Q29: Las alteraciones de la motilidad del cuerpo esofágico no influyen en el reflujo gastroesofágico. | R29: illes-balears-2022-base-caso-2 | T29: 12 | U29: AD_ILLES_BALEARS_2022__EXAM__exam__cuadernillo-de-examen-aparato-digestivo-fea.pdf | V29: AD_ILLES_BALEARS_2022__ANSWER_KEY__answer-key__plantilla-correctora-supuesto-2.pdf | W29: 5eceae15bd81c58f863d274997e8a560c84dba9717d9b5d914e1daf55ebfdc99 | X29: 5917e7b2c898c26c97c4b59d8298d0b34fc56233041f7f09cbd3dbf9ed08a739 | Y29: source_answer_key_pdf: Codex PDF-source repair: PDF-source repair SRC-008. Source: exams-other-regions-spain-pdfs/illes-balears/2022/answer-key/answer-key__plantilla-correctora-supuesto-2.pdf, PDF page 1. | AA29: Named case block | AB29: Yes
A30: 27 | B30: 2299 | C30: illes-balears|2022|caso-2|28 | D30: Illes Balears | E30: 2022 | F30: illes-balears/2022 | G30: caso-2 | H30: 28 | I30: Named clinical-case section | J30: Named clinical-case section | K30: mandatory_named_case | L30: Yes | M30: Positive / standard | P30: B | Q30: No hay diferencias en la gravedad de la pirosis entre los diferentes fenotipos de reflujo gastroesofágico. | R30: illes-balears-2022-base-caso-2 | T30: 12 | U30: AD_ILLES_BALEARS_2022__EXAM__exam__cuadernillo-de-examen-aparato-digestivo-fea.pdf | V30: AD_ILLES_BALEARS_2022__ANSWER_KEY__answer-key__plantilla-correctora-supuesto-2.pdf | W30: 2f704ddce6331088b97be2d19c9dfb939dd6f20ecaa05ffd3b34b5f7b28b38c7 | X30: 1427496e68805e480caea329fead13c919856353d384aa2b980ed7e2d0370229 | Y30: source_answer_key_pdf: Codex PDF-source repair: PDF-source repair SRC-008. Source: exams-other-regions-spain-pdfs/illes-balears/2022/answer-key/answer-key__plantilla-correctora-supuesto-2.pdf, PDF page 1. | AA30: Named case block | AB30: Yes
A31: 28 | B31: 2300 | C31: illes-balears|2022|caso-2|29 | D31: Illes Balears | E31: 2022 | F31: illes-balears/2022 | G31: caso-2 | H31: 29 | I31: Named clinical-case section | J31: Named clinical-case section | K31: mandatory_named_case | L31: Yes | M31: Negated / exception | N31: negated | P31: B | Q31: Existe una buena correlación entre la intensidad o la frecuencia de los síntomas de ERGE y la gravedad de las lesiones endoscópicas. | R31: illes-balears-2022-base-caso-2 | T31: 13 | U31: AD_ILLES_BALEARS_2022__EXAM__exam__cuadernillo-de-examen-aparato-digestivo-fea.pdf | V31: AD_ILLES_BALEARS_2022__ANSWER_KEY__answer-key__plantilla-correctora-supuesto-2.pdf | W31: f516a21d94c475ef442b2a0b512b68e3664b8ce4559c013d67467c13d661bae3 | X31: 5ecfbf9e5897133a2301fafac07bc1f364ed7ff78c9e59bc72febbe962f846ce | Y31: source_answer_key_pdf: Codex PDF-source repair: PDF-source repair SRC-008. Source: exams-other-regions-spain-pdfs/illes-balears/2022/answer-key/answer-key__plantilla-correctora-supuesto-2.pdf, PDF page 1. | AA31: Named case block | AB31: Yes
A32: 29 | B32: 2301 | C32: illes-balears|2022|caso-2|30 | D32: Illes Balears | E32: 2022 | F32: illes-balears/2022 | G32: caso-2 | H32: 30 | I32: Named clinical-case section | J32: Named clinical-case section | K32: mandatory_named_case | L32: Yes | M32: Positive / standard | P32: C | Q32: Supone una o más lesiones de la mucosa, con confluencia y afectación menor del 75 % de la circunferencia del esófago. | R32: illes-balears-2022-base-caso-2 | T32: 13 | U32: AD_ILLES_BALEARS_2022__EXAM__exam__cuadernillo-de-examen-aparato-digestivo-fea.pdf | V32: AD_ILLES_BALEARS_2022__ANSWER_KEY__answer-key__plantilla-correctora-supuesto-2.pdf | W32: 70372455a58763598b00b870e0e398b0ab6ff48604b2b97bb488f9922411dd6d | X32: 3bd1291f3a4f46dbd6925b60339bcb25845205139f1c0c675e95c32577fa0516 | Y32: source_answer_key_pdf: Codex PDF-source repair: PDF-source repair SRC-008. Source: exams-other-regions-spain-pdfs/illes-balears/2022/answer-key/answer-key__plantilla-correctora-supuesto-2.pdf, PDF page 1. | AA32: Named case block | AB32: Yes
A33: 30 | B33: 2302 | C33: illes-balears|2022|caso-2|31 | D33: Illes Balears | E33: 2022 | F33: illes-balears/2022 | G33: caso-2 | H33: 31 | I33: Named clinical-case section | J33: Named clinical-case section | K33: mandatory_named_case | L33: Yes | M33: Positive / standard | P33: C | Q33: Impedancia intraluminal multicanal asociada a pH-metría. | R33: illes-balears-2022-base-caso-2 | T33: 13 | U33: AD_ILLES_BALEARS_2022__EXAM__exam__cuadernillo-de-examen-aparato-digestivo-fea.pdf | V33: AD_ILLES_BALEARS_2022__ANSWER_KEY__answer-key__plantilla-correctora-supuesto-2.pdf | W33: b1b12135b689720f90997ecc1896d87b22f84f0a20a06390257b83534b865818 | X33: ac6f9ba6359dcce2e1c92122e6c52ae87eeecb6ca20227de33a9e957ba1ebba8 | Y33: source_answer_key_pdf: Codex PDF-source repair: PDF-source repair SRC-008. Source: exams-other-regions-spain-pdfs/illes-balears/2022/answer-key/answer-key__plantilla-correctora-supuesto-2.pdf, PDF page 1. | AA33: Named case block | AB33: Yes
A34: 31 | B34: 2303 | C34: illes-balears|2022|caso-2|32 | D34: Illes Balears | E34: 2022 | F34: illes-balears/2022 | G34: caso-2 | H34: 32 | I34: Named clinical-case section | J34: Named clinical-case section | K34: mandatory_named_case | L34: Yes | M34: Negated / exception | N34: negated | P34: C | Q34: No interfiere su interpretación si hay alteraciones de la motilidad o histológicas del esófago. | R34: illes-balears-2022-base-caso-2 | T34: 14 | U34: AD_ILLES_BALEARS_2022__EXAM__exam__cuadernillo-de-examen-aparato-digestivo-fea.pdf | V34: AD_ILLES_BALEARS_2022__ANSWER_KEY__answer-key__plantilla-correctora-supuesto-2.pdf | W34: 2208df2a87ef958f67da9b48780a031220fa24a1369d73ed951873062234a28d | X34: fceafb8f5d44c836384234fdfd120921427d1ee6018d44cf48651ef4c1719489 | Y34: source_answer_key_pdf: Codex PDF-source repair: PDF-source repair SRC-008. Source: exams-other-regions-spain-pdfs/illes-balears/2022/answer-key/answer-key__plantilla-correctora-supuesto-2.pdf, PDF page 1. | AA34: Named case block | AB34: Yes
A35: 32 | B35: 2304 | C35: illes-balears|2022|caso-2|33 | D35: Illes Balears | E35: 2022 | F35: illes-balears/2022 | G35: caso-2 | H35: 33 | I35: Named clinical-case section | J35: Named clinical-case section | K35: mandatory_named_case | L35: Yes | M35: Negated / exception | N35: negated | P35: D | Q35: Edad superior a 50 años sin diferencia de sexo y raza. | R35: illes-balears-2022-base-caso-2 | T35: 14 | U35: AD_ILLES_BALEARS_2022__EXAM__exam__cuadernillo-de-examen-aparato-digestivo-fea.pdf | V35: AD_ILLES_BALEARS_2022__ANSWER_KEY__answer-key__plantilla-correctora-supuesto-2.pdf | W35: 2b1d1d786b7bd0e95d12923fc23d1f17e4dfcc1e8f0aaa335c992209d709df7e | X35: ea2a6d85429619926060ffd509d9f02d67b729a040e6fc93d8b5a9b61f32c3ef | Y35: source_answer_key_pdf: Codex PDF-source repair: PDF-source repair SRC-008. Source: exams-other-regions-spain-pdfs/illes-balears/2022/answer-key/answer-key__plantilla-correctora-supuesto-2.pdf, PDF page 1. | AA35: Named case block | AB35: Yes
A36: 33 | B36: 2305 | C36: illes-balears|2022|caso-2|34 | D36: Illes Balears | E36: 2022 | F36: illes-balears/2022 | G36: caso-2 | H36: 34 | I36: Named clinical-case section | J36: Named clinical-case section | K36: mandatory_named_case | L36: Yes | M36: Negated / exception | N36: negated | P36: C | Q36: Siempre se aconseja biopsiar un esófago de Barrett en presencia de esofagitis por reflujo. | R36: illes-balears-2022-base-caso-2 | T36: 14 | U36: AD_ILLES_BALEARS_2022__EXAM__exam__cuadernillo-de-examen-aparato-digestivo-fea.pdf | V36: AD_ILLES_BALEARS_2022__ANSWER_KEY__answer-key__plantilla-correctora-supuesto-2.pdf | W36: f407a27f4953ae648b0562456f1d60c8d7b918238eee184d235425babdac16d9 | X36: d85d06457115f7aef70bc51c94fc4772b6d12d7690ddd506eac0f042df0437d1 | Y36: source_answer_key_pdf: Codex PDF-source repair: PDF-source repair SRC-008. Source: exams-other-regions-spain-pdfs/illes-balears/2022/answer-key/answer-key__plantilla-correctora-supuesto-2.pdf, PDF page 1. | AA36: Named case block | AB36: Yes
A37: 34 | B37: 2306 | C37: illes-balears|2022|caso-2|35 | D37: Illes Balears | E37: 2022 | F37: illes-balears/2022 | G37: caso-2 | H37: 35 | I37: Named clinical-case section | J37: Named clinical-case section | K37: mandatory_named_case | L37: Yes | M37: Positive / standard | P37: D | Q37: Todas las respuestas anteriores son correctas. | R37: illes-balears-2022-base-caso-2 | T37: 15 | U37: AD_ILLES_BALEARS_2022__EXAM__exam__cuadernillo-de-examen-aparato-digestivo-fea.pdf | V37: AD_ILLES_BALEARS_2022__ANSWER_KEY__answer-key__plantilla-correctora-supuesto-2.pdf | W37: 29ea5b1ba367cd614b5d1a515a4a8ea2991c86cd55eee5d72097d5e765581b22 | X37: 67d5cf394df1540b47a835da4b369f831430386c2a42c7d542926591ed369902 | Y37: source_answer_key_pdf: Codex PDF-source repair: PDF-source repair SRC-008. Source: exams-other-regions-spain-pdfs/illes-balears/2022/answer-key/answer-key__plantilla-correctora-supuesto-2.pdf, PDF page 1. | AA37: Named case block | AB37: Yes
A38: 35 | B38: 2307 | C38: illes-balears|2022|caso-2|36 | D38: Illes Balears | E38: 2022 | F38: illes-balears/2022 | G38: caso-2 | H38: 36 | I38: Named clinical-case section | J38: Named clinical-case section | K38: mandatory_named_case | L38: Yes | M38: Negated / exception | N38: negated | P38: B | Q38: La longitud del esófago. | R38: illes-balears-2022-base-caso-2 | T38: 15 | U38: AD_ILLES_BALEARS_2022__EXAM__exam__cuadernillo-de-examen-aparato-digestivo-fea.pdf | V38: AD_ILLES_BALEARS_2022__ANSWER_KEY__answer-key__plantilla-correctora-supuesto-2.pdf | W38: 0caa5d5650481fc86ee6dda9d5b726d887acbbcc85cee9f0bc7661f8a62fc39d | X38: 47be8a0b580d1898d64af6f3390dd3e8857c1359944bb82780e2b43a908fc410 | Y38: source_answer_key_pdf: Codex PDF-source repair: PDF-source repair SRC-008. Source: exams-other-regions-spain-pdfs/illes-balears/2022/answer-key/answer-key__plantilla-correctora-supuesto-2.pdf, PDF page 1. | AA38: Named case block | AB38: Yes
A39: 36 | B39: 2308 | C39: illes-balears|2022|caso-2|37 | D39: Illes Balears | E39: 2022 | F39: illes-balears/2022 | G39: caso-2 | H39: 37 | I39: Named clinical-case section | J39: Named clinical-case section | K39: mandatory_named_case | L39: Yes | M39: Positive / standard | P39: B | Q39: Se deben hacer biopsias en botes separados de los cuatro cuadrantes cada 2 cm de esófago de Barrett o cada 1 cm si hay displasia severa previa. | R39: illes-balears-2022-base-caso-2 | T39: 15 | U39: AD_ILLES_BALEARS_2022__EXAM__exam__cuadernillo-de-examen-aparato-digestivo-fea.pdf | V39: AD_ILLES_BALEARS_2022__ANSWER_KEY__answer-key__plantilla-correctora-supuesto-2.pdf | W39: ef05f0e397859da238119f60985df869ed0f4e4363164bf9f7e1f09939dd4258 | X39: 36cfb6de3f4da6dbaee75437a451f4888ebb18364a6dff9d848b17d88e1910c8 | Y39: source_answer_key_pdf: Codex PDF-source repair: PDF-source repair SRC-008. Source: exams-other-regions-spain-pdfs/illes-balears/2022/answer-key/answer-key__plantilla-correctora-supuesto-2.pdf, PDF page 1. | AA39: Named case block | AB39: Yes
A40: 37 | B40: 2309 | C40: illes-balears|2022|caso-2|38 | D40: Illes Balears | E40: 2022 | F40: illes-balears/2022 | G40: caso-2 | H40: 38 | I40: Named clinical-case section | J40: Named clinical-case section | K40: mandatory_named_case | L40: Yes | M40: Negated / exception | N40: negated | P40: C | Q40: Ante el hallazgo de displasia indefinida se recomienda una revisión endoscópica en dos años. | R40: illes-balears-2022-base-caso-2 | T40: 15 | U40: AD_ILLES_BALEARS_2022__EXAM__exam__cuadernillo-de-examen-aparato-digestivo-fea.pdf | V40: AD_ILLES_BALEARS_2022__ANSWER_KEY__answer-key__plantilla-correctora-supuesto-2.pdf | W40: c744333d943cbb4ab9f7783611f98fb9b56835149c24c918b9c43c2dc4f0039a | X40: 6bef62dfbf0bd904d71f9f452c10d6c5c909c814361a05c664652f3ae1e1f48d | Y40: source_answer_key_pdf: Codex PDF-source repair: PDF-source repair SRC-008. Source: exams-other-regions-spain-pdfs/illes-balears/2022/answer-key/answer-key__plantilla-correctora-supuesto-2.pdf, PDF page 1. | AA40: Named case block | AB40: Yes
A41: 38 | B41: 2310 | C41: illes-balears|2022|caso-2|39 | D41: Illes Balears | E41: 2022 | F41: illes-balears/2022 | G41: caso-2 | H41: 39 | I41: Named clinical-case section | J41: Named clinical-case section | K41: mandatory_named_case | L41: Yes | M41: Negated / exception | N41: negated | P41: B | Q41: La cirugía antirreflujo se considera una opción más eficaz que el tratamiento médico con IBP para los pacientes con esófago de Barrett. | R41: illes-balears-2022-base-caso-2 | T41: 16 | U41: AD_ILLES_BALEARS_2022__EXAM__exam__cuadernillo-de-examen-aparato-digestivo-fea.pdf | V41: AD_ILLES_BALEARS_2022__ANSWER_KEY__answer-key__plantilla-correctora-supuesto-2.pdf | W41: 1379a97c3800c586c61b05d334c0398999c7df995dc13961fdc9176e6656dd6c | X41: d528d03b4712d8598f24b2678d06c5812ee0d81c774e3dca9516d098f3a62c6a | Y41: source_answer_key_pdf: Codex PDF-source repair: PDF-source repair SRC-008. Source: exams-other-regions-spain-pdfs/illes-balears/2022/answer-key/answer-key__plantilla-correctora-supuesto-2.pdf, PDF page 1. | AA41: Named case block | AB41: Yes
A42: 39 | B42: 2311 | C42: illes-balears|2022|caso-2|40 | D42: Illes Balears | E42: 2022 | F42: illes-balears/2022 | G42: caso-2 | H42: 40 | I42: Named clinical-case section | J42: Named clinical-case section | K42: mandatory_named_case | L42: Yes | M42: Negated / exception | N42: negated | P42: B | Q42: La ablación por radiofrecuencia es coste-efectiva en todos los casos de esófago de Barrett de longitud larga (superior a 5 cm). | R42: illes-balears-2022-base-caso-2 | T42: 16 | U42: AD_ILLES_BALEARS_2022__EXAM__exam__cuadernillo-de-examen-aparato-digestivo-fea.pdf | V42: AD_ILLES_BALEARS_2022__ANSWER_KEY__answer-key__plantilla-correctora-supuesto-2.pdf | W42: 84f7652f68600af19aa7f80427b3ada734c84cfe1e7fe02751d88c820f525759 | X42: 44a128072af793beb42bdecffffe95d00aa03322245c5275a97ed03407f717e4 | Y42: source_answer_key_pdf: Codex PDF-source repair: PDF-source repair SRC-008. Source: exams-other-regions-spain-pdfs/illes-balears/2022/answer-key/answer-key__plantilla-correctora-supuesto-2.pdf, PDF page 1. | AA42: Named case block | AB42: Yes
A43: 40 | B43: 2312 | C43: illes-balears|2022|caso-2|41 | D43: Illes Balears | E43: 2022 | F43: illes-balears/2022 | G43: caso-2 | H43: 41 | I43: Named clinical-case section | J43: Named clinical-case section | K43: mandatory_named_case | L43: Yes | M43: Positive / standard | P43: A | Q43: Planificar una resección endoscópica de la lesión con displasia de grado alto y posteriormente una ablación con radiofrecuencia de todo el esófago de Barrett. | R43: illes-balears-2022-base-caso-2 | T43: 16 | U43: AD_ILLES_BALEARS_2022__EXAM__exam__cuadernillo-de-examen-aparato-digestivo-fea.pdf | V43: AD_ILLES_BALEARS_2022__ANSWER_KEY__answer-key__plantilla-correctora-supuesto-2.pdf | W43: c2df05163bf7e1ee42202e1b7d2f4ab15bbf7921c6a0ad79dde9b1a0a02925f0 | X43: 29d7b8c46040d3db8dc1d1440be224d6c0d032885f4542369a02e27d4c1d76bb | Y43: source_answer_key_pdf: Codex PDF-source repair: PDF-source repair SRC-008. Source: exams-other-regions-spain-pdfs/illes-balears/2022/answer-key/answer-key__plantilla-correctora-supuesto-2.pdf, PDF page 1. | AA43: Named case block | AB43: Yes
A44: 41 | B44: 2313 | C44: illes-balears|2022|caso-2|42 | D44: Illes Balears | E44: 2022 | F44: illes-balears/2022 | G44: caso-2 | H44: 42 | I44: Named clinical-case section | J44: Named clinical-case section | K44: mandatory_named_case | L44: Yes | M44: Positive / standard | P44: D | Q44: Todas las respuestas anteriores son correctas. | R44: illes-balears-2022-base-caso-2 | T44: 17 | U44: AD_ILLES_BALEARS_2022__EXAM__exam__cuadernillo-de-examen-aparato-digestivo-fea.pdf | V44: AD_ILLES_BALEARS_2022__ANSWER_KEY__answer-key__plantilla-correctora-supuesto-2.pdf | W44: e2de243dc92fa6f3556bacf9fd99994e1e592a1cbcd76bb573ab712d9af3c4b7 | X44: 2916fecffbf05757f6e70491ec2ccc14473caef9c9e719585d7d4c4ba30fe1d4 | Y44: correct_letter: Codex PDF-source repair: PDF-source repair SRC-008. Source: exams-other-regions-spain-pdfs/illes-balears/2022/answer-key/answer-key__plantilla-correctora-supuesto-2.pdf, PDF page 1. | correct_option_text: Codex PDF-source repair: PDF-source repair SRC-008. Source: exams-other-regions-spain-pdfs/illes-balears/2022/exam/exam__cuadernillo-de-examen-aparato-digestivo-fea.pdf, PDF page 17. | source_answer_key_pdf: Codex PDF-source repair: PDF-source repair SRC-008. Source: exams-other-regions-spain-pdfs/illes-balears/2022/answer-key/answer-key__plantilla-correctora-supuesto-2.pdf, PDF page 1. | AA44: Named case block | AB44: Yes
A45: 42 | B45: 2314 | C45: illes-balears|2022|caso-2|43 | D45: Illes Balears | E45: 2022 | F45: illes-balears/2022 | G45: caso-2 | H45: 43 | I45: Named clinical-case section | J45: Named clinical-case section | K45: mandatory_named_case | L45: Yes | M45: Positive / standard | P45: B | Q45: Los factores pronósticos del tumor son favorables por lo que se debe discutir en un equipo multidisciplinar para decidir la actitud terapéutica. | R45: illes-balears-2022-base-caso-2 | T45: 17 | U45: AD_ILLES_BALEARS_2022__EXAM__exam__cuadernillo-de-examen-aparato-digestivo-fea.pdf | V45: AD_ILLES_BALEARS_2022__ANSWER_KEY__answer-key__plantilla-correctora-supuesto-2.pdf | W45: 3fb875d9271653ff2516e1e9e296ded2f791df2b262f9e3db6be63683d750d19 | X45: ff3bd193b0df220b2476d32fa10ff7a9b8e5f073b638808f9a19f2844c1e0004 | Y45: correct_letter: Codex PDF-source repair: PDF-source repair SRC-008. Source: exams-other-regions-spain-pdfs/illes-balears/2022/answer-key/answer-key__plantilla-correctora-supuesto-2.pdf, PDF page 1. | correct_option_text: Codex PDF-source repair: PDF-source repair SRC-008. Source: exams-other-regions-spain-pdfs/illes-balears/2022/exam/exam__cuadernillo-de-examen-aparato-digestivo-fea.pdf, PDF page 17. | source_answer_key_pdf: Codex PDF-source repair: PDF-source repair SRC-008. Source: exams-other-regions-spain-pdfs/illes-balears/2022/answer-key/answer-key__plantilla-correctora-supuesto-2.pdf, PDF page 1. | AA45: Named case block | AB45: Yes
A46: 43 | B46: 2315 | C46: illes-balears|2022|caso-2|44 | D46: Illes Balears | E46: 2022 | F46: illes-balears/2022 | G46: caso-2 | H46: 44 | I46: Named clinical-case section | J46: Named clinical-case section | K46: mandatory_named_case | L46: Yes | M46: Negated / exception | N46: negated | P46: D | Q46: Una vez hecha la ablación por RFA no necesita ningún seguimiento endoscópico por la recurrencia baja de displasia. | R46: illes-balears-2022-base-caso-2 | T46: 17 | U46: AD_ILLES_BALEARS_2022__EXAM__exam__cuadernillo-de-examen-aparato-digestivo-fea.pdf | V46: AD_ILLES_BALEARS_2022__ANSWER_KEY__answer-key__plantilla-correctora-supuesto-2.pdf | W46: 4394008641f6999e8820461e3d5acf28d56324b4270b910139ab13b14c6fc8d2 | X46: 6dfbbd215bb3051dab99d96327154e366529875c4219ab1d23ea5153a5c0577f | Y46: source_answer_key_pdf: Codex PDF-source repair: PDF-source repair SRC-008. Source: exams-other-regions-spain-pdfs/illes-balears/2022/answer-key/answer-key__plantilla-correctora-supuesto-2.pdf, PDF page 1. | AA46: Named case block | AB46: Yes
A47: 44 | B47: 2316 | C47: illes-balears|2022|caso-2|45 | D47: Illes Balears | E47: 2022 | F47: illes-balears/2022 | G47: caso-2 | H47: 45 | I47: Named clinical-case section | J47: Named clinical-case section | K47: mandatory_named_case | L47: Yes | M47: Negated / exception | N47: negated | P47: D | Q47: Raza caucásica. | R47: illes-balears-2022-base-caso-2 | T47: 18 | U47: AD_ILLES_BALEARS_2022__EXAM__exam__cuadernillo-de-examen-aparato-digestivo-fea.pdf | V47: AD_ILLES_BALEARS_2022__ANSWER_KEY__answer-key__plantilla-correctora-supuesto-2.pdf | W47: ceb122a03a2f86299c620a1ea5bba19e93785cd7397b4067a9a2f37e3e7ad409 | X47: 0e0cad5e2ee5b36497a86c91a172f31ea50159a238881675bf91e4ba2720414e | Y47: correct_letter: Codex PDF-source repair: PDF-source repair SRC-008. Source: exams-other-regions-spain-pdfs/illes-balears/2022/answer-key/answer-key__plantilla-correctora-supuesto-2.pdf, PDF page 1. | correct_option_text: Codex PDF-source repair: PDF-source repair SRC-008. Source: exams-other-regions-spain-pdfs/illes-balears/2022/exam/exam__cuadernillo-de-examen-aparato-digestivo-fea.pdf, PDF page 18. | source_answer_key_pdf: Codex PDF-source repair: PDF-source repair SRC-008. Source: exams-other-regions-spain-pdfs/illes-balears/2022/answer-key/answer-key__plantilla-correctora-supuesto-2.pdf, PDF page 1. | AA47: Named case block | AB47: Yes
A48: 45 | B48: 2318 | C48: illes-balears|2022|caso-2|47 | D48: Illes Balears | E48: 2022 | F48: illes-balears/2022 | G48: caso-2 | H48: 47 | I48: Named clinical-case section | J48: Named clinical-case section | K48: mandatory_named_case | L48: Yes | M48: Negated / exception | N48: negated | P48: D | Q48: La incidencia de adenocarcinoma de esófago está disminuyendo gracias a los avances diagnósticos. | R48: illes-balears-2022-base-caso-2 | T48: 18 | U48: AD_ILLES_BALEARS_2022__EXAM__exam__cuadernillo-de-examen-aparato-digestivo-fea.pdf | V48: AD_ILLES_BALEARS_2022__ANSWER_KEY__answer-key__plantilla-correctora-supuesto-2.pdf | W48: 8a7ecb774cb384b6763b6aea90e8940215c7287553140595fab08fc093797b5d | X48: ab239f26c787d9cda6106d704d53b95f232fd5110789c904c42beda5fc070e16 | Y48: source_answer_key_pdf: Codex PDF-source repair: PDF-source repair SRC-008. Source: exams-other-regions-spain-pdfs/illes-balears/2022/answer-key/answer-key__plantilla-correctora-supuesto-2.pdf, PDF page 1. | AA48: Named case block | AB48: Yes
A49: 46 | B49: 2319 | C49: illes-balears|2022|caso-2|48 | D49: Illes Balears | E49: 2022 | F49: illes-balears/2022 | G49: caso-2 | H49: 48 | I49: Named clinical-case section | J49: Named clinical-case section | K49: mandatory_named_case | L49: Yes | M49: Positive / standard | P49: B | Q49: Crioterapia. | R49: illes-balears-2022-base-caso-2 | T49: 18 | U49: AD_ILLES_BALEARS_2022__EXAM__exam__cuadernillo-de-examen-aparato-digestivo-fea.pdf | V49: AD_ILLES_BALEARS_2022__ANSWER_KEY__answer-key__plantilla-correctora-supuesto-2.pdf | W49: 68d42634f1b8061a1efa0a9004d3a0eb189ec2b0bd985c098930530f9ea929f9 | X49: 4fd287995a4fdd5826e6e05fb1f27115b5bf12cecff2128d4cbff15d74d92379 | Y49: source_answer_key_pdf: Codex PDF-source repair: PDF-source repair SRC-008. Source: exams-other-regions-spain-pdfs/illes-balears/2022/answer-key/answer-key__plantilla-correctora-supuesto-2.pdf, PDF page 1. | AA49: Named case block | AB49: Yes
A50: 47 | B50: 2320 | C50: illes-balears|2022|caso-3|49 | D50: Illes Balears | E50: 2022 | F50: illes-balears/2022 | G50: caso-3 | H50: 49 | I50: Named clinical-case section | J50: Named clinical-case section | K50: mandatory_named_case | L50: Yes | M50: Positive / standard | P50: C | Q50: Pancreatitis crónica calcificante. | R50: illes-balears-2022-base-caso-3 | T50: 19 | U50: AD_ILLES_BALEARS_2022__EXAM__exam__cuadernillo-de-examen-aparato-digestivo-fea.pdf | V50: AD_ILLES_BALEARS_2022__ANSWER_KEY__answer-key__plantilla-correctora-del-examen.pdf | W50: 0564c37e64d2d0af7f9fc1ac1ac5950cb6643ece12b69936e5f1a9567ced1063 | X50: 089bb04db1abc77135b7c2175f9732d52e742ee405f6da442957dcd5f24d6de3 | AA50: Named case block | AB50: Yes
A51: 48 | B51: 2321 | C51: illes-balears|2022|caso-3|50 | D51: Illes Balears | E51: 2022 | F51: illes-balears/2022 | G51: caso-3 | H51: 50 | I51: Named clinical-case section | J51: Named clinical-case section | K51: mandatory_named_case | L51: Yes | M51: Positive / standard | P51: B | Q51: La historia clínica, los datos analíticos y las pruebas de imagen son suficientes para establecer el diagnóstico. | R51: illes-balears-2022-base-caso-3 | T51: 19 | U51: AD_ILLES_BALEARS_2022__EXAM__exam__cuadernillo-de-examen-aparato-digestivo-fea.pdf | V51: AD_ILLES_BALEARS_2022__ANSWER_KEY__answer-key__plantilla-correctora-del-examen.pdf | W51: e30ebc36d6be519e7a628d17e4f73e23f364a9207459616767a460e711be3193 | X51: 484bf348c6b904f0b328d9ded489183dcd7dc1f514c324de0ae38b3d3e432086 | AA51: Named case block | AB51: Yes
A52: 49 | B52: 2322 | C52: illes-balears|2022|caso-3|51 | D52: Illes Balears | E52: 2022 | F52: illes-balears/2022 | G52: caso-3 | H52: 51 | I52: Named clinical-case section | J52: Named clinical-case section | K52: mandatory_named_case | L52: Yes | M52: Positive / standard | P52: B | Q52: Colangiopancreatografía por resonancia magnética. | R52: illes-balears-2022-base-caso-3 | T52: 20 | U52: AD_ILLES_BALEARS_2022__EXAM__exam__cuadernillo-de-examen-aparato-digestivo-fea.pdf | V52: AD_ILLES_BALEARS_2022__ANSWER_KEY__answer-key__plantilla-correctora-del-examen.pdf | W52: 694159468cc7fbe37b6acc478ce645f817a4832fa82977e6013086f98ae9c11a | X52: 6f2ba28727b54a1f1c181216246957f4cb066aecb5952c99e8a2b4fb086cada1 | AA52: Named case block | AB52: Yes
A53: 50 | B53: 2323 | C53: illes-balears|2022|caso-3|52 | D53: Illes Balears | E53: 2022 | F53: illes-balears/2022 | G53: caso-3 | H53: 52 | I53: Named clinical-case section | J53: Named clinical-case section | K53: mandatory_named_case | L53: Yes | M53: Positive / standard | P53: D | Q53: TIGAR-O. | R53: illes-balears-2022-base-caso-3 | T53: 20 | U53: AD_ILLES_BALEARS_2022__EXAM__exam__cuadernillo-de-examen-aparato-digestivo-fea.pdf | V53: AD_ILLES_BALEARS_2022__ANSWER_KEY__answer-key__plantilla-correctora-del-examen.pdf | W53: 62ac92045ad2337a38c26229171c41e1171f8286a956ebb6d4f91685c2e32d53 | X53: fb81324a850bd4e11a0d020965f0ca316c989df0ec1f2cf3923bf632fb0bcbcb | AA53: Named case block | AB53: Yes
A54: 51 | B54: 2324 | C54: illes-balears|2022|caso-3|53 | D54: Illes Balears | E54: 2022 | F54: illes-balears/2022 | G54: caso-3 | H54: 53 | I54: Named clinical-case section | J54: Named clinical-case section | K54: mandatory_named_case | L54: Yes | M54: Positive / standard | P54: B | Q54: Elastasa fecal pancreática. | R54: illes-balears-2022-base-caso-3 | T54: 20 | U54: AD_ILLES_BALEARS_2022__EXAM__exam__cuadernillo-de-examen-aparato-digestivo-fea.pdf | V54: AD_ILLES_BALEARS_2022__ANSWER_KEY__answer-key__plantilla-correctora-del-examen.pdf | W54: e9495489f2d56fb87df000349e979007491c72b82a946f4bb2b1b44a3a21d44b | X54: 5ee6c9b7ceef17a6ea37e323b9e1d25f6040422c6341bfbac8812273ca513c34 | AA54: Named case block | AB54: Yes
A55: 52 | B55: 2325 | C55: illes-balears|2022|caso-3|54 | D55: Illes Balears | E55: 2022 | F55: illes-balears/2022 | G55: caso-3 | H55: 54 | I55: Named clinical-case section | J55: Named clinical-case section | K55: mandatory_named_case | L55: Yes | M55: Positive / standard | P55: B | Q55: Peso, índice de masa corporal y determinación de vitaminas liposolubles y otros micronutrientes (magnesio, zinc y vitamina B12). | R55: illes-balears-2022-base-caso-3 | T55: 20 | U55: AD_ILLES_BALEARS_2022__EXAM__exam__cuadernillo-de-examen-aparato-digestivo-fea.pdf | V55: AD_ILLES_BALEARS_2022__ANSWER_KEY__answer-key__plantilla-correctora-del-examen.pdf | W55: 4f2fc51c6699395b12144329c00e7c43e7fe4fc305030e9d3b2340a033f364be | X55: d574a5929a25e21de6267725d1dbc3fdac7621722f907ce8805580558d2b922e | Y55: option_d: Codex PDF-source repair: PDF-source repair SRC-009. Source: exams-other-regions-spain-pdfs/illes-balears/2022/exam/exam__cuadernillo-de-examen-aparato-digestivo-fea.pdf, PDF page 20. | AA55: Named case block | AB55: Yes
A56: 53 | B56: 2326 | C56: illes-balears|2022|caso-3|55 | D56: Illes Balears | E56: 2022 | F56: illes-balears/2022 | G56: caso-3 | H56: 55 | I56: Named clinical-case section | J56: Named clinical-case section | K56: mandatory_named_case | L56: Yes | M56: Positive / standard | P56: D | Q56: Todas las respuestas anteriores son correctas. | R56: illes-balears-2022-base-caso-3, illes-balears-2022-caso-3-transition-01 | T56: 21 | U56: AD_ILLES_BALEARS_2022__EXAM__exam__cuadernillo-de-examen-aparato-digestivo-fea.pdf | V56: AD_ILLES_BALEARS_2022__ANSWER_KEY__answer-key__plantilla-correctora-del-examen.pdf | W56: 4c3d6d1f190c8f1308a87bd1bc52e51d1a11da58088546cd52e550a112b65be9 | X56: 88db57741301448b1ea51a982f6565cbd7325ac441db66ea5317da4de4a7598c | Z56: illes-balears-2022-caso-3-transition-01 | AA56: Named case block | AB56: Yes
A57: 54 | B57: 2327 | C57: illes-balears|2022|caso-3|56 | D57: Illes Balears | E57: 2022 | F57: illes-balears/2022 | G57: caso-3 | H57: 56 | I57: Named clinical-case section | J57: Named clinical-case section | K57: mandatory_named_case | L57: Yes | M57: Positive / standard | P57: C | Q57: Debe iniciarse inmediatamente un tratamiento enzimático sustitutivo. | R57: illes-balears-2022-base-caso-3, illes-balears-2022-caso-3-transition-01 | T57: 21 | U57: AD_ILLES_BALEARS_2022__EXAM__exam__cuadernillo-de-examen-aparato-digestivo-fea.pdf | V57: AD_ILLES_BALEARS_2022__ANSWER_KEY__answer-key__plantilla-correctora-del-examen.pdf | W57: 6dc2b301527b9f55f8ceeb42df7a8397d45ad495ba5516c211cc702210bcc2e6 | X57: 5a9f446af5d9d6b1b15f4ed388d2fc3cd6b98481cd3545ad9f3882c220a60d8c | Z57: illes-balears-2022-caso-3-transition-01 | AA57: Named case block | AB57: Yes
A58: 55 | B58: 2328 | C58: illes-balears|2022|caso-3|57 | D58: Illes Balears | E58: 2022 | F58: illes-balears/2022 | G58: caso-3 | H58: 57 | I58: Named clinical-case section | J58: Named clinical-case section | K58: mandatory_named_case | L58: Yes | M58: Positive / standard | P58: D | Q58: 50.000 U en desayuno, comida y cena y 25.000 U en los snacks. | R58: illes-balears-2022-base-caso-3, illes-balears-2022-caso-3-transition-01 | T58: 21 | U58: AD_ILLES_BALEARS_2022__EXAM__exam__cuadernillo-de-examen-aparato-digestivo-fea.pdf | V58: AD_ILLES_BALEARS_2022__ANSWER_KEY__answer-key__plantilla-correctora-del-examen.pdf | W58: 4e8cfbfe6f00ae799bb1a5ded98ed50c4d6af64bc5631cdd83869acbde7dc2c6 | X58: 17c449da528e92678601c9d8d04ac5cdd9a684ffd69c2cb362760f9cb773e0cb | Z58: illes-balears-2022-caso-3-transition-01 | AA58: Named case block | AB58: Yes
A59: 56 | B59: 2329 | C59: illes-balears|2022|caso-3|58 | D59: Illes Balears | E59: 2022 | F59: illes-balears/2022 | G59: caso-3 | H59: 58 | I59: Named clinical-case section | J59: Named clinical-case section | K59: mandatory_named_case | L59: Yes | M59: Positive / standard | P59: B | Q59: Aumentar la dosis de enzimas pancreáticas y añadir inhibidores de la bomba de protones al TES. | R59: illes-balears-2022-base-caso-3, illes-balears-2022-caso-3-transition-01 | T59: 21 | U59: AD_ILLES_BALEARS_2022__EXAM__exam__cuadernillo-de-examen-aparato-digestivo-fea.pdf | V59: AD_ILLES_BALEARS_2022__ANSWER_KEY__answer-key__plantilla-correctora-del-examen.pdf | W59: 59767f7202d1ab1665646ec1000a7d87d31e124718bbbde6a6642911152a0f7c | X59: 1b9e58dfa6cba9bd9ee0cf2f2157b96d0f91b538caeb3de87c0c27a4ab434f25 | Z59: illes-balears-2022-caso-3-transition-01 | AA59: Named case block | AB59: Yes
A60: 57 | B60: 2330 | C60: illes-balears|2022|caso-3|59 | D60: Illes Balears | E60: 2022 | F60: illes-balears/2022 | G60: caso-3 | H60: 59 | I60: Named clinical-case section | J60: Named clinical-case section | K60: mandatory_named_case | L60: Yes | M60: Positive / standard | P60: C | Q60: ...presenta más riesgo de sobrecrecimiento bacteriano en el intestino delgado (SIBO). | R60: illes-balears-2022-base-caso-3, illes-balears-2022-caso-3-transition-01 | T60: 22 | U60: AD_ILLES_BALEARS_2022__EXAM__exam__cuadernillo-de-examen-aparato-digestivo-fea.pdf | V60: AD_ILLES_BALEARS_2022__ANSWER_KEY__answer-key__plantilla-correctora-del-examen.pdf | W60: 810244359dfb8efb7b7d54520dd31f0d6a6c080865d45099abf200345c4c3ef4 | X60: aa2f3bd01385fe8c0da9a02055fc5624e382608ba9f8fd0e4dd5ae2d7df66b41 | Z60: illes-balears-2022-caso-3-transition-01 | AA60: Named case block | AB60: Yes
A61: 58 | B61: 2331 | C61: illes-balears|2022|caso-3|60 | D61: Illes Balears | E61: 2022 | F61: illes-balears/2022 | G61: caso-3 | H61: 60 | I61: Named clinical-case section | J61: Named clinical-case section | K61: mandatory_named_case | L61: Yes | M61: Positive / standard | P61: A | Q61: Es suficiente la mejoría sintomática y la normalización de los parámetros nutricionales. | R61: illes-balears-2022-base-caso-3, illes-balears-2022-caso-3-transition-01 | T61: 22 | U61: AD_ILLES_BALEARS_2022__EXAM__exam__cuadernillo-de-examen-aparato-digestivo-fea.pdf | V61: AD_ILLES_BALEARS_2022__ANSWER_KEY__answer-key__plantilla-correctora-del-examen.pdf | W61: 44d312ed41401545eb2b8f9b7dea716d49955318522fad71f3222cb7e82fdcf3 | X61: 778694276926dd86d0aa2cac246187d041e3553120cbc34cce15bdd30d7cff69 | Z61: illes-balears-2022-caso-3-transition-01 | AA61: Named case block | AB61: Yes
A62: 59 | B62: 2332 | C62: illes-balears|2022|caso-3|61 | D62: Illes Balears | E62: 2022 | F62: illes-balears/2022 | G62: caso-3 | H62: 61 | I62: Named clinical-case section | J62: Named clinical-case section | K62: mandatory_named_case | L62: Yes | M62: Positive / standard | P62: B | Q62: No hay una estrategia definida para la detección del cáncer de páncreas en estos pacientes. | R62: illes-balears-2022-base-caso-3, illes-balears-2022-caso-3-transition-01 | T62: 22 | U62: AD_ILLES_BALEARS_2022__EXAM__exam__cuadernillo-de-examen-aparato-digestivo-fea.pdf | V62: AD_ILLES_BALEARS_2022__ANSWER_KEY__answer-key__plantilla-correctora-del-examen.pdf | W62: 5da02bdc165c46df33bf1ad54c8926f7e394dc578d599194751737628fa63326 | X62: 91b958a2693f766efacbb8500056b92c30671369037a92ef3d6f7a44e5fe0478 | Y62: option_d: Codex PDF-source repair: PDF-source repair SRC-009. Source: exams-other-regions-spain-pdfs/illes-balears/2022/exam/exam__cuadernillo-de-examen-aparato-digestivo-fea.pdf, PDF page 22. | Z62: illes-balears-2022-caso-3-transition-01 | AA62: Named case block | AB62: Yes
A63: 60 | B63: 2333 | C63: illes-balears|2022|caso-3|62 | D63: Illes Balears | E63: 2022 | F63: illes-balears/2022 | G63: caso-3 | H63: 62 | I63: Named clinical-case section | J63: Named clinical-case section | K63: mandatory_named_case | L63: Yes | M63: Positive / standard | P63: D | Q63: Todas las respuestas anteriores son correctas. | R63: illes-balears-2022-base-caso-3, illes-balears-2022-caso-3-transition-01, illes-balears-2022-caso-3-transition-02 | T63: 22 | U63: AD_ILLES_BALEARS_2022__EXAM__exam__cuadernillo-de-examen-aparato-digestivo-fea.pdf | V63: AD_ILLES_BALEARS_2022__ANSWER_KEY__answer-key__plantilla-correctora-del-examen.pdf | W63: 5201b8755a0ee723faf60cc3950b036de9d5f3c93694275c4b8beee422fb0857 | X63: 247fac55d7e68a2176e21fcc4fb4f51f13dd5bcf4d82e75a156e8811f8f7a8df | Y63: correct_option_text: Codex PDF-source repair: PDF-source repair SRC-009. Source: exams-other-regions-spain-pdfs/illes-balears/2022/exam/exam__cuadernillo-de-examen-aparato-digestivo-fea.pdf, PDF page 22. | option_d: Codex PDF-source repair: PDF-source repair SRC-009. Source: exams-other-regions-spain-pdfs/illes-balears/2022/exam/exam__cuadernillo-de-examen-aparato-digestivo-fea.pdf, PDF page 22. | Z63: illes-balears-2022-caso-3-transition-02 | AA63: Named case block | AB63: Yes
A64: 61 | B64: 2334 | C64: illes-balears|2022|caso-3|63 | D64: Illes Balears | E64: 2022 | F64: illes-balears/2022 | G64: caso-3 | H64: 63 | I64: Named clinical-case section | J64: Named clinical-case section | K64: mandatory_named_case | L64: Yes | M64: Positive / standard | P64: C | Q64: CPRE con citología de colédoco y colocación de un drenaje biliar de plástico. | R64: illes-balears-2022-base-caso-3, illes-balears-2022-caso-3-transition-01, illes-balears-2022-caso-3-transition-02, illes-balears-2022-caso-3-transition-03 | T64: 23 | U64: AD_ILLES_BALEARS_2022__EXAM__exam__cuadernillo-de-examen-aparato-digestivo-fea.pdf | V64: AD_ILLES_BALEARS_2022__ANSWER_KEY__answer-key__plantilla-correctora-del-examen.pdf | W64: 31cd5f04f9c12d2128b5fe7af216e59819ebd4fd3e687abd4f1d3a1dc60f96a3 | X64: 4a35d17503a64b10673e1f002438fcf8affa1ea10a79bb46c9a84ecbe3a4dbf1 | Z64: illes-balears-2022-caso-3-transition-03 | AA64: Named case block | AB64: Yes
A65: 62 | B65: 2335 | C65: illes-balears|2022|caso-3|64 | D65: Illes Balears | E65: 2022 | F65: illes-balears/2022 | G65: caso-3 | H65: 64 | I65: Named clinical-case section | J65: Named clinical-case section | K65: mandatory_named_case | L65: Yes | M65: Positive / standard | P65: A | Q65: Debe solicitarse una ecoendoscopia con aspiración de aguja fina (PAAF) o fine needle biopsy (FNB) de la lesión. | R65: illes-balears-2022-base-caso-3, illes-balears-2022-caso-3-transition-01, illes-balears-2022-caso-3-transition-02, illes-balears-2022-caso-3-transition-03 | T65: 23 | U65: AD_ILLES_BALEARS_2022__EXAM__exam__cuadernillo-de-examen-aparato-digestivo-fea.pdf | V65: AD_ILLES_BALEARS_2022__ANSWER_KEY__answer-key__plantilla-correctora-del-examen.pdf | W65: 3fe2ccd77a529f7d9720dd9b483a907634084f86fba0c662a1acd3d0ba095419 | X65: ef39bed41c7fce74371888d97c1fab0d09dfdbef6a1f84ef73cc833181c5145c | Z65: illes-balears-2022-caso-3-transition-03 | AA65: Named case block | AB65: Yes
A66: 63 | B66: 2336 | C66: illes-balears|2022|caso-3|65 | D66: Illes Balears | E66: 2022 | F66: illes-balears/2022 | G66: caso-3 | H66: 65 | I66: Named clinical-case section | J66: Named clinical-case section | K66: mandatory_named_case | L66: Yes | M66: Positive / standard | P66: A | Q66: Un patrón heterogéneo predominantemente verde. | R66: illes-balears-2022-base-caso-3, illes-balears-2022-caso-3-transition-01, illes-balears-2022-caso-3-transition-02, illes-balears-2022-caso-3-transition-03 | T66: 23 | U66: AD_ILLES_BALEARS_2022__EXAM__exam__cuadernillo-de-examen-aparato-digestivo-fea.pdf | V66: AD_ILLES_BALEARS_2022__ANSWER_KEY__answer-key__plantilla-correctora-del-examen.pdf | W66: 467e5363fc65bdec6f023d06f60bcaae422e6efbf899d77a7a1bd6bf31469fba | X66: 504bdafe2585b41139d76ae9ba6096defa7baefa1970402c418dad2428a2e4a6 | Z66: illes-balears-2022-caso-3-transition-03 | AA66: Named case block | AB66: Yes
A67: 64 | B67: 2337 | C67: illes-balears|2022|caso-3|66 | D67: Illes Balears | E67: 2022 | F67: illes-balears/2022 | G67: caso-3 | H67: 66 | I67: Named clinical-case section | J67: Named clinical-case section | K67: mandatory_named_case | L67: Yes | M67: Positive / standard | P67: C | Q67: Debe valorarse la resecabilidad de la lesión en base a la afectación vascular arterial y venosa. | R67: illes-balears-2022-base-caso-3, illes-balears-2022-caso-3-transition-01, illes-balears-2022-caso-3-transition-02, illes-balears-2022-caso-3-transition-03 | T67: 24 | U67: AD_ILLES_BALEARS_2022__EXAM__exam__cuadernillo-de-examen-aparato-digestivo-fea.pdf | V67: AD_ILLES_BALEARS_2022__ANSWER_KEY__answer-key__plantilla-correctora-del-examen.pdf | W67: 8fe5f429c28fe4d1880392c82b2f7981c2041ffa2e397decd66e681a03b3f09c | X67: f410ab1c4ad4df3397add050ee7d2f36851df22585aeab8bc66e6e877176017a | Z67: illes-balears-2022-caso-3-transition-03 | AA67: Named case block | AB67: Yes
A68: 65 | B68: 2338 | C68: illes-balears|2022|caso-3|67 | D68: Illes Balears | E68: 2022 | F68: illes-balears/2022 | G68: caso-3 | H68: 67 | I68: Named clinical-case section | J68: Named clinical-case section | K68: mandatory_named_case | L68: Yes | M68: Positive / standard | P68: C | Q68: Localmente avanzado. | R68: illes-balears-2022-base-caso-3, illes-balears-2022-caso-3-transition-01, illes-balears-2022-caso-3-transition-02, illes-balears-2022-caso-3-transition-03 | T68: 24 | U68: AD_ILLES_BALEARS_2022__EXAM__exam__cuadernillo-de-examen-aparato-digestivo-fea.pdf | V68: AD_ILLES_BALEARS_2022__ANSWER_KEY__answer-key__plantilla-correctora-del-examen.pdf | W68: d3bc236d5d06d5ea897ed23ecb79502db4ac639d11c4f405265d9d39e6e8aa7f | X68: c5b6a44ed962302e1a106b13f1672ad44ea3dd66152fde8e707c6e2c8164147a | Z68: illes-balears-2022-caso-3-transition-03 | AA68: Named case block | AB68: Yes
A69: 66 | B69: 2339 | C69: illes-balears|2022|caso-3|68 | D69: Illes Balears | E69: 2022 | F69: illes-balears/2022 | G69: caso-3 | H69: 68 | I69: Named clinical-case section | J69: Named clinical-case section | K69: mandatory_named_case | L69: Yes | M69: Negated / exception | N69: negated | P69: C | Q69: Un 75 % de la población no expresa el antígeno Lewis por lo que los niveles de CA 19-9 no son informativos en estos pacientes. | R69: illes-balears-2022-base-caso-3, illes-balears-2022-caso-3-transition-01, illes-balears-2022-caso-3-transition-02, illes-balears-2022-caso-3-transition-03 | T69: 24 | U69: AD_ILLES_BALEARS_2022__EXAM__exam__cuadernillo-de-examen-aparato-digestivo-fea.pdf | V69: AD_ILLES_BALEARS_2022__ANSWER_KEY__answer-key__plantilla-correctora-del-examen.pdf | W69: 2bf285afd9276cb332d226c0429b23331b0be274c442cffbc49a5af1e3c8db8e | X69: eb2087addd72de009183d5219146be7bb5c1da98a4a74ec8bb0860310b47ee92 | Z69: illes-balears-2022-caso-3-transition-03 | AA69: Named case block | AB69: Yes
A70: 67 | B70: 2340 | C70: illes-balears|2022|caso-3|69 | D70: Illes Balears | E70: 2022 | F70: illes-balears/2022 | G70: caso-3 | H70: 69 | I70: Named clinical-case section | J70: Named clinical-case section | K70: mandatory_named_case | L70: Yes | M70: Positive / standard | P70: D | Q70: Todas las respuestas anteriores son correctas. | R70: illes-balears-2022-base-caso-3, illes-balears-2022-caso-3-transition-01, illes-balears-2022-caso-3-transition-02, illes-balears-2022-caso-3-transition-03 | T70: 25 | U70: AD_ILLES_BALEARS_2022__EXAM__exam__cuadernillo-de-examen-aparato-digestivo-fea.pdf | V70: AD_ILLES_BALEARS_2022__ANSWER_KEY__answer-key__plantilla-correctora-del-examen.pdf | W70: ab0cf31e13f333e72387cd7add52e4414107367a96caf3c6ed1778249af27a99 | X70: f374f3060b5d776d1f3eeff4e6e9935bdd076a3608d174f35f6590c423517291 | Z70: illes-balears-2022-caso-3-transition-03 | AA70: Named case block | AB70: Yes
A71: 68 | B71: 2341 | C71: illes-balears|2022|caso-3|70 | D71: Illes Balears | E71: 2022 | F71: illes-balears/2022 | G71: caso-3 | H71: 70 | I71: Named clinical-case section | J71: Named clinical-case section | K71: mandatory_named_case | L71: Yes | M71: Positive / standard | P71: D | Q71: La gabapentina puede ser útil en el tratamiento del dolor neuropático. | R71: illes-balears-2022-base-caso-3, illes-balears-2022-caso-3-transition-01, illes-balears-2022-caso-3-transition-02, illes-balears-2022-caso-3-transition-03 | T71: 25 | U71: AD_ILLES_BALEARS_2022__EXAM__exam__cuadernillo-de-examen-aparato-digestivo-fea.pdf | V71: AD_ILLES_BALEARS_2022__ANSWER_KEY__answer-key__plantilla-correctora-del-examen.pdf | W71: 5aeae5598bd9525e6e90c88e57dcd6d68cffbc623ba3751baca5cc1599b23f84 | X71: 27122ba592faa03692212085fe78cc86b4fa32244f7a775e1a13c7ec3aeed5d6 | Z71: illes-balears-2022-caso-3-transition-03 | AA71: Named case block | AB71: Yes
A72: 69 | B72: 2342 | C72: illes-balears|2022|caso-3|71 | D72: Illes Balears | E72: 2022 | F72: illes-balears/2022 | G72: caso-3 | H72: 71 | I72: Named clinical-case section | J72: Named clinical-case section | K72: mandatory_named_case | L72: Yes | M72: Negated / exception | N72: negated | P72: C | Q72: Normalmente aparece como una lesión hiperdensa comparada con el parénquima pancreático adyacente. | R72: illes-balears-2022-base-caso-3, illes-balears-2022-caso-3-transition-01, illes-balears-2022-caso-3-transition-02, illes-balears-2022-caso-3-transition-03 | T72: 25 | U72: AD_ILLES_BALEARS_2022__EXAM__exam__cuadernillo-de-examen-aparato-digestivo-fea.pdf | V72: AD_ILLES_BALEARS_2022__ANSWER_KEY__answer-key__plantilla-correctora-del-examen.pdf | W72: a1fe165812b530cb47db1b16dfa652eafb6fe98236f1f26ae92b0b82bc84958f | X72: 6d45e1f46f550cc649eebcc26dd09f62b18c6395cfd517fd9a6c3b6bff4ff563 | Z72: illes-balears-2022-caso-3-transition-03 | AA72: Named case block | AB72: Yes
A73: 70 | B73: 2343 | C73: illes-balears|2022|caso-3|72 | D73: Illes Balears | E73: 2022 | F73: illes-balears/2022 | G73: caso-3 | H73: 72 | I73: Named clinical-case section | J73: Named clinical-case section | K73: mandatory_named_case | L73: Yes | M73: Positive / standard | P73: D | Q73: Todas las respuestas anteriores son ciertas. | R73: illes-balears-2022-base-caso-3, illes-balears-2022-caso-3-transition-01, illes-balears-2022-caso-3-transition-02, illes-balears-2022-caso-3-transition-03 | T73: 25 | U73: AD_ILLES_BALEARS_2022__EXAM__exam__cuadernillo-de-examen-aparato-digestivo-fea.pdf | V73: AD_ILLES_BALEARS_2022__ANSWER_KEY__answer-key__plantilla-correctora-del-examen.pdf | W73: 9e14e32f300073da6569d0d5fb779c83d54cfdf6abe8b60635c95f58f9f3f323 | X73: d3da1b96b55e7c198838fadb17ba6f1133eec78ed899b9c0fa421cb1a49b724c | Z73: illes-balears-2022-caso-3-transition-03 | AA73: Named case block | AB73: Yes
A74: 71 | B74: 2344 | C74: illes-balears|2022|caso-4|73 | D74: Illes Balears | E74: 2022 | F74: illes-balears/2022 | G74: caso-4 | H74: 73 | I74: Named clinical-case section | J74: Named clinical-case section | K74: mandatory_named_case | L74: Yes | M74: Positive / standard | P74: C | Q74: Enfermedad de Crohn. | R74: illes-balears-2022-base-caso-4 | T74: 26 | U74: AD_ILLES_BALEARS_2022__EXAM__exam__cuadernillo-de-examen-aparato-digestivo-fea.pdf | V74: AD_ILLES_BALEARS_2022__ANSWER_KEY__answer-key__plantilla-correctora-del-examen.pdf | W74: 365f4ed89a7337ea6a866836ff14a3f1086cc6065e52a650311acb1b1cdaf200 | X74: 844517d8e79096bc81d4c9adec65f7f437d8b8c8507e64a0cf89aeff37747fc2 | AA74: Named case block | AB74: Yes
A75: 72 | B75: 2345 | C75: illes-balears|2022|caso-4|74 | D75: Illes Balears | E75: 2022 | F75: illes-balears/2022 | G75: caso-4 | H75: 74 | I75: Named clinical-case section | J75: Named clinical-case section | K75: mandatory_named_case | L75: Yes | M75: Positive / standard | P75: D | Q75: Todas las respuestas anteriores son correctas. | R75: illes-balears-2022-base-caso-4 | T75: 26 | U75: AD_ILLES_BALEARS_2022__EXAM__exam__cuadernillo-de-examen-aparato-digestivo-fea.pdf | V75: AD_ILLES_BALEARS_2022__ANSWER_KEY__answer-key__plantilla-correctora-del-examen.pdf | W75: a11ed5baebabfa08dbe725ab97639c5f136d550f135c034980aeb752815f76b8 | X75: f8fbe9262ad2628138348bc31c4d9a3794cbdd03952c982d1176476fa4beb133 | AA75: Named case block | AB75: Yes
A76: 73 | B76: 2346 | C76: illes-balears|2022|caso-4|75 | D76: Illes Balears | E76: 2022 | F76: illes-balears/2022 | G76: caso-4 | H76: 75 | I76: Named clinical-case section | J76: Named clinical-case section | K76: mandatory_named_case | L76: Yes | M76: Negated / exception | N76: negated | P76: D | Q76: En la colitis ulcerosa la inflamación intestinal es transmural. | R76: illes-balears-2022-base-caso-4 | T76: 27 | U76: AD_ILLES_BALEARS_2022__EXAM__exam__cuadernillo-de-examen-aparato-digestivo-fea.pdf | V76: AD_ILLES_BALEARS_2022__ANSWER_KEY__answer-key__plantilla-correctora-del-examen.pdf | W76: 7af41093b0381dab97b5266f5fc930d3a127fc9b52f249bb54029c86eb6fa187 | X76: 4200e8874e49dc33ed50bc0755cd0006fe5382be15cee972ba842f5c3cef04fc | AA76: Named case block | AB76: Yes
A77: 74 | B77: 2347 | C77: illes-balears|2022|caso-4|76 | D77: Illes Balears | E77: 2022 | F77: illes-balears/2022 | G77: caso-4 | H77: 76 | I77: Named clinical-case section | J77: Named clinical-case section | K77: mandatory_named_case | L77: Yes | M77: Positive / standard | P77: A | Q77: Edad. | R77: illes-balears-2022-base-caso-4 | T77: 27 | U77: AD_ILLES_BALEARS_2022__EXAM__exam__cuadernillo-de-examen-aparato-digestivo-fea.pdf | V77: AD_ILLES_BALEARS_2022__ANSWER_KEY__answer-key__plantilla-correctora-del-examen.pdf | W77: 81537d638ef0a72b56472fac7ffe71f61b40ea4612b40bd132fadbc4d5da0afc | X77: c51eff9c5979baa12a62eb2a6cd4d5b372a77090f9cb76f607784d1a91bfd763 | AA77: Named case block | AB77: Yes
A78: 75 | B78: 2348 | C78: illes-balears|2022|caso-4|77 | D78: Illes Balears | E78: 2022 | F78: illes-balears/2022 | G78: caso-4 | H78: 77 | I78: Named clinical-case section | J78: Named clinical-case section | K78: mandatory_named_case | L78: Yes | M78: Positive / standard | P78: D | Q78: Todas las respuestas anteriores son correctas. | R78: illes-balears-2022-base-caso-4 | T78: 27 | U78: AD_ILLES_BALEARS_2022__EXAM__exam__cuadernillo-de-examen-aparato-digestivo-fea.pdf | V78: AD_ILLES_BALEARS_2022__ANSWER_KEY__answer-key__plantilla-correctora-del-examen.pdf | W78: 6b70625b0c1ae161d45a216c515afa0794cb1cd5119d9ff03c54434d42865d60 | X78: f6e445a3edc4b0ee9ef55006a1c04e172ea04ed91ca25396d67f9827a36b2a98 | AA78: Named case block | AB78: Yes
